Workbook

Sheet Закуп
A1: Закуп без НДС | B1: Закуп с НДС | C1: № | D1: Поставщ Произв 0-нет | E1: ✔️ Коробки | F1: Коммент | G1: Тип | H1: Fefco | I1: Профиль В Е | J1: Форма чья? | K1: SKU eng | L1: sale | M1: Ц или М | N1: Каталог | O1: V л знач | P1: V л сайт | Q1: V л прайс | R1: Д | S1: Ш | T1: В | U1: S загот м2 F/Знач (2×(Д+Ш)+60) × (Ш+В+8) | V1: Длинные | W1: Плоские | X1: Наибольшые сторона, мм &emsp; | Y1: Средняя сторона, мм &emsp; | Z1: Наименьшые сторона, мм &emsp; | AA1: Тип коробки &emsp; | AB1: Цена м2 руб без НДС | AC1: Объем, литров для сайта старые
A2: 0.28 | B2: =A2*1.2 -> 0.336 | C2: 2 | D2: У | E2: 230х85х150 | G2: Ч | H2: 0201 | I2: В | J2: х | K2: K1 | N2: =IF(D2="","",IF(LEFT(D2,1)="0",0,1)) -> 1 | O2: =ROUND(R2*S2*T2/1000000,2) -> 2.93 | P2: =IF(O2="","", IF(O2<1,"0,1-0,9 литров", IF(O2<2,"1-1,9 литра", IF(O2<3,"2-2,9 литра", IF(O2<4,"3-3,9 литра", IF(O2<6,"4-5,9 литра",IF(O2<8,"6-7,9 литра",IF(O2<10,"8-9,9 литров",IF(O2<15,"10-14,9 литров",IF(O2<20,"15-19,9 литров",IF(O2<30,"20-29 литров",IF(O2<50,"30-49 литров",IF(O2<60,"50-59 литров",IF(O2<70,"60-69 литров",IF(O2<80,"70-79 литров",IF(O2<90,"80-89 литров",IF(O2<100,"90-99 литров",IF(O2<200,"100-200 литров","200+ литров")))))))))))))))))) -> 2-2,9 литра | Q2: =IF(O2="","",IF(O2<1,"<1 л",IF(O2<=2,"1-2 л",IF(O2<=3,"2-3 л",IF(O2<=5,"3-5 л",IF(O2<=10,"5-10 л",IF(O2<=20,"10-20 л",IF(O2<=50,"20-50 л",IF(O2<=100,"50-100 л","100+ л"))))))))) -> 2-3 л | R2: =IF(E2="","",--LEFT(E2,FIND("х",E2)-1)) -> 230 | S2: =IF(E2="","",--MID(E2,FIND("х",E2)+1,FIND("х",E2,FIND("х",E2)+1)-FIND("х",E2)-1)) -> 85 | T2: =IF(E2="","",--RIGHT(E2,LEN(E2)-FIND("х",E2,FIND("х",E2)+1))) -> 150 | U2: =(2*(R2+S2)+60)*(S2+T2+8)/1000000 -> 0.16767 | V2: =IF(OR(AND(R2>=2*S2,R2>=2*T2),AND(S2>=2*R2,S2>=2*T2),AND(T2>=2*R2,T2>=2*S2)),"Длинные","") | W2: =IF(OR(AND(R2<=S2/2,R2<=T2/2),AND(S2<=R2/2,S2<=T2/2),AND(T2<=R2/2,T2<=S2/2)),"Плоские","") | X2: =IF(LARGE($R2:$T2,1)="","",IF(LARGE($R2:$T2,1)<=99,"10-99 мм",IF(LARGE($R2:$T2,1)<=199,"100-199 мм",IF(LARGE($R2:$T2,1)<=299,"200-299 мм",IF(LARGE($R2:$T2,1)<=399,"300-399 мм",IF(LARGE($R2:$T2,1)<=499,"400-499 мм",IF(LARGE($R2:$T2,1)<=599,"500-599 мм",IF(LARGE($R2:$T2,1)<=699,"600-699 мм",IF(LARGE($R2:$T2,1)<=999,"700-999 мм","1000+ мм"))))))))) -> 200-299 мм | Y2: =IF(LARGE($R2:$T2,2)="","",IF(LARGE($R2:$T2,2)<=99,"10-99 мм",IF(LARGE($R2:$T2,2)<=199,"100-199 мм",IF(LARGE($R2:$T2,2)<=299,"200-299 мм",IF(LARGE($R2:$T2,2)<=399,"300-399 мм",IF(LARGE($R2:$T2,2)<=499,"400-499 мм",IF(LARGE($R2:$T2,2)<=599,"500-599 мм",IF(LARGE($R2:$T2,2)<=699,"600-699 мм",IF(LARGE($R2:$T2,2)<=999,"700-999 мм","1000+ мм"))))))))) -> 100-199 мм | Z2: =IF(SMALL($R2:$T2,1)="","",IF(SMALL($R2:$T2,1)<=99,"10-99 мм",IF(SMALL($R2:$T2,1)<=199,"100-199 мм",IF(SMALL($R2:$T2,1)<=299,"200-299 мм",IF(SMALL($R2:$T2,1)<=399,"300-399 мм",IF(SMALL($R2:$T2,1)<=499,"400-499 мм",IF(SMALL($R2:$T2,1)<=599,"500-599 мм",IF(SMALL($R2:$T2,1)<=699,"600-699 мм",IF(SMALL($R2:$T2,1)<=999,"700-999 мм","1000+ мм"))))))))) -> 10-99 мм | AA2: =IF(G2="","",IF(G2="Л","Лист гофрокартона",IF(G2="КД","Крышка-дно",IF(G2="С","Самосборные",IF(G2="Ч","Четырехклапанные",IF(G2="А","Архивные","Неизвестно")))))) -> Четырехклапанные | AB2: 1.73 | AC2: =IF(O2="","",IF(O2<=1,"0-1 литров",IF(O2<=3,"2-3 литра",IF(O2<=5,"4-5 литра",IF(O2<=7,"6-7 литра",IF(O2<=9,"8-9 литров",IF(O2<=14,"10-14 литров",IF(O2<=19,"15-19 литров",IF(O2<=29,"20-29 литров",IF(O2<=49,"30-49 литров",IF(O2<=59,"50-59 литров",IF(O2<=70,"60-69 литров",IF(O2<=79,"70-79 литров",IF(O2<=89,"80-89 литров",IF(O2<=99,"90-99 литров",IF(O2<=200,"100-200 литров","200+ литров")))))))))))))))) -> 2-3 литра
A3: 0.73 | B3: =A3*1.2 -> 0.876 | C3: 3 | D3: У | E3: 245х245х165 | G3: Ч | H3: 0201 | I3: В | J3: х | K3: K2 | N3: =IF(D3="","",IF(LEFT(D3,1)="0",0,1)) -> 1 | O3: =ROUND(R3*S3*T3/1000000,2) -> 9.9 | P3: =IF(O3="","", IF(O3<1,"0,1-0,9 литров", IF(O3<2,"1-1,9 литра", IF(O3<3,"2-2,9 литра", IF(O3<4,"3-3,9 литра", IF(O3<6,"4-5,9 литра",IF(O3<8,"6-7,9 литра",IF(O3<10,"8-9,9 литров",IF(O3<15,"10-14,9 литров",IF(O3<20,"15-19,9 литров",IF(O3<30,"20-29 литров",IF(O3<50,"30-49 литров",IF(O3<60,"50-59 литров",IF(O3<70,"60-69 литров",IF(O3<80,"70-79 литров",IF(O3<90,"80-89 литров",IF(O3<100,"90-99 литров",IF(O3<200,"100-200 литров","200+ литров")))))))))))))))))) -> 8-9,9 литров | Q3: =IF(O3="","",IF(O3<1,"<1 л",IF(O3<=2,"1-2 л",IF(O3<=3,"2-3 л",IF(O3<=5,"3-5 л",IF(O3<=10,"5-10 л",IF(O3<=20,"10-20 л",IF(O3<=50,"20-50 л",IF(O3<=100,"50-100 л","100+ л"))))))))) -> 5-10 л | R3: =IF(E3="","",--LEFT(E3,FIND("х",E3)-1)) -> 245 | S3: =IF(E3="","",--MID(E3,FIND("х",E3)+1,FIND("х",E3,FIND("х",E3)+1)-FIND("х",E3)-1)) -> 245 | T3: =IF(E3="","",--RIGHT(E3,LEN(E3)-FIND("х",E3,FIND("х",E3)+1))) -> 165 | U3: =(2*(R3+S3)+60)*(S3+T3+8)/1000000 -> 0.43472 | V3: =IF(OR(AND(R3>=2*S3,R3>=2*T3),AND(S3>=2*R3,S3>=2*T3),AND(T3>=2*R3,T3>=2*S3)),"Длинные","") | W3: =IF(OR(AND(R3<=S3/2,R3<=T3/2),AND(S3<=R3/2,S3<=T3/2),AND(T3<=R3/2,T3<=S3/2)),"Плоские","") | X3: =IF(LARGE($R3:$T3,1)="","",IF(LARGE($R3:$T3,1)<=99,"10-99 мм",IF(LARGE($R3:$T3,1)<=199,"100-199 мм",IF(LARGE($R3:$T3,1)<=299,"200-299 мм",IF(LARGE($R3:$T3,1)<=399,"300-399 мм",IF(LARGE($R3:$T3,1)<=499,"400-499 мм",IF(LARGE($R3:$T3,1)<=599,"500-599 мм",IF(LARGE($R3:$T3,1)<=699,"600-699 мм",IF(LARGE($R3:$T3,1)<=999,"700-999 мм","1000+ мм"))))))))) -> 200-299 мм | Y3: =IF(LARGE($R3:$T3,2)="","",IF(LARGE($R3:$T3,2)<=99,"10-99 мм",IF(LARGE($R3:$T3,2)<=199,"100-199 мм",IF(LARGE($R3:$T3,2)<=299,"200-299 мм",IF(LARGE($R3:$T3,2)<=399,"300-399 мм",IF(LARGE($R3:$T3,2)<=499,"400-499 мм",IF(LARGE($R3:$T3,2)<=599,"500-599 мм",IF(LARGE($R3:$T3,2)<=699,"600-699 мм",IF(LARGE($R3:$T3,2)<=999,"700-999 мм","1000+ мм"))))))))) -> 200-299 мм | Z3: =IF(SMALL($R3:$T3,1)="","",IF(SMALL($R3:$T3,1)<=99,"10-99 мм",IF(SMALL($R3:$T3,1)<=199,"100-199 мм",IF(SMALL($R3:$T3,1)<=299,"200-299 мм",IF(SMALL($R3:$T3,1)<=399,"300-399 мм",IF(SMALL($R3:$T3,1)<=499,"400-499 мм",IF(SMALL($R3:$T3,1)<=599,"500-599 мм",IF(SMALL($R3:$T3,1)<=699,"600-699 мм",IF(SMALL($R3:$T3,1)<=999,"700-999 мм","1000+ мм"))))))))) -> 100-199 мм | AA3: =IF(G3="","",IF(G3="Л","Лист гофрокартона",IF(G3="КД","Крышка-дно",IF(G3="С","Самосборные",IF(G3="Ч","Четырехклапанные",IF(G3="А","Архивные","Неизвестно")))))) -> Четырехклапанные | AB3: 1.73 | AC3: =IF(O3="","",IF(O3<=1,"0-1 литров",IF(O3<=3,"2-3 литра",IF(O3<=5,"4-5 литра",IF(O3<=7,"6-7 литра",IF(O3<=9,"8-9 литров",IF(O3<=14,"10-14 литров",IF(O3<=19,"15-19 литров",IF(O3<=29,"20-29 литров",IF(O3<=49,"30-49 литров",IF(O3<=59,"50-59 литров",IF(O3<=70,"60-69 литров",IF(O3<=79,"70-79 литров",IF(O3<=89,"80-89 литров",IF(O3<=99,"90-99 литров",IF(O3<=200,"100-200 литров","200+ литров")))))))))))))))) -> 10-14 литров
A4: 0.51 | B4: =A4*1.2 -> 0.612 | C4: 4 | D4: У | E4: 380х160х100 | G4: Ч | H4: 0201 | I4: В | J4: х | K4: K3 | N4: =IF(D4="","",IF(LEFT(D4,1)="0",0,1)) -> 1 | O4: =ROUND(R4*S4*T4/1000000,2) -> 6.08 | P4: =IF(O4="","", IF(O4<1,"0,1-0,9 литров", IF(O4<2,"1-1,9 литра", IF(O4<3,"2-2,9 литра", IF(O4<4,"3-3,9 литра", IF(O4<6,"4-5,9 литра",IF(O4<8,"6-7,9 литра",IF(O4<10,"8-9,9 литров",IF(O4<15,"10-14,9 литров",IF(O4<20,"15-19,9 литров",IF(O4<30,"20-29 литров",IF(O4<50,"30-49 литров",IF(O4<60,"50-59 литров",IF(O4<70,"60-69 литров",IF(O4<80,"70-79 литров",IF(O4<90,"80-89 литров",IF(O4<100,"90-99 литров",IF(O4<200,"100-200 литров","200+ литров")))))))))))))))))) -> 6-7,9 литра | Q4: =IF(O4="","",IF(O4<1,"<1 л",IF(O4<=2,"1-2 л",IF(O4<=3,"2-3 л",IF(O4<=5,"3-5 л",IF(O4<=10,"5-10 л",IF(O4<=20,"10-20 л",IF(O4<=50,"20-50 л",IF(O4<=100,"50-100 л","100+ л"))))))))) -> 5-10 л | R4: =IF(E4="","",--LEFT(E4,FIND("х",E4)-1)) -> 380 | S4: =IF(E4="","",--MID(E4,FIND("х",E4)+1,FIND("х",E4,FIND("х",E4)+1)-FIND("х",E4)-1)) -> 160 | T4: =IF(E4="","",--RIGHT(E4,LEN(E4)-FIND("х",E4,FIND("х",E4)+1))) -> 100 | U4: =(2*(R4+S4)+60)*(S4+T4+8)/1000000 -> 0.30552 | V4: =IF(OR(AND(R4>=2*S4,R4>=2*T4),AND(S4>=2*R4,S4>=2*T4),AND(T4>=2*R4,T4>=2*S4)),"Длинные","") -> Длинные | W4: =IF(OR(AND(R4<=S4/2,R4<=T4/2),AND(S4<=R4/2,S4<=T4/2),AND(T4<=R4/2,T4<=S4/2)),"Плоские","") | X4: =IF(LARGE($R4:$T4,1)="","",IF(LARGE($R4:$T4,1)<=99,"10-99 мм",IF(LARGE($R4:$T4,1)<=199,"100-199 мм",IF(LARGE($R4:$T4,1)<=299,"200-299 мм",IF(LARGE($R4:$T4,1)<=399,"300-399 мм",IF(LARGE($R4:$T4,1)<=499,"400-499 мм",IF(LARGE($R4:$T4,1)<=599,"500-599 мм",IF(LARGE($R4:$T4,1)<=699,"600-699 мм",IF(LARGE($R4:$T4,1)<=999,"700-999 мм","1000+ мм"))))))))) -> 300-399 мм | Y4: =IF(LARGE($R4:$T4,2)="","",IF(LARGE($R4:$T4,2)<=99,"10-99 мм",IF(LARGE($R4:$T4,2)<=199,"100-199 мм",IF(LARGE($R4:$T4,2)<=299,"200-299 мм",IF(LARGE($R4:$T4,2)<=399,"300-399 мм",IF(LARGE($R4:$T4,2)<=499,"400-499 мм",IF(LARGE($R4:$T4,2)<=599,"500-599 мм",IF(LARGE($R4:$T4,2)<=699,"600-699 мм",IF(LARGE($R4:$T4,2)<=999,"700-999 мм","1000+ мм"))))))))) -> 100-199 мм | Z4: =IF(SMALL($R4:$T4,1)="","",IF(SMALL($R4:$T4,1)<=99,"10-99 мм",IF(SMALL($R4:$T4,1)<=199,"100-199 мм",IF(SMALL($R4:$T4,1)<=299,"200-299 мм",IF(SMALL($R4:$T4,1)<=399,"300-399 мм",IF(SMALL($R4:$T4,1)<=499,"400-499 мм",IF(SMALL($R4:$T4,1)<=599,"500-599 мм",IF(SMALL($R4:$T4,1)<=699,"600-699 мм",IF(SMALL($R4:$T4,1)<=999,"700-999 мм","1000+ мм"))))))))) -> 100-199 мм | AA4: =IF(G4="","",IF(G4="Л","Лист гофрокартона",IF(G4="КД","Крышка-дно",IF(G4="С","Самосборные",IF(G4="Ч","Четырехклапанные",IF(G4="А","Архивные","Неизвестно")))))) -> Четырехклапанные | AB4: 1.73 | AC4: =IF(O4="","",IF(O4<=1,"0-1 литров",IF(O4<=3,"2-3 литра",IF(O4<=5,"4-5 литра",IF(O4<=7,"6-7 литра",IF(O4<=9,"8-9 литров",IF(O4<=14,"10-14 литров",IF(O4<=19,"15-19 литров",IF(O4<=29,"20-29 литров",IF(O4<=49,"30-49 литров",IF(O4<=59,"50-59 литров",IF(O4<=70,"60-69 литров",IF(O4<=79,"70-79 литров",IF(O4<=89,"80-89 литров",IF(O4<=99,"90-99 литров",IF(O4<=200,"100-200 литров","200+ литров")))))))))))))))) -> 6-7 литра
A5: 2.48 | B5: =A5*1.2 -> 2.976 | C5: 5 | D5: У | E5: 460х410х390 | G5: Ч | H5: 0201 | I5: В | J5: х | K5: K4 | N5: =IF(D5="","",IF(LEFT(D5,1)="0",0,1)) -> 1 | O5: =ROUND(R5*S5*T5/1000000,2) -> 73.55 | P5: =IF(O5="","", IF(O5<1,"0,1-0,9 литров", IF(O5<2,"1-1,9 литра", IF(O5<3,"2-2,9 литра", IF(O5<4,"3-3,9 литра", IF(O5<6,"4-5,9 литра",IF(O5<8,"6-7,9 литра",IF(O5<10,"8-9,9 литров",IF(O5<15,"10-14,9 литров",IF(O5<20,"15-19,9 литров",IF(O5<30,"20-29 литров",IF(O5<50,"30-49 литров",IF(O5<60,"50-59 литров",IF(O5<70,"60-69 литров",IF(O5<80,"70-79 литров",IF(O5<90,"80-89 литров",IF(O5<100,"90-99 литров",IF(O5<200,"100-200 литров","200+ литров")))))))))))))))))) -> 70-79 литров | Q5: =IF(O5="","",IF(O5<1,"<1 л",IF(O5<=2,"1-2 л",IF(O5<=3,"2-3 л",IF(O5<=5,"3-5 л",IF(O5<=10,"5-10 л",IF(O5<=20,"10-20 л",IF(O5<=50,"20-50 л",IF(O5<=100,"50-100 л","100+ л"))))))))) -> 50-100 л | R5: =IF(E5="","",--LEFT(E5,FIND("х",E5)-1)) -> 460 | S5: =IF(E5="","",--MID(E5,FIND("х",E5)+1,FIND("х",E5,FIND("х",E5)+1)-FIND("х",E5)-1)) -> 410 | T5: =IF(E5="","",--RIGHT(E5,LEN(E5)-FIND("х",E5,FIND("х",E5)+1))) -> 390 | U5: =(2*(R5+S5)+60)*(S5+T5+8)/1000000 -> 1.4544 | V5: =IF(OR(AND(R5>=2*S5,R5>=2*T5),AND(S5>=2*R5,S5>=2*T5),AND(T5>=2*R5,T5>=2*S5)),"Длинные","") | W5: =IF(OR(AND(R5<=S5/2,R5<=T5/2),AND(S5<=R5/2,S5<=T5/2),AND(T5<=R5/2,T5<=S5/2)),"Плоские","") | X5: =IF(LARGE($R5:$T5,1)="","",IF(LARGE($R5:$T5,1)<=99,"10-99 мм",IF(LARGE($R5:$T5,1)<=199,"100-199 мм",IF(LARGE($R5:$T5,1)<=299,"200-299 мм",IF(LARGE($R5:$T5,1)<=399,"300-399 мм",IF(LARGE($R5:$T5,1)<=499,"400-499 мм",IF(LARGE($R5:$T5,1)<=599,"500-599 мм",IF(LARGE($R5:$T5,1)<=699,"600-699 мм",IF(LARGE($R5:$T5,1)<=999,"700-999 мм","1000+ мм"))))))))) -> 400-499 мм | Y5: =IF(LARGE($R5:$T5,2)="","",IF(LARGE($R5:$T5,2)<=99,"10-99 мм",IF(LARGE($R5:$T5,2)<=199,"100-199 мм",IF(LARGE($R5:$T5,2)<=299,"200-299 мм",IF(LARGE($R5:$T5,2)<=399,"300-399 мм",IF(LARGE($R5:$T5,2)<=499,"400-499 мм",IF(LARGE($R5:$T5,2)<=599,"500-599 мм",IF(LARGE($R5:$T5,2)<=699,"600-699 мм",IF(LARGE($R5:$T5,2)<=999,"700-999 мм","1000+ мм"))))))))) -> 400-499 мм | Z5: =IF(SMALL($R5:$T5,1)="","",IF(SMALL($R5:$T5,1)<=99,"10-99 мм",IF(SMALL($R5:$T5,1)<=199,"100-199 мм",IF(SMALL($R5:$T5,1)<=299,"200-299 мм",IF(SMALL($R5:$T5,1)<=399,"300-399 мм",IF(SMALL($R5:$T5,1)<=499,"400-499 мм",IF(SMALL($R5:$T5,1)<=599,"500-599 мм",IF(SMALL($R5:$T5,1)<=699,"600-699 мм",IF(SMALL($R5:$T5,1)<=999,"700-999 мм","1000+ мм"))))))))) -> 300-399 мм | AA5: =IF(G5="","",IF(G5="Л","Лист гофрокартона",IF(G5="КД","Крышка-дно",IF(G5="С","Самосборные",IF(G5="Ч","Четырехклапанные",IF(G5="А","Архивные","Неизвестно")))))) -> Четырехклапанные | AB5: 1.73 | AC5: =IF(O5="","",IF(O5<=1,"0-1 литров",IF(O5<=3,"2-3 литра",IF(O5<=5,"4-5 литра",IF(O5<=7,"6-7 литра",IF(O5<=9,"8-9 литров",IF(O5<=14,"10-14 литров",IF(O5<=19,"15-19 литров",IF(O5<=29,"20-29 литров",IF(O5<=49,"30-49 литров",IF(O5<=59,"50-59 литров",IF(O5<=70,"60-69 литров",IF(O5<=79,"70-79 литров",IF(O5<=89,"80-89 литров",IF(O5<=99,"90-99 литров",IF(O5<=200,"100-200 литров","200+ литров")))))))))))))))) -> 70-79 литров
A6: 2.2 | B6: =A6*1.2 -> 2.64 | C6: 6 | D6: У | E6: 460х310х490 | G6: Ч | H6: 0201 | I6: В | J6: х | K6: K5 | N6: =IF(D6="","",IF(LEFT(D6,1)="0",0,1)) -> 1 | O6: =ROUND(R6*S6*T6/1000000,2) -> 69.87 | P6: =IF(O6="","", IF(O6<1,"0,1-0,9 литров", IF(O6<2,"1-1,9 литра", IF(O6<3,"2-2,9 литра", IF(O6<4,"3-3,9 литра", IF(O6<6,"4-5,9 литра",IF(O6<8,"6-7,9 литра",IF(O6<10,"8-9,9 литров",IF(O6<15,"10-14,9 литров",IF(O6<20,"15-19,9 литров",IF(O6<30,"20-29 литров",IF(O6<50,"30-49 литров",IF(O6<60,"50-59 литров",IF(O6<70,"60-69 литров",IF(O6<80,"70-79 литров",IF(O6<90,"80-89 литров",IF(O6<100,"90-99 литров",IF(O6<200,"100-200 литров","200+ литров")))))))))))))))))) -> 60-69 литров | Q6: =IF(O6="","",IF(O6<1,"<1 л",IF(O6<=2,"1-2 л",IF(O6<=3,"2-3 л",IF(O6<=5,"3-5 л",IF(O6<=10,"5-10 л",IF(O6<=20,"10-20 л",IF(O6<=50,"20-50 л",IF(O6<=100,"50-100 л","100+ л"))))))))) -> 50-100 л | R6: =IF(E6="","",--LEFT(E6,FIND("х",E6)-1)) -> 460 | S6: =IF(E6="","",--MID(E6,FIND("х",E6)+1,FIND("х",E6,FIND("х",E6)+1)-FIND("х",E6)-1)) -> 310 | T6: =IF(E6="","",--RIGHT(E6,LEN(E6)-FIND("х",E6,FIND("х",E6)+1))) -> 490 | U6: =(2*(R6+S6)+60)*(S6+T6+8)/1000000 -> 1.2928 | V6: =IF(OR(AND(R6>=2*S6,R6>=2*T6),AND(S6>=2*R6,S6>=2*T6),AND(T6>=2*R6,T6>=2*S6)),"Длинные","") | W6: =IF(OR(AND(R6<=S6/2,R6<=T6/2),AND(S6<=R6/2,S6<=T6/2),AND(T6<=R6/2,T6<=S6/2)),"Плоские","") | X6: =IF(LARGE($R6:$T6,1)="","",IF(LARGE($R6:$T6,1)<=99,"10-99 мм",IF(LARGE($R6:$T6,1)<=199,"100-199 мм",IF(LARGE($R6:$T6,1)<=299,"200-299 мм",IF(LARGE($R6:$T6,1)<=399,"300-399 мм",IF(LARGE($R6:$T6,1)<=499,"400-499 мм",IF(LARGE($R6:$T6,1)<=599,"500-599 мм",IF(LARGE($R6:$T6,1)<=699,"600-699 мм",IF(LARGE($R6:$T6,1)<=999,"700-999 мм","1000+ мм"))))))))) -> 400-499 мм | Y6: =IF(LARGE($R6:$T6,2)="","",IF(LARGE($R6:$T6,2)<=99,"10-99 мм",IF(LARGE($R6:$T6,2)<=199,"100-199 мм",IF(LARGE($R6:$T6,2)<=299,"200-299 мм",IF(LARGE($R6:$T6,2)<=399,"300-399 мм",IF(LARGE($R6:$T6,2)<=499,"400-499 мм",IF(LARGE($R6:$T6,2)<=599,"500-599 мм",IF(LARGE($R6:$T6,2)<=699,"600-699 мм",IF(LARGE($R6:$T6,2)<=999,"700-999 мм","1000+ мм"))))))))) -> 400-499 мм | Z6: =IF(SMALL($R6:$T6,1)="","",IF(SMALL($R6:$T6,1)<=99,"10-99 мм",IF(SMALL($R6:$T6,1)<=199,"100-199 мм",IF(SMALL($R6:$T6,1)<=299,"200-299 мм",IF(SMALL($R6:$T6,1)<=399,"300-399 мм",IF(SMALL($R6:$T6,1)<=499,"400-499 мм",IF(SMALL($R6:$T6,1)<=599,"500-599 мм",IF(SMALL($R6:$T6,1)<=699,"600-699 мм",IF(SMALL($R6:$T6,1)<=999,"700-999 мм","1000+ мм"))))))))) -> 300-399 мм | AA6: =IF(G6="","",IF(G6="Л","Лист гофрокартона",IF(G6="КД","Крышка-дно",IF(G6="С","Самосборные",IF(G6="Ч","Четырехклапанные",IF(G6="А","Архивные","Неизвестно")))))) -> Четырехклапанные | AB6: 1.73 | AC6: =IF(O6="","",IF(O6<=1,"0-1 литров",IF(O6<=3,"2-3 литра",IF(O6<=5,"4-5 литра",IF(O6<=7,"6-7 литра",IF(O6<=9,"8-9 литров",IF(O6<=14,"10-14 литров",IF(O6<=19,"15-19 литров",IF(O6<=29,"20-29 литров",IF(O6<=49,"30-49 литров",IF(O6<=59,"50-59 литров",IF(O6<=70,"60-69 литров",IF(O6<=79,"70-79 литров",IF(O6<=89,"80-89 литров",IF(O6<=99,"90-99 литров",IF(O6<=200,"100-200 литров","200+ литров")))))))))))))))) -> 60-69 литров
A7: 3.05 | B7: =A7*1.2 -> 3.66 | C7: 7 | D7: У | E7: 585х385х500 | G7: Ч | H7: 0201 | I7: В | J7: х | K7: K6 | N7: =IF(D7="","",IF(LEFT(D7,1)="0",0,1)) -> 1 | O7: =ROUND(R7*S7*T7/1000000,2) -> 112.61 | P7: =IF(O7="","", IF(O7<1,"0,1-0,9 литров", IF(O7<2,"1-1,9 литра", IF(O7<3,"2-2,9 литра", IF(O7<4,"3-3,9 литра", IF(O7<6,"4-5,9 литра",IF(O7<8,"6-7,9 литра",IF(O7<10,"8-9,9 литров",IF(O7<15,"10-14,9 литров",IF(O7<20,"15-19,9 литров",IF(O7<30,"20-29 литров",IF(O7<50,"30-49 литров",IF(O7<60,"50-59 литров",IF(O7<70,"60-69 литров",IF(O7<80,"70-79 литров",IF(O7<90,"80-89 литров",IF(O7<100,"90-99 литров",IF(O7<200,"100-200 литров","200+ литров")))))))))))))))))) -> 100-200 литров | Q7: =IF(O7="","",IF(O7<1,"<1 л",IF(O7<=2,"1-2 л",IF(O7<=3,"2-3 л",IF(O7<=5,"3-5 л",IF(O7<=10,"5-10 л",IF(O7<=20,"10-20 л",IF(O7<=50,"20-50 л",IF(O7<=100,"50-100 л","100+ л"))))))))) -> 100+ л | R7: =IF(E7="","",--LEFT(E7,FIND("х",E7)-1)) -> 585 | S7: =IF(E7="","",--MID(E7,FIND("х",E7)+1,FIND("х",E7,FIND("х",E7)+1)-FIND("х",E7)-1)) -> 385 | T7: =IF(E7="","",--RIGHT(E7,LEN(E7)-FIND("х",E7,FIND("х",E7)+1))) -> 500 | U7: =(2*(R7+S7)+60)*(S7+T7+8)/1000000 -> 1.786 | V7: =IF(OR(AND(R7>=2*S7,R7>=2*T7),AND(S7>=2*R7,S7>=2*T7),AND(T7>=2*R7,T7>=2*S7)),"Длинные","") | W7: =IF(OR(AND(R7<=S7/2,R7<=T7/2),AND(S7<=R7/2,S7<=T7/2),AND(T7<=R7/2,T7<=S7/2)),"Плоские","") | X7: =IF(LARGE($R7:$T7,1)="","",IF(LARGE($R7:$T7,1)<=99,"10-99 мм",IF(LARGE($R7:$T7,1)<=199,"100-199 мм",IF(LARGE($R7:$T7,1)<=299,"200-299 мм",IF(LARGE($R7:$T7,1)<=399,"300-399 мм",IF(LARGE($R7:$T7,1)<=499,"400-499 мм",IF(LARGE($R7:$T7,1)<=599,"500-599 мм",IF(LARGE($R7:$T7,1)<=699,"600-699 мм",IF(LARGE($R7:$T7,1)<=999,"700-999 мм","1000+ мм"))))))))) -> 500-599 мм | Y7: =IF(LARGE($R7:$T7,2)="","",IF(LARGE($R7:$T7,2)<=99,"10-99 мм",IF(LARGE($R7:$T7,2)<=199,"100-199 мм",IF(LARGE($R7:$T7,2)<=299,"200-299 мм",IF(LARGE($R7:$T7,2)<=399,"300-399 мм",IF(LARGE($R7:$T7,2)<=499,"400-499 мм",IF(LARGE($R7:$T7,2)<=599,"500-599 мм",IF(LARGE($R7:$T7,2)<=699,"600-699 мм",IF(LARGE($R7:$T7,2)<=999,"700-999 мм","1000+ мм"))))))))) -> 500-599 мм | Z7: =IF(SMALL($R7:$T7,1)="","",IF(SMALL($R7:$T7,1)<=99,"10-99 мм",IF(SMALL($R7:$T7,1)<=199,"100-199 мм",IF(SMALL($R7:$T7,1)<=299,"200-299 мм",IF(SMALL($R7:$T7,1)<=399,"300-399 мм",IF(SMALL($R7:$T7,1)<=499,"400-499 мм",IF(SMALL($R7:$T7,1)<=599,"500-599 мм",IF(SMALL($R7:$T7,1)<=699,"600-699 мм",IF(SMALL($R7:$T7,1)<=999,"700-999 мм","1000+ мм"))))))))) -> 300-399 мм | AA7: =IF(G7="","",IF(G7="Л","Лист гофрокартона",IF(G7="КД","Крышка-дно",IF(G7="С","Самосборные",IF(G7="Ч","Четырехклапанные",IF(G7="А","Архивные","Неизвестно")))))) -> Четырехклапанные | AB7: 1.73 | AC7: =IF(O7="","",IF(O7<=1,"0-1 литров",IF(O7<=3,"2-3 литра",IF(O7<=5,"4-5 литра",IF(O7<=7,"6-7 литра",IF(O7<=9,"8-9 литров",IF(O7<=14,"10-14 литров",IF(O7<=19,"15-19 литров",IF(O7<=29,"20-29 литров",IF(O7<=49,"30-49 литров",IF(O7<=59,"50-59 литров",IF(O7<=70,"60-69 литров",IF(O7<=79,"70-79 литров",IF(O7<=89,"80-89 литров",IF(O7<=99,"90-99 литров",IF(O7<=200,"100-200 литров","200+ литров")))))))))))))))) -> 100-200 литров
A8: 1.3 | B8: =A8*1.2 -> 1.56 | C8: 8 | D8: У | E8: 280х220х500 | G8: Ч | H8: 0201 | I8: В | J8: х | K8: K7 | N8: =IF(D8="","",IF(LEFT(D8,1)="0",0,1)) -> 1 | O8: =ROUND(R8*S8*T8/1000000,2) -> 30.8 | P8: =IF(O8="","", IF(O8<1,"0,1-0,9 литров", IF(O8<2,"1-1,9 литра", IF(O8<3,"2-2,9 литра", IF(O8<4,"3-3,9 литра", IF(O8<6,"4-5,9 литра",IF(O8<8,"6-7,9 литра",IF(O8<10,"8-9,9 литров",IF(O8<15,"10-14,9 литров",IF(O8<20,"15-19,9 литров",IF(O8<30,"20-29 литров",IF(O8<50,"30-49 литров",IF(O8<60,"50-59 литров",IF(O8<70,"60-69 литров",IF(O8<80,"70-79 литров",IF(O8<90,"80-89 литров",IF(O8<100,"90-99 литров",IF(O8<200,"100-200 литров","200+ литров")))))))))))))))))) -> 30-49 литров | Q8: =IF(O8="","",IF(O8<1,"<1 л",IF(O8<2,"1-2 л",IF(O8<3,"2-3 л",IF(O8<5,"3-5 л",IF(O8<10,"5-10 л",IF(O8<20,"10-20 л",IF(O8<50,"20-50 л",IF(O8<100,"50-100 л","100+ л"))))))))) -> 20-50 л | R8: =IF(E8="","",--LEFT(E8,FIND("х",E8)-1)) -> 280 | S8: =IF(E8="","",--MID(E8,FIND("х",E8)+1,FIND("х",E8,FIND("х",E8)+1)-FIND("х",E8)-1)) -> 220 | T8: =IF(E8="","",--RIGHT(E8,LEN(E8)-FIND("х",E8,FIND("х",E8)+1))) -> 500 | U8: =(2*(R8+S8)+60)*(S8+T8+8)/1000000 -> 0.77168 | V8: =IF(OR(AND(R8>=2*S8,R8>=2*T8),AND(S8>=2*R8,S8>=2*T8),AND(T8>=2*R8,T8>=2*S8)),"Длинные","") | W8: =IF(OR(AND(R8<=S8/2,R8<=T8/2),AND(S8<=R8/2,S8<=T8/2),AND(T8<=R8/2,T8<=S8/2)),"Плоские","") | X8: =IF(LARGE($R8:$T8,1)="","",IF(LARGE($R8:$T8,1)<=99,"10-99 мм",IF(LARGE($R8:$T8,1)<=199,"100-199 мм",IF(LARGE($R8:$T8,1)<=299,"200-299 мм",IF(LARGE($R8:$T8,1)<=399,"300-399 мм",IF(LARGE($R8:$T8,1)<=499,"400-499 мм",IF(LARGE($R8:$T8,1)<=599,"500-599 мм",IF(LARGE($R8:$T8,1)<=699,"600-699 мм",IF(LARGE($R8:$T8,1)<=999,"700-999 мм","1000+ мм"))))))))) -> 500-599 мм | Y8: =IF(LARGE($R8:$T8,2)="","",IF(LARGE($R8:$T8,2)<=99,"10-99 мм",IF(LARGE($R8:$T8,2)<=199,"100-199 мм",IF(LARGE($R8:$T8,2)<=299,"200-299 мм",IF(LARGE($R8:$T8,2)<=399,"300-399 мм",IF(LARGE($R8:$T8,2)<=499,"400-499 мм",IF(LARGE($R8:$T8,2)<=599,"500-599 мм",IF(LARGE($R8:$T8,2)<=699,"600-699 мм",IF(LARGE($R8:$T8,2)<=999,"700-999 мм","1000+ мм"))))))))) -> 200-299 мм | Z8: =IF(SMALL($R8:$T8,1)="","",IF(SMALL($R8:$T8,1)<=99,"10-99 мм",IF(SMALL($R8:$T8,1)<=199,"100-199 мм",IF(SMALL($R8:$T8,1)<=299,"200-299 мм",IF(SMALL($R8:$T8,1)<=399,"300-399 мм",IF(SMALL($R8:$T8,1)<=499,"400-499 мм",IF(SMALL($R8:$T8,1)<=599,"500-599 мм",IF(SMALL($R8:$T8,1)<=699,"600-699 мм",IF(SMALL($R8:$T8,1)<=999,"700-999 мм","1000+ мм"))))))))) -> 200-299 мм | AA8: =IF(G8="","",IF(G8="Л","Лист гофрокартона",IF(G8="КД","Крышка-дно",IF(G8="С","Самосборные",IF(G8="Ч","Четырехклапанные",IF(G8="А","Архивные","Неизвестно")))))) -> Четырехклапанные | AB8: 1.73 | AC8: =IF(O8="","",IF(O8<=1,"0-1 литров",IF(O8<=3,"2-3 литра",IF(O8<=5,"4-5 литра",IF(O8<=7,"6-7 литра",IF(O8<=9,"8-9 литров",IF(O8<=14,"10-14 литров",IF(O8<=19,"15-19 литров",IF(O8<=29,"20-29 литров",IF(O8<=49,"30-49 литров",IF(O8<=59,"50-59 литров",IF(O8<=70,"60-69 литров",IF(O8<=79,"70-79 литров",IF(O8<=89,"80-89 литров",IF(O8<=99,"90-99 литров",IF(O8<=200,"100-200 литров","200+ литров")))))))))))))))) -> 30-49 литров
A9: 1.25 | B9: =A9*1.2 -> 1.5 | C9: 9 | D9: У | E9: 405х55х605 | F9: 605х55х405 | G9: Ч | H9: 0215 | I9: В | J9: х | K9: K8 | N9: =IF(D9="","",IF(LEFT(D9,1)="0",0,1)) -> 1 | O9: =ROUND(R9*S9*T9/1000000,2) -> 13.48 | P9: =IF(O9="","", IF(O9<1,"0,1-0,9 литров", IF(O9<2,"1-1,9 литра", IF(O9<3,"2-2,9 литра", IF(O9<4,"3-3,9 литра", IF(O9<6,"4-5,9 литра",IF(O9<8,"6-7,9 литра",IF(O9<10,"8-9,9 литров",IF(O9<15,"10-14,9 литров",IF(O9<20,"15-19,9 литров",IF(O9<30,"20-29 литров",IF(O9<50,"30-49 литров",IF(O9<60,"50-59 литров",IF(O9<70,"60-69 литров",IF(O9<80,"70-79 литров",IF(O9<90,"80-89 литров",IF(O9<100,"90-99 литров",IF(O9<200,"100-200 литров","200+ литров")))))))))))))))))) -> 10-14,9 литров | Q9: =IF(O9="","",IF(O9<1,"<1 л",IF(O9<2,"1-2 л",IF(O9<3,"2-3 л",IF(O9<5,"3-5 л",IF(O9<10,"5-10 л",IF(O9<20,"10-20 л",IF(O9<50,"20-50 л",IF(O9<100,"50-100 л","100+ л"))))))))) -> 10-20 л | R9: =IF(E9="","",--LEFT(E9,FIND("х",E9)-1)) -> 405 | S9: =IF(E9="","",--MID(E9,FIND("х",E9)+1,FIND("х",E9,FIND("х",E9)+1)-FIND("х",E9)-1)) -> 55 | T9: =IF(E9="","",--RIGHT(E9,LEN(E9)-FIND("х",E9,FIND("х",E9)+1))) -> 605 | U9: =(2*(R9+S9)+60)*(S9+T9+8)/1000000 -> 0.65464 | V9: =IF(OR(AND(R9>=2*S9,R9>=2*T9),AND(S9>=2*R9,S9>=2*T9),AND(T9>=2*R9,T9>=2*S9)),"Длинные","") | W9: =IF(OR(AND(R9<=S9/2,R9<=T9/2),AND(S9<=R9/2,S9<=T9/2),AND(T9<=R9/2,T9<=S9/2)),"Плоские","") -> Плоские | X9: =IF(LARGE($R9:$T9,1)="","",IF(LARGE($R9:$T9,1)<=99,"10-99 мм",IF(LARGE($R9:$T9,1)<=199,"100-199 мм",IF(LARGE($R9:$T9,1)<=299,"200-299 мм",IF(LARGE($R9:$T9,1)<=399,"300-399 мм",IF(LARGE($R9:$T9,1)<=499,"400-499 мм",IF(LARGE($R9:$T9,1)<=599,"500-599 мм",IF(LARGE($R9:$T9,1)<=699,"600-699 мм",IF(LARGE($R9:$T9,1)<=999,"700-999 мм","1000+ мм"))))))))) -> 600-699 мм | Y9: =IF(LARGE($R9:$T9,2)="","",IF(LARGE($R9:$T9,2)<=99,"10-99 мм",IF(LARGE($R9:$T9,2)<=199,"100-199 мм",IF(LARGE($R9:$T9,2)<=299,"200-299 мм",IF(LARGE($R9:$T9,2)<=399,"300-399 мм",IF(LARGE($R9:$T9,2)<=499,"400-499 мм",IF(LARGE($R9:$T9,2)<=599,"500-599 мм",IF(LARGE($R9:$T9,2)<=699,"600-699 мм",IF(LARGE($R9:$T9,2)<=999,"700-999 мм","1000+ мм"))))))))) -> 400-499 мм | Z9: =IF(SMALL($R9:$T9,1)="","",IF(SMALL($R9:$T9,1)<=99,"10-99 мм",IF(SMALL($R9:$T9,1)<=199,"100-199 мм",IF(SMALL($R9:$T9,1)<=299,"200-299 мм",IF(SMALL($R9:$T9,1)<=399,"300-399 мм",IF(SMALL($R9:$T9,1)<=499,"400-499 мм",IF(SMALL($R9:$T9,1)<=599,"500-599 мм",IF(SMALL($R9:$T9,1)<=699,"600-699 мм",IF(SMALL($R9:$T9,1)<=999,"700-999 мм","1000+ мм"))))))))) -> 10-99 мм | AA9: =IF(G9="","",IF(G9="Л","Лист гофрокартона",IF(G9="КД","Крышка-дно",IF(G9="С","Самосборные",IF(G9="Ч","Четырехклапанные",IF(G9="А","Архивные","Неизвестно")))))) -> Четырехклапанные | AB9: 1.73 | AC9: =IF(O9="","",IF(O9<=1,"0-1 литров",IF(O9<=3,"2-3 литра",IF(O9<=5,"4-5 литра",IF(O9<=7,"6-7 литра",IF(O9<=9,"8-9 литров",IF(O9<=14,"10-14 литров",IF(O9<=19,"15-19 литров",IF(O9<=29,"20-29 литров",IF(O9<=49,"30-49 литров",IF(O9<=59,"50-59 литров",IF(O9<=70,"60-69 литров",IF(O9<=79,"70-79 литров",IF(O9<=89,"80-89 литров",IF(O9<=99,"90-99 литров",IF(O9<=200,"100-200 литров","200+ литров")))))))))))))))) -> 10-14 литров
A10: 1.09 | B10: =A10*1.2 -> 1.308 | C10: 10 | D10: У | E10: 160х150х800 | G10: Ч | H10: 0201 | I10: В | J10: х | K10: K9 | N10: =IF(D10="","",IF(LEFT(D10,1)="0",0,1)) -> 1 | O10: =ROUND(R10*S10*T10/1000000,2) -> 19.2 | P10: =IF(O10="","", IF(O10<1,"0,1-0,9 литров", IF(O10<2,"1-1,9 литра", IF(O10<3,"2-2,9 литра", IF(O10<4,"3-3,9 литра", IF(O10<6,"4-5,9 литра",IF(O10<8,"6-7,9 литра",IF(O10<10,"8-9,9 литров",IF(O10<15,"10-14,9 литров",IF(O10<20,"15-19,9 литров",IF(O10<30,"20-29 литров",IF(O10<50,"30-49 литров",IF(O10<60,"50-59 литров",IF(O10<70,"60-69 литров",IF(O10<80,"70-79 литров",IF(O10<90,"80-89 литров",IF(O10<100,"90-99 литров",IF(O10<200,"100-200 литров","200+ литров")))))))))))))))))) -> 15-19,9 литров | Q10: =IF(O10="","",IF(O10<1,"<1 л",IF(O10<2,"1-2 л",IF(O10<3,"2-3 л",IF(O10<5,"3-5 л",IF(O10<10,"5-10 л",IF(O10<20,"10-20 л",IF(O10<50,"20-50 л",IF(O10<100,"50-100 л","100+ л"))))))))) -> 10-20 л | R10: =IF(E10="","",--LEFT(E10,FIND("х",E10)-1)) -> 160 | S10: =IF(E10="","",--MID(E10,FIND("х",E10)+1,FIND("х",E10,FIND("х",E10)+1)-FIND("х",E10)-1)) -> 150 | T10: =IF(E10="","",--RIGHT(E10,LEN(E10)-FIND("х",E10,FIND("х",E10)+1))) -> 800 | U10: =(2*(R10+S10)+60)*(S10+T10+8)/1000000 -> 0.65144 | V10: =IF(OR(AND(R10>=2*S10,R10>=2*T10),AND(S10>=2*R10,S10>=2*T10),AND(T10>=2*R10,T10>=2*S10)),"Длинные","") -> Длинные | W10: =IF(OR(AND(R10<=S10/2,R10<=T10/2),AND(S10<=R10/2,S10<=T10/2),AND(T10<=R10/2,T10<=S10/2)),"Плоские","") | X10: =IF(LARGE($R10:$T10,1)="","",IF(LARGE($R10:$T10,1)<=99,"10-99 мм",IF(LARGE($R10:$T10,1)<=199,"100-199 мм",IF(LARGE($R10:$T10,1)<=299,"200-299 мм",IF(LARGE($R10:$T10,1)<=399,"300-399 мм",IF(LARGE($R10:$T10,1)<=499,"400-499 мм",IF(LARGE($R10:$T10,1)<=599,"500-599 мм",IF(LARGE($R10:$T10,1)<=699,"600-699 мм",IF(LARGE($R10:$T10,1)<=999,"700-999 мм","1000+ мм"))))))))) -> 700-999 мм | Y10: =IF(LARGE($R10:$T10,2)="","",IF(LARGE($R10:$T10,2)<=99,"10-99 мм",IF(LARGE($R10:$T10,2)<=199,"100-199 мм",IF(LARGE($R10:$T10,2)<=299,"200-299 мм",IF(LARGE($R10:$T10,2)<=399,"300-399 мм",IF(LARGE($R10:$T10,2)<=499,"400-499 мм",IF(LARGE($R10:$T10,2)<=599,"500-599 мм",IF(LARGE($R10:$T10,2)<=699,"600-699 мм",IF(LARGE($R10:$T10,2)<=999,"700-999 мм","1000+ мм"))))))))) -> 100-199 мм | Z10: =IF(SMALL($R10:$T10,1)="","",IF(SMALL($R10:$T10,1)<=99,"10-99 мм",IF(SMALL($R10:$T10,1)<=199,"100-199 мм",IF(SMALL($R10:$T10,1)<=299,"200-299 мм",IF(SMALL($R10:$T10,1)<=399,"300-399 мм",IF(SMALL($R10:$T10,1)<=499,"400-499 мм",IF(SMALL($R10:$T10,1)<=599,"500-599 мм",IF(SMALL($R10:$T10,1)<=699,"600-699 мм",IF(SMALL($R10:$T10,1)<=999,"700-999 мм","1000+ мм"))))))))) -> 100-199 мм | AA10: =IF(G10="","",IF(G10="Л","Лист гофрокартона",IF(G10="КД","Крышка-дно",IF(G10="С","Самосборные",IF(G10="Ч","Четырехклапанные",IF(G10="А","Архивные","Неизвестно")))))) -> Четырехклапанные | AB10: 1.73 | AC10: =IF(O10="","",IF(O10<=1,"0-1 литров",IF(O10<=3,"2-3 литра",IF(O10<=5,"4-5 литра",IF(O10<=7,"6-7 литра",IF(O10<=9,"8-9 литров",IF(O10<=14,"10-14 литров",IF(O10<=19,"15-19 литров",IF(O10<=29,"20-29 литров",IF(O10<=49,"30-49 литров",IF(O10<=59,"50-59 литров",IF(O10<=70,"60-69 литров",IF(O10<=79,"70-79 литров",IF(O10<=89,"80-89 литров",IF(O10<=99,"90-99 литров",IF(O10<=200,"100-200 литров","200+ литров")))))))))))))))) -> 20-29 литров
A11: 1.9 | B11: =A11*1.2 -> 2.28 | C11: 11 | D11: У | E11: 870х510х35 | G11: Ч | H11: 0401 | I11: В | J11: х | K11: K10 | N11: =IF(D11="","",IF(LEFT(D11,1)="0",0,1)) -> 1 | O11: =ROUND(R11*S11*T11/1000000,2) -> 15.53 | P11: =IF(O11="","", IF(O11<1,"0,1-0,9 литров", IF(O11<2,"1-1,9 литра", IF(O11<3,"2-2,9 литра", IF(O11<4,"3-3,9 литра", IF(O11<6,"4-5,9 литра",IF(O11<8,"6-7,9 литра",IF(O11<10,"8-9,9 литров",IF(O11<15,"10-14,9 литров",IF(O11<20,"15-19,9 литров",IF(O11<30,"20-29 литров",IF(O11<50,"30-49 литров",IF(O11<60,"50-59 литров",IF(O11<70,"60-69 литров",IF(O11<80,"70-79 литров",IF(O11<90,"80-89 литров",IF(O11<100,"90-99 литров",IF(O11<200,"100-200 литров","200+ литров")))))))))))))))))) -> 15-19,9 литров | Q11: =IF(O11="","",IF(O11<1,"<1 л",IF(O11<2,"1-2 л",IF(O11<3,"2-3 л",IF(O11<5,"3-5 л",IF(O11<10,"5-10 л",IF(O11<20,"10-20 л",IF(O11<50,"20-50 л",IF(O11<100,"50-100 л","100+ л"))))))))) -> 10-20 л | R11: =IF(E11="","",--LEFT(E11,FIND("х",E11)-1)) -> 870 | S11: =IF(E11="","",--MID(E11,FIND("х",E11)+1,FIND("х",E11,FIND("х",E11)+1)-FIND("х",E11)-1)) -> 510 | T11: =IF(E11="","",--RIGHT(E11,LEN(E11)-FIND("х",E11,FIND("х",E11)+1))) -> 35 | U11: =(2*(R11+S11)+60)*(S11+T11+8)/1000000 -> 1.55946 | V11: =IF(OR(AND(R11>=2*S11,R11>=2*T11),AND(S11>=2*R11,S11>=2*T11),AND(T11>=2*R11,T11>=2*S11)),"Длинные","") | W11: =IF(OR(AND(R11<=S11/2,R11<=T11/2),AND(S11<=R11/2,S11<=T11/2),AND(T11<=R11/2,T11<=S11/2)),"Плоские","") -> Плоские | X11: =IF(LARGE($R11:$T11,1)="","",IF(LARGE($R11:$T11,1)<=99,"10-99 мм",IF(LARGE($R11:$T11,1)<=199,"100-199 мм",IF(LARGE($R11:$T11,1)<=299,"200-299 мм",IF(LARGE($R11:$T11,1)<=399,"300-399 мм",IF(LARGE($R11:$T11,1)<=499,"400-499 мм",IF(LARGE($R11:$T11,1)<=599,"500-599 мм",IF(LARGE($R11:$T11,1)<=699,"600-699 мм",IF(LARGE($R11:$T11,1)<=999,"700-999 мм","1000+ мм"))))))))) -> 700-999 мм | Y11: =IF(LARGE($R11:$T11,2)="","",IF(LARGE($R11:$T11,2)<=99,"10-99 мм",IF(LARGE($R11:$T11,2)<=199,"100-199 мм",IF(LARGE($R11:$T11,2)<=299,"200-299 мм",IF(LARGE($R11:$T11,2)<=399,"300-399 мм",IF(LARGE($R11:$T11,2)<=499,"400-499 мм",IF(LARGE($R11:$T11,2)<=599,"500-599 мм",IF(LARGE($R11:$T11,2)<=699,"600-699 мм",IF(LARGE($R11:$T11,2)<=999,"700-999 мм","1000+ мм"))))))))) -> 500-599 мм | Z11: =IF(SMALL($R11:$T11,1)="","",IF(SMALL($R11:$T11,1)<=99,"10-99 мм",IF(SMALL($R11:$T11,1)<=199,"100-199 мм",IF(SMALL($R11:$T11,1)<=299,"200-299 мм",IF(SMALL($R11:$T11,1)<=399,"300-399 мм",IF(SMALL($R11:$T11,1)<=499,"400-499 мм",IF(SMALL($R11:$T11,1)<=599,"500-599 мм",IF(SMALL($R11:$T11,1)<=699,"600-699 мм",IF(SMALL($R11:$T11,1)<=999,"700-999 мм","1000+ мм"))))))))) -> 10-99 мм | AA11: =IF(G11="","",IF(G11="Л","Лист гофрокартона",IF(G11="КД","Крышка-дно",IF(G11="С","Самосборные",IF(G11="Ч","Четырехклапанные",IF(G11="А","Архивные","Неизвестно")))))) -> Четырехклапанные | AB11: 1.73 | AC11: =IF(O11="","",IF(O11<=1,"0-1 литров",IF(O11<=3,"2-3 литра",IF(O11<=5,"4-5 литра",IF(O11<=7,"6-7 литра",IF(O11<=9,"8-9 литров",IF(O11<=14,"10-14 литров",IF(O11<=19,"15-19 литров",IF(O11<=29,"20-29 литров",IF(O11<=49,"30-49 литров",IF(O11<=59,"50-59 литров",IF(O11<=70,"60-69 литров",IF(O11<=79,"70-79 литров",IF(O11<=89,"80-89 литров",IF(O11<=99,"90-99 литров",IF(O11<=200,"100-200 литров","200+ литров")))))))))))))))) -> 15-19 литров
A12: 1.71 | B12: =A12*1.2 -> 2.052 | C12: 12 | D12: У | E12: 400х400х200 | G12: Ч | H12: 0201 | I12: В | J12: х | K12: K11 | N12: =IF(D12="","",IF(LEFT(D12,1)="0",0,1)) -> 1 | O12: =ROUND(R12*S12*T12/1000000,2) -> 32 | P12: =IF(O12="","", IF(O12<1,"0,1-0,9 литров", IF(O12<2,"1-1,9 литра", IF(O12<3,"2-2,9 литра", IF(O12<4,"3-3,9 литра", IF(O12<6,"4-5,9 литра",IF(O12<8,"6-7,9 литра",IF(O12<10,"8-9,9 литров",IF(O12<15,"10-14,9 литров",IF(O12<20,"15-19,9 литров",IF(O12<30,"20-29 литров",IF(O12<50,"30-49 литров",IF(O12<60,"50-59 литров",IF(O12<70,"60-69 литров",IF(O12<80,"70-79 литров",IF(O12<90,"80-89 литров",IF(O12<100,"90-99 литров",IF(O12<200,"100-200 литров","200+ литров")))))))))))))))))) -> 30-49 литров | Q12: =IF(O12="","",IF(O12<1,"<1 л",IF(O12<2,"1-2 л",IF(O12<3,"2-3 л",IF(O12<5,"3-5 л",IF(O12<10,"5-10 л",IF(O12<20,"10-20 л",IF(O12<50,"20-50 л",IF(O12<100,"50-100 л","100+ л"))))))))) -> 20-50 л | R12: =IF(E12="","",--LEFT(E12,FIND("х",E12)-1)) -> 400 | S12: =IF(E12="","",--MID(E12,FIND("х",E12)+1,FIND("х",E12,FIND("х",E12)+1)-FIND("х",E12)-1)) -> 400 | T12: =IF(E12="","",--RIGHT(E12,LEN(E12)-FIND("х",E12,FIND("х",E12)+1))) -> 200 | U12: =(2*(R12+S12)+60)*(S12+T12+8)/1000000 -> 1.00928 | V12: =IF(OR(AND(R12>=2*S12,R12>=2*T12),AND(S12>=2*R12,S12>=2*T12),AND(T12>=2*R12,T12>=2*S12)),"Длинные","") | W12: =IF(OR(AND(R12<=S12/2,R12<=T12/2),AND(S12<=R12/2,S12<=T12/2),AND(T12<=R12/2,T12<=S12/2)),"Плоские","") -> Плоские | X12: =IF(LARGE($R12:$T12,1)="","",IF(LARGE($R12:$T12,1)<=99,"10-99 мм",IF(LARGE($R12:$T12,1)<=199,"100-199 мм",IF(LARGE($R12:$T12,1)<=299,"200-299 мм",IF(LARGE($R12:$T12,1)<=399,"300-399 мм",IF(LARGE($R12:$T12,1)<=499,"400-499 мм",IF(LARGE($R12:$T12,1)<=599,"500-599 мм",IF(LARGE($R12:$T12,1)<=699,"600-699 мм",IF(LARGE($R12:$T12,1)<=999,"700-999 мм","1000+ мм"))))))))) -> 400-499 мм | Y12: =IF(LARGE($R12:$T12,2)="","",IF(LARGE($R12:$T12,2)<=99,"10-99 мм",IF(LARGE($R12:$T12,2)<=199,"100-199 мм",IF(LARGE($R12:$T12,2)<=299,"200-299 мм",IF(LARGE($R12:$T12,2)<=399,"300-399 мм",IF(LARGE($R12:$T12,2)<=499,"400-499 мм",IF(LARGE($R12:$T12,2)<=599,"500-599 мм",IF(LARGE($R12:$T12,2)<=699,"600-699 мм",IF(LARGE($R12:$T12,2)<=999,"700-999 мм","1000+ мм"))))))))) -> 400-499 мм | Z12: =IF(SMALL($R12:$T12,1)="","",IF(SMALL($R12:$T12,1)<=99,"10-99 мм",IF(SMALL($R12:$T12,1)<=199,"100-199 мм",IF(SMALL($R12:$T12,1)<=299,"200-299 мм",IF(SMALL($R12:$T12,1)<=399,"300-399 мм",IF(SMALL($R12:$T12,1)<=499,"400-499 мм",IF(SMALL($R12:$T12,1)<=599,"500-599 мм",IF(SMALL($R12:$T12,1)<=699,"600-699 мм",IF(SMALL($R12:$T12,1)<=999,"700-999 мм","1000+ мм"))))))))) -> 200-299 мм | AA12: =IF(G12="","",IF(G12="Л","Лист гофрокартона",IF(G12="КД","Крышка-дно",IF(G12="С","Самосборные",IF(G12="Ч","Четырехклапанные",IF(G12="А","Архивные","Неизвестно")))))) -> Четырехклапанные | AB12: 1.73 | AC12: =IF(O12="","",IF(O12<=1,"0-1 литров",IF(O12<=3,"2-3 литра",IF(O12<=5,"4-5 литра",IF(O12<=7,"6-7 литра",IF(O12<=9,"8-9 литров",IF(O12<=14,"10-14 литров",IF(O12<=19,"15-19 литров",IF(O12<=29,"20-29 литров",IF(O12<=49,"30-49 литров",IF(O12<=59,"50-59 литров",IF(O12<=70,"60-69 литров",IF(O12<=79,"70-79 литров",IF(O12<=89,"80-89 литров",IF(O12<=99,"90-99 литров",IF(O12<=200,"100-200 литров","200+ литров")))))))))))))))) -> 30-49 литров
A13: 2.18 | B13: =A13*1.2 -> 2.616 | C13: 13 | D13: У | E13: 400х400х400 | G13: Ч | H13: 0201 | I13: В | J13: х | K13: K12 | N13: =IF(D13="","",IF(LEFT(D13,1)="0",0,1)) -> 1 | O13: =ROUND(R13*S13*T13/1000000,2) -> 64 | P13: =IF(O13="","", IF(O13<1,"0,1-0,9 литров", IF(O13<2,"1-1,9 литра", IF(O13<3,"2-2,9 литра", IF(O13<4,"3-3,9 литра", IF(O13<6,"4-5,9 литра",IF(O13<8,"6-7,9 литра",IF(O13<10,"8-9,9 литров",IF(O13<15,"10-14,9 литров",IF(O13<20,"15-19,9 литров",IF(O13<30,"20-29 литров",IF(O13<50,"30-49 литров",IF(O13<60,"50-59 литров",IF(O13<70,"60-69 литров",IF(O13<80,"70-79 литров",IF(O13<90,"80-89 литров",IF(O13<100,"90-99 литров",IF(O13<200,"100-200 литров","200+ литров")))))))))))))))))) -> 60-69 литров | Q13: =IF(O13="","",IF(O13<1,"<1 л",IF(O13<2,"1-2 л",IF(O13<3,"2-3 л",IF(O13<5,"3-5 л",IF(O13<10,"5-10 л",IF(O13<20,"10-20 л",IF(O13<50,"20-50 л",IF(O13<100,"50-100 л","100+ л"))))))))) -> 50-100 л | R13: =IF(E13="","",--LEFT(E13,FIND("х",E13)-1)) -> 400 | S13: =IF(E13="","",--MID(E13,FIND("х",E13)+1,FIND("х",E13,FIND("х",E13)+1)-FIND("х",E13)-1)) -> 400 | T13: =IF(E13="","",--RIGHT(E13,LEN(E13)-FIND("х",E13,FIND("х",E13)+1))) -> 400 | U13: =(2*(R13+S13)+60)*(S13+T13+8)/1000000 -> 1.34128 | V13: =IF(OR(AND(R13>=2*S13,R13>=2*T13),AND(S13>=2*R13,S13>=2*T13),AND(T13>=2*R13,T13>=2*S13)),"Длинные","") | W13: =IF(OR(AND(R13<=S13/2,R13<=T13/2),AND(S13<=R13/2,S13<=T13/2),AND(T13<=R13/2,T13<=S13/2)),"Плоские","") | X13: =IF(LARGE($R13:$T13,1)="","",IF(LARGE($R13:$T13,1)<=99,"10-99 мм",IF(LARGE($R13:$T13,1)<=199,"100-199 мм",IF(LARGE($R13:$T13,1)<=299,"200-299 мм",IF(LARGE($R13:$T13,1)<=399,"300-399 мм",IF(LARGE($R13:$T13,1)<=499,"400-499 мм",IF(LARGE($R13:$T13,1)<=599,"500-599 мм",IF(LARGE($R13:$T13,1)<=699,"600-699 мм",IF(LARGE($R13:$T13,1)<=999,"700-999 мм","1000+ мм"))))))))) -> 400-499 мм | Y13: =IF(LARGE($R13:$T13,2)="","",IF(LARGE($R13:$T13,2)<=99,"10-99 мм",IF(LARGE($R13:$T13,2)<=199,"100-199 мм",IF(LARGE($R13:$T13,2)<=299,"200-299 мм",IF(LARGE($R13:$T13,2)<=399,"300-399 мм",IF(LARGE($R13:$T13,2)<=499,"400-499 мм",IF(LARGE($R13:$T13,2)<=599,"500-599 мм",IF(LARGE($R13:$T13,2)<=699,"600-699 мм",IF(LARGE($R13:$T13,2)<=999,"700-999 мм","1000+ мм"))))))))) -> 400-499 мм | Z13: =IF(SMALL($R13:$T13,1)="","",IF(SMALL($R13:$T13,1)<=99,"10-99 мм",IF(SMALL($R13:$T13,1)<=199,"100-199 мм",IF(SMALL($R13:$T13,1)<=299,"200-299 мм",IF(SMALL($R13:$T13,1)<=399,"300-399 мм",IF(SMALL($R13:$T13,1)<=499,"400-499 мм",IF(SMALL($R13:$T13,1)<=599,"500-599 мм",IF(SMALL($R13:$T13,1)<=699,"600-699 мм",IF(SMALL($R13:$T13,1)<=999,"700-999 мм","1000+ мм"))))))))) -> 400-499 мм | AA13: =IF(G13="","",IF(G13="Л","Лист гофрокартона",IF(G13="КД","Крышка-дно",IF(G13="С","Самосборные",IF(G13="Ч","Четырехклапанные",IF(G13="А","Архивные","Неизвестно")))))) -> Четырехклапанные | AB13: 1.73 | AC13: =IF(O13="","",IF(O13<=1,"0-1 литров",IF(O13<=3,"2-3 литра",IF(O13<=5,"4-5 литра",IF(O13<=7,"6-7 литра",IF(O13<=9,"8-9 литров",IF(O13<=14,"10-14 литров",IF(O13<=19,"15-19 литров",IF(O13<=29,"20-29 литров",IF(O13<=49,"30-49 литров",IF(O13<=59,"50-59 литров",IF(O13<=70,"60-69 литров",IF(O13<=79,"70-79 литров",IF(O13<=89,"80-89 литров",IF(O13<=99,"90-99 литров",IF(O13<=200,"100-200 литров","200+ литров")))))))))))))))) -> 60-69 литров
A14: 0.13 | B14: =A14*1.2 -> 0.156 | C14: 14 | D14: У | E14: 50х50х145 | G14: С | H14: 0215 | I14: Е | J14: х | K14: K14 | N14: =IF(D14="","",IF(LEFT(D14,1)="0",0,1)) -> 1 | O14: =ROUND(R14*S14*T14/1000000,2) -> 0.36 | P14: =IF(O14="","", IF(O14<1,"0,1-0,9 литров", IF(O14<2,"1-1,9 литра", IF(O14<3,"2-2,9 литра", IF(O14<4,"3-3,9 литра", IF(O14<6,"4-5,9 литра",IF(O14<8,"6-7,9 литра",IF(O14<10,"8-9,9 литров",IF(O14<15,"10-14,9 литров",IF(O14<20,"15-19,9 литров",IF(O14<30,"20-29 литров",IF(O14<50,"30-49 литров",IF(O14<60,"50-59 литров",IF(O14<70,"60-69 литров",IF(O14<80,"70-79 литров",IF(O14<90,"80-89 литров",IF(O14<100,"90-99 литров",IF(O14<200,"100-200 литров","200+ литров")))))))))))))))))) -> 0,1-0,9 литров | Q14: =IF(O14="","",IF(O14<1,"<1 л",IF(O14<2,"1-2 л",IF(O14<3,"2-3 л",IF(O14<5,"3-5 л",IF(O14<10,"5-10 л",IF(O14<20,"10-20 л",IF(O14<50,"20-50 л",IF(O14<100,"50-100 л","100+ л"))))))))) -> <1 л | R14: =IF(E14="","",--LEFT(E14,FIND("х",E14)-1)) -> 50 | S14: =IF(E14="","",--MID(E14,FIND("х",E14)+1,FIND("х",E14,FIND("х",E14)+1)-FIND("х",E14)-1)) -> 50 | T14: =IF(E14="","",--RIGHT(E14,LEN(E14)-FIND("х",E14,FIND("х",E14)+1))) -> 145 | U14: =(2*(R14+S14)+60)*(S14+T14+8)/1000000 -> 0.05278 | V14: =IF(OR(AND(R14>=2*S14,R14>=2*T14),AND(S14>=2*R14,S14>=2*T14),AND(T14>=2*R14,T14>=2*S14)),"Длинные","") -> Длинные | W14: =IF(OR(AND(R14<=S14/2,R14<=T14/2),AND(S14<=R14/2,S14<=T14/2),AND(T14<=R14/2,T14<=S14/2)),"Плоские","") | X14: =IF(LARGE($R14:$T14,1)="","",IF(LARGE($R14:$T14,1)<=99,"10-99 мм",IF(LARGE($R14:$T14,1)<=199,"100-199 мм",IF(LARGE($R14:$T14,1)<=299,"200-299 мм",IF(LARGE($R14:$T14,1)<=399,"300-399 мм",IF(LARGE($R14:$T14,1)<=499,"400-499 мм",IF(LARGE($R14:$T14,1)<=599,"500-599 мм",IF(LARGE($R14:$T14,1)<=699,"600-699 мм",IF(LARGE($R14:$T14,1)<=999,"700-999 мм","1000+ мм"))))))))) -> 100-199 мм | Y14: =IF(LARGE($R14:$T14,2)="","",IF(LARGE($R14:$T14,2)<=99,"10-99 мм",IF(LARGE($R14:$T14,2)<=199,"100-199 мм",IF(LARGE($R14:$T14,2)<=299,"200-299 мм",IF(LARGE($R14:$T14,2)<=399,"300-399 мм",IF(LARGE($R14:$T14,2)<=499,"400-499 мм",IF(LARGE($R14:$T14,2)<=599,"500-599 мм",IF(LARGE($R14:$T14,2)<=699,"600-699 мм",IF(LARGE($R14:$T14,2)<=999,"700-999 мм","1000+ мм"))))))))) -> 10-99 мм | Z14: =IF(SMALL($R14:$T14,1)="","",IF(SMALL($R14:$T14,1)<=99,"10-99 мм",IF(SMALL($R14:$T14,1)<=199,"100-199 мм",IF(SMALL($R14:$T14,1)<=299,"200-299 мм",IF(SMALL($R14:$T14,1)<=399,"300-399 мм",IF(SMALL($R14:$T14,1)<=499,"400-499 мм",IF(SMALL($R14:$T14,1)<=599,"500-599 мм",IF(SMALL($R14:$T14,1)<=699,"600-699 мм",IF(SMALL($R14:$T14,1)<=999,"700-999 мм","1000+ мм"))))))))) -> 10-99 мм | AA14: =IF(G14="","",IF(G14="Л","Лист гофрокартона",IF(G14="КД","Крышка-дно",IF(G14="С","Самосборные",IF(G14="Ч","Четырехклапанные",IF(G14="А","Архивные","Неизвестно")))))) -> Самосборные | AB14: 1.73 | AC14: =IF(O14="","",IF(O14<=1,"0-1 литров",IF(O14<=3,"2-3 литра",IF(O14<=5,"4-5 литра",IF(O14<=7,"6-7 литра",IF(O14<=9,"8-9 литров",IF(O14<=14,"10-14 литров",IF(O14<=19,"15-19 литров",IF(O14<=29,"20-29 литров",IF(O14<=49,"30-49 литров",IF(O14<=59,"50-59 литров",IF(O14<=70,"60-69 литров",IF(O14<=79,"70-79 литров",IF(O14<=89,"80-89 литров",IF(O14<=99,"90-99 литров",IF(O14<=200,"100-200 литров","200+ литров")))))))))))))))) -> 0-1 литров
A15: 0.17 | B15: =A15*1.2 -> 0.204 | C15: 15 | D15: У | E15: 200х90х25 | G15: С | H15: 0427 | I15: Е | J15: х | K15: K15 | N15: =IF(D15="","",IF(LEFT(D15,1)="0",0,1)) -> 1 | O15: =ROUND(R15*S15*T15/1000000,2) -> 0.45 | P15: =IF(O15="","", IF(O15<1,"0,1-0,9 литров", IF(O15<2,"1-1,9 литра", IF(O15<3,"2-2,9 литра", IF(O15<4,"3-3,9 литра", IF(O15<6,"4-5,9 литра",IF(O15<8,"6-7,9 литра",IF(O15<10,"8-9,9 литров",IF(O15<15,"10-14,9 литров",IF(O15<20,"15-19,9 литров",IF(O15<30,"20-29 литров",IF(O15<50,"30-49 литров",IF(O15<60,"50-59 литров",IF(O15<70,"60-69 литров",IF(O15<80,"70-79 литров",IF(O15<90,"80-89 литров",IF(O15<100,"90-99 литров",IF(O15<200,"100-200 литров","200+ литров")))))))))))))))))) -> 0,1-0,9 литров | Q15: =IF(O15="","",IF(O15<1,"<1 л",IF(O15<2,"1-2 л",IF(O15<3,"2-3 л",IF(O15<5,"3-5 л",IF(O15<10,"5-10 л",IF(O15<20,"10-20 л",IF(O15<50,"20-50 л",IF(O15<100,"50-100 л","100+ л"))))))))) -> <1 л | R15: =IF(E15="","",--LEFT(E15,FIND("х",E15)-1)) -> 200 | S15: =IF(E15="","",--MID(E15,FIND("х",E15)+1,FIND("х",E15,FIND("х",E15)+1)-FIND("х",E15)-1)) -> 90 | T15: =IF(E15="","",--RIGHT(E15,LEN(E15)-FIND("х",E15,FIND("х",E15)+1))) -> 25 | U15: =(2*(R15+S15)+60)*(S15+T15+8)/1000000 -> 0.07872 | V15: =IF(OR(AND(R15>=2*S15,R15>=2*T15),AND(S15>=2*R15,S15>=2*T15),AND(T15>=2*R15,T15>=2*S15)),"Длинные","") -> Длинные | W15: =IF(OR(AND(R15<=S15/2,R15<=T15/2),AND(S15<=R15/2,S15<=T15/2),AND(T15<=R15/2,T15<=S15/2)),"Плоские","") -> Плоские | X15: =IF(LARGE($R15:$T15,1)="","",IF(LARGE($R15:$T15,1)<=99,"10-99 мм",IF(LARGE($R15:$T15,1)<=199,"100-199 мм",IF(LARGE($R15:$T15,1)<=299,"200-299 мм",IF(LARGE($R15:$T15,1)<=399,"300-399 мм",IF(LARGE($R15:$T15,1)<=499,"400-499 мм",IF(LARGE($R15:$T15,1)<=599,"500-599 мм",IF(LARGE($R15:$T15,1)<=699,"600-699 мм",IF(LARGE($R15:$T15,1)<=999,"700-999 мм","1000+ мм"))))))))) -> 200-299 мм | Y15: =IF(LARGE($R15:$T15,2)="","",IF(LARGE($R15:$T15,2)<=99,"10-99 мм",IF(LARGE($R15:$T15,2)<=199,"100-199 мм",IF(LARGE($R15:$T15,2)<=299,"200-299 мм",IF(LARGE($R15:$T15,2)<=399,"300-399 мм",IF(LARGE($R15:$T15,2)<=499,"400-499 мм",IF(LARGE($R15:$T15,2)<=599,"500-599 мм",IF(LARGE($R15:$T15,2)<=699,"600-699 мм",IF(LARGE($R15:$T15,2)<=999,"700-999 мм","1000+ мм"))))))))) -> 10-99 мм | Z15: =IF(SMALL($R15:$T15,1)="","",IF(SMALL($R15:$T15,1)<=99,"10-99 мм",IF(SMALL($R15:$T15,1)<=199,"100-199 мм",IF(SMALL($R15:$T15,1)<=299,"200-299 мм",IF(SMALL($R15:$T15,1)<=399,"300-399 мм",IF(SMALL($R15:$T15,1)<=499,"400-499 мм",IF(SMALL($R15:$T15,1)<=599,"500-599 мм",IF(SMALL($R15:$T15,1)<=699,"600-699 мм",IF(SMALL($R15:$T15,1)<=999,"700-999 мм","1000+ мм"))))))))) -> 10-99 мм | AA15: =IF(G15="","",IF(G15="Л","Лист гофрокартона",IF(G15="КД","Крышка-дно",IF(G15="С","Самосборные",IF(G15="Ч","Четырехклапанные",IF(G15="А","Архивные","Неизвестно")))))) -> Самосборные | AB15: 1.73 | AC15: =IF(O15="","",IF(O15<=1,"0-1 литров",IF(O15<=3,"2-3 литра",IF(O15<=5,"4-5 литра",IF(O15<=7,"6-7 литра",IF(O15<=9,"8-9 литров",IF(O15<=14,"10-14 литров",IF(O15<=19,"15-19 литров",IF(O15<=29,"20-29 литров",IF(O15<=49,"30-49 литров",IF(O15<=59,"50-59 литров",IF(O15<=70,"60-69 литров",IF(O15<=79,"70-79 литров",IF(O15<=89,"80-89 литров",IF(O15<=99,"90-99 литров",IF(O15<=200,"100-200 литров","200+ литров")))))))))))))))) -> 0-1 литров
A16: 0.54 | B16: =A16*1.2 -> 0.648 | C16: 16 | D16: У | E16: 250х100х320 | G16: Ч | H16: 0201 | I16: В | J16: х | K16: K16 | N16: =IF(D16="","",IF(LEFT(D16,1)="0",0,1)) -> 1 | O16: =ROUND(R16*S16*T16/1000000,2) -> 8 | P16: =IF(O16="","", IF(O16<1,"0,1-0,9 литров", IF(O16<2,"1-1,9 литра", IF(O16<3,"2-2,9 литра", IF(O16<4,"3-3,9 литра", IF(O16<6,"4-5,9 литра",IF(O16<8,"6-7,9 литра",IF(O16<10,"8-9,9 литров",IF(O16<15,"10-14,9 литров",IF(O16<20,"15-19,9 литров",IF(O16<30,"20-29 литров",IF(O16<50,"30-49 литров",IF(O16<60,"50-59 литров",IF(O16<70,"60-69 литров",IF(O16<80,"70-79 литров",IF(O16<90,"80-89 литров",IF(O16<100,"90-99 литров",IF(O16<200,"100-200 литров","200+ литров")))))))))))))))))) -> 8-9,9 литров | Q16: =IF(O16="","",IF(O16<1,"<1 л",IF(O16<2,"1-2 л",IF(O16<3,"2-3 л",IF(O16<5,"3-5 л",IF(O16<10,"5-10 л",IF(O16<20,"10-20 л",IF(O16<50,"20-50 л",IF(O16<100,"50-100 л","100+ л"))))))))) -> 5-10 л | R16: =IF(E16="","",--LEFT(E16,FIND("х",E16)-1)) -> 250 | S16: =IF(E16="","",--MID(E16,FIND("х",E16)+1,FIND("х",E16,FIND("х",E16)+1)-FIND("х",E16)-1)) -> 100 | T16: =IF(E16="","",--RIGHT(E16,LEN(E16)-FIND("х",E16,FIND("х",E16)+1))) -> 320 | U16: =(2*(R16+S16)+60)*(S16+T16+8)/1000000 -> 0.32528 | V16: =IF(OR(AND(R16>=2*S16,R16>=2*T16),AND(S16>=2*R16,S16>=2*T16),AND(T16>=2*R16,T16>=2*S16)),"Длинные","") | W16: =IF(OR(AND(R16<=S16/2,R16<=T16/2),AND(S16<=R16/2,S16<=T16/2),AND(T16<=R16/2,T16<=S16/2)),"Плоские","") -> Плоские | X16: =IF(LARGE($R16:$T16,1)="","",IF(LARGE($R16:$T16,1)<=99,"10-99 мм",IF(LARGE($R16:$T16,1)<=199,"100-199 мм",IF(LARGE($R16:$T16,1)<=299,"200-299 мм",IF(LARGE($R16:$T16,1)<=399,"300-399 мм",IF(LARGE($R16:$T16,1)<=499,"400-499 мм",IF(LARGE($R16:$T16,1)<=599,"500-599 мм",IF(LARGE($R16:$T16,1)<=699,"600-699 мм",IF(LARGE($R16:$T16,1)<=999,"700-999 мм","1000+ мм"))))))))) -> 300-399 мм | Y16: =IF(LARGE($R16:$T16,2)="","",IF(LARGE($R16:$T16,2)<=99,"10-99 мм",IF(LARGE($R16:$T16,2)<=199,"100-199 мм",IF(LARGE($R16:$T16,2)<=299,"200-299 мм",IF(LARGE($R16:$T16,2)<=399,"300-399 мм",IF(LARGE($R16:$T16,2)<=499,"400-499 мм",IF(LARGE($R16:$T16,2)<=599,"500-599 мм",IF(LARGE($R16:$T16,2)<=699,"600-699 мм",IF(LARGE($R16:$T16,2)<=999,"700-999 мм","1000+ мм"))))))))) -> 200-299 мм | Z16: =IF(SMALL($R16:$T16,1)="","",IF(SMALL($R16:$T16,1)<=99,"10-99 мм",IF(SMALL($R16:$T16,1)<=199,"100-199 мм",IF(SMALL($R16:$T16,1)<=299,"200-299 мм",IF(SMALL($R16:$T16,1)<=399,"300-399 мм",IF(SMALL($R16:$T16,1)<=499,"400-499 мм",IF(SMALL($R16:$T16,1)<=599,"500-599 мм",IF(SMALL($R16:$T16,1)<=699,"600-699 мм",IF(SMALL($R16:$T16,1)<=999,"700-999 мм","1000+ мм"))))))))) -> 100-199 мм | AA16: =IF(G16="","",IF(G16="Л","Лист гофрокартона",IF(G16="КД","Крышка-дно",IF(G16="С","Самосборные",IF(G16="Ч","Четырехклапанные",IF(G16="А","Архивные","Неизвестно")))))) -> Четырехклапанные | AB16: 1.73 | AC16: =IF(O16="","",IF(O16<=1,"0-1 литров",IF(O16<=3,"2-3 литра",IF(O16<=5,"4-5 литра",IF(O16<=7,"6-7 литра",IF(O16<=9,"8-9 литров",IF(O16<=14,"10-14 литров",IF(O16<=19,"15-19 литров",IF(O16<=29,"20-29 литров",IF(O16<=49,"30-49 литров",IF(O16<=59,"50-59 литров",IF(O16<=70,"60-69 литров",IF(O16<=79,"70-79 литров",IF(O16<=89,"80-89 литров",IF(O16<=99,"90-99 литров",IF(O16<=200,"100-200 литров","200+ литров")))))))))))))))) -> 8-9 литров
A17: 0.15 | B17: =A17*1.2 -> 0.18 | C17: 17 | D17: У | E17: 90х80х30 | G17: С | H17: 0427 | I17: Е | J17: х | K17: K17 | N17: =IF(D17="","",IF(LEFT(D17,1)="0",0,1)) -> 1 | O17: =ROUND(R17*S17*T17/1000000,2) -> 0.22 | P17: =IF(O17="","", IF(O17<1,"0,1-0,9 литров", IF(O17<2,"1-1,9 литра", IF(O17<3,"2-2,9 литра", IF(O17<4,"3-3,9 литра", IF(O17<6,"4-5,9 литра",IF(O17<8,"6-7,9 литра",IF(O17<10,"8-9,9 литров",IF(O17<15,"10-14,9 литров",IF(O17<20,"15-19,9 литров",IF(O17<30,"20-29 литров",IF(O17<50,"30-49 литров",IF(O17<60,"50-59 литров",IF(O17<70,"60-69 литров",IF(O17<80,"70-79 литров",IF(O17<90,"80-89 литров",IF(O17<100,"90-99 литров",IF(O17<200,"100-200 литров","200+ литров")))))))))))))))))) -> 0,1-0,9 литров | Q17: =IF(O17="","",IF(O17<1,"<1 л",IF(O17<2,"1-2 л",IF(O17<3,"2-3 л",IF(O17<5,"3-5 л",IF(O17<10,"5-10 л",IF(O17<20,"10-20 л",IF(O17<50,"20-50 л",IF(O17<100,"50-100 л","100+ л"))))))))) -> <1 л | R17: =IF(E17="","",--LEFT(E17,FIND("х",E17)-1)) -> 90 | S17: =IF(E17="","",--MID(E17,FIND("х",E17)+1,FIND("х",E17,FIND("х",E17)+1)-FIND("х",E17)-1)) -> 80 | T17: =IF(E17="","",--RIGHT(E17,LEN(E17)-FIND("х",E17,FIND("х",E17)+1))) -> 30 | U17: =(2*(R17+S17)+60)*(S17+T17+8)/1000000 -> 0.0472 | V17: =IF(OR(AND(R17>=2*S17,R17>=2*T17),AND(S17>=2*R17,S17>=2*T17),AND(T17>=2*R17,T17>=2*S17)),"Длинные","") | W17: =IF(OR(AND(R17<=S17/2,R17<=T17/2),AND(S17<=R17/2,S17<=T17/2),AND(T17<=R17/2,T17<=S17/2)),"Плоские","") -> Плоские | X17: =IF(LARGE($R17:$T17,1)="","",IF(LARGE($R17:$T17,1)<=99,"10-99 мм",IF(LARGE($R17:$T17,1)<=199,"100-199 мм",IF(LARGE($R17:$T17,1)<=299,"200-299 мм",IF(LARGE($R17:$T17,1)<=399,"300-399 мм",IF(LARGE($R17:$T17,1)<=499,"400-499 мм",IF(LARGE($R17:$T17,1)<=599,"500-599 мм",IF(LARGE($R17:$T17,1)<=699,"600-699 мм",IF(LARGE($R17:$T17,1)<=999,"700-999 мм","1000+ мм"))))))))) -> 10-99 мм | Y17: =IF(LARGE($R17:$T17,2)="","",IF(LARGE($R17:$T17,2)<=99,"10-99 мм",IF(LARGE($R17:$T17,2)<=199,"100-199 мм",IF(LARGE($R17:$T17,2)<=299,"200-299 мм",IF(LARGE($R17:$T17,2)<=399,"300-399 мм",IF(LARGE($R17:$T17,2)<=499,"400-499 мм",IF(LARGE($R17:$T17,2)<=599,"500-599 мм",IF(LARGE($R17:$T17,2)<=699,"600-699 мм",IF(LARGE($R17:$T17,2)<=999,"700-999 мм","1000+ мм"))))))))) -> 10-99 мм | Z17: =IF(SMALL($R17:$T17,1)="","",IF(SMALL($R17:$T17,1)<=99,"10-99 мм",IF(SMALL($R17:$T17,1)<=199,"100-199 мм",IF(SMALL($R17:$T17,1)<=299,"200-299 мм",IF(SMALL($R17:$T17,1)<=399,"300-399 мм",IF(SMALL($R17:$T17,1)<=499,"400-499 мм",IF(SMALL($R17:$T17,1)<=599,"500-599 мм",IF(SMALL($R17:$T17,1)<=699,"600-699 мм",IF(SMALL($R17:$T17,1)<=999,"700-999 мм","1000+ мм"))))))))) -> 10-99 мм | AA17: =IF(G17="","",IF(G17="Л","Лист гофрокартона",IF(G17="КД","Крышка-дно",IF(G17="С","Самосборные",IF(G17="Ч","Четырехклапанные",IF(G17="А","Архивные","Неизвестно")))))) -> Самосборные | AB17: 1.73 | AC17: =IF(O17="","",IF(O17<=1,"0-1 литров",IF(O17<=3,"2-3 литра",IF(O17<=5,"4-5 литра",IF(O17<=7,"6-7 литра",IF(O17<=9,"8-9 литров",IF(O17<=14,"10-14 литров",IF(O17<=19,"15-19 литров",IF(O17<=29,"20-29 литров",IF(O17<=49,"30-49 литров",IF(O17<=59,"50-59 литров",IF(O17<=70,"60-69 литров",IF(O17<=79,"70-79 литров",IF(O17<=89,"80-89 литров",IF(O17<=99,"90-99 литров",IF(O17<=200,"100-200 литров","200+ литров")))))))))))))))) -> 0-1 литров
A18: 0.28 | B18: =A18*1.2 -> 0.336 | C18: 18 | D18: У | E18: 65х65х40 | G18: С | H18: 0215 | I18: Е | J18: х | K18: K18 | N18: =IF(D18="","",IF(LEFT(D18,1)="0",0,1)) -> 1 | O18: =ROUND(R18*S18*T18/1000000,2) -> 0.17 | P18: =IF(O18="","", IF(O18<1,"0,1-0,9 литров", IF(O18<2,"1-1,9 литра", IF(O18<3,"2-2,9 литра", IF(O18<4,"3-3,9 литра", IF(O18<6,"4-5,9 литра",IF(O18<8,"6-7,9 литра",IF(O18<10,"8-9,9 литров",IF(O18<15,"10-14,9 литров",IF(O18<20,"15-19,9 литров",IF(O18<30,"20-29 литров",IF(O18<50,"30-49 литров",IF(O18<60,"50-59 литров",IF(O18<70,"60-69 литров",IF(O18<80,"70-79 литров",IF(O18<90,"80-89 литров",IF(O18<100,"90-99 литров",IF(O18<200,"100-200 литров","200+ литров")))))))))))))))))) -> 0,1-0,9 литров | Q18: =IF(O18="","",IF(O18<1,"<1 л",IF(O18<2,"1-2 л",IF(O18<3,"2-3 л",IF(O18<5,"3-5 л",IF(O18<10,"5-10 л",IF(O18<20,"10-20 л",IF(O18<50,"20-50 л",IF(O18<100,"50-100 л","100+ л"))))))))) -> <1 л | R18: =IF(E18="","",--LEFT(E18,FIND("х",E18)-1)) -> 65 | S18: =IF(E18="","",--MID(E18,FIND("х",E18)+1,FIND("х",E18,FIND("х",E18)+1)-FIND("х",E18)-1)) -> 65 | T18: =IF(E18="","",--RIGHT(E18,LEN(E18)-FIND("х",E18,FIND("х",E18)+1))) -> 40 | U18: =(2*(R18+S18)+60)*(S18+T18+8)/1000000 -> 0.03616 | V18: =IF(OR(AND(R18>=2*S18,R18>=2*T18),AND(S18>=2*R18,S18>=2*T18),AND(T18>=2*R18,T18>=2*S18)),"Длинные","") | W18: =IF(OR(AND(R18<=S18/2,R18<=T18/2),AND(S18<=R18/2,S18<=T18/2),AND(T18<=R18/2,T18<=S18/2)),"Плоские","") | X18: =IF(LARGE($R18:$T18,1)="","",IF(LARGE($R18:$T18,1)<=99,"10-99 мм",IF(LARGE($R18:$T18,1)<=199,"100-199 мм",IF(LARGE($R18:$T18,1)<=299,"200-299 мм",IF(LARGE($R18:$T18,1)<=399,"300-399 мм",IF(LARGE($R18:$T18,1)<=499,"400-499 мм",IF(LARGE($R18:$T18,1)<=599,"500-599 мм",IF(LARGE($R18:$T18,1)<=699,"600-699 мм",IF(LARGE($R18:$T18,1)<=999,"700-999 мм","1000+ мм"))))))))) -> 10-99 мм | Y18: =IF(LARGE($R18:$T18,2)="","",IF(LARGE($R18:$T18,2)<=99,"10-99 мм",IF(LARGE($R18:$T18,2)<=199,"100-199 мм",IF(LARGE($R18:$T18,2)<=299,"200-299 мм",IF(LARGE($R18:$T18,2)<=399,"300-399 мм",IF(LARGE($R18:$T18,2)<=499,"400-499 мм",IF(LARGE($R18:$T18,2)<=599,"500-599 мм",IF(LARGE($R18:$T18,2)<=699,"600-699 мм",IF(LARGE($R18:$T18,2)<=999,"700-999 мм","1000+ мм"))))))))) -> 10-99 мм | Z18: =IF(SMALL($R18:$T18,1)="","",IF(SMALL($R18:$T18,1)<=99,"10-99 мм",IF(SMALL($R18:$T18,1)<=199,"100-199 мм",IF(SMALL($R18:$T18,1)<=299,"200-299 мм",IF(SMALL($R18:$T18,1)<=399,"300-399 мм",IF(SMALL($R18:$T18,1)<=499,"400-499 мм",IF(SMALL($R18:$T18,1)<=599,"500-599 мм",IF(SMALL($R18:$T18,1)<=699,"600-699 мм",IF(SMALL($R18:$T18,1)<=999,"700-999 мм","1000+ мм"))))))))) -> 10-99 мм | AA18: =IF(G18="","",IF(G18="Л","Лист гофрокартона",IF(G18="КД","Крышка-дно",IF(G18="С","Самосборные",IF(G18="Ч","Четырехклапанные",IF(G18="А","Архивные","Неизвестно")))))) -> Самосборные | AB18: 1.73 | AC18: =IF(O18="","",IF(O18<=1,"0-1 литров",IF(O18<=3,"2-3 литра",IF(O18<=5,"4-5 литра",IF(O18<=7,"6-7 литра",IF(O18<=9,"8-9 литров",IF(O18<=14,"10-14 литров",IF(O18<=19,"15-19 литров",IF(O18<=29,"20-29 литров",IF(O18<=49,"30-49 литров",IF(O18<=59,"50-59 литров",IF(O18<=70,"60-69 литров",IF(O18<=79,"70-79 литров",IF(O18<=89,"80-89 литров",IF(O18<=99,"90-99 литров",IF(O18<=200,"100-200 литров","200+ литров")))))))))))))))) -> 0-1 литров
A19: 0.28 | B19: =A19*1.2 -> 0.336 | C19: 19 | D19: У | E19: 178х120х46 | G19: С | H19: 0426 | I19: Е | J19: х | K19: K19 | N19: =IF(D19="","",IF(LEFT(D19,1)="0",0,1)) -> 1 | O19: =ROUND(R19*S19*T19/1000000,2) -> 0.98 | P19: =IF(O19="","", IF(O19<1,"0,1-0,9 литров", IF(O19<2,"1-1,9 литра", IF(O19<3,"2-2,9 литра", IF(O19<4,"3-3,9 литра", IF(O19<6,"4-5,9 литра",IF(O19<8,"6-7,9 литра",IF(O19<10,"8-9,9 литров",IF(O19<15,"10-14,9 литров",IF(O19<20,"15-19,9 литров",IF(O19<30,"20-29 литров",IF(O19<50,"30-49 литров",IF(O19<60,"50-59 литров",IF(O19<70,"60-69 литров",IF(O19<80,"70-79 литров",IF(O19<90,"80-89 литров",IF(O19<100,"90-99 литров",IF(O19<200,"100-200 литров","200+ литров")))))))))))))))))) -> 0,1-0,9 литров | Q19: =IF(O19="","",IF(O19<1,"<1 л",IF(O19<2,"1-2 л",IF(O19<3,"2-3 л",IF(O19<5,"3-5 л",IF(O19<10,"5-10 л",IF(O19<20,"10-20 л",IF(O19<50,"20-50 л",IF(O19<100,"50-100 л","100+ л"))))))))) -> <1 л | R19: =IF(E19="","",--LEFT(E19,FIND("х",E19)-1)) -> 178 | S19: =IF(E19="","",--MID(E19,FIND("х",E19)+1,FIND("х",E19,FIND("х",E19)+1)-FIND("х",E19)-1)) -> 120 | T19: =IF(E19="","",--RIGHT(E19,LEN(E19)-FIND("х",E19,FIND("х",E19)+1))) -> 46 | U19: =(2*(R19+S19)+60)*(S19+T19+8)/1000000 -> 0.114144 | V19: =IF(OR(AND(R19>=2*S19,R19>=2*T19),AND(S19>=2*R19,S19>=2*T19),AND(T19>=2*R19,T19>=2*S19)),"Длинные","") | W19: =IF(OR(AND(R19<=S19/2,R19<=T19/2),AND(S19<=R19/2,S19<=T19/2),AND(T19<=R19/2,T19<=S19/2)),"Плоские","") -> Плоские | X19: =IF(LARGE($R19:$T19,1)="","",IF(LARGE($R19:$T19,1)<=99,"10-99 мм",IF(LARGE($R19:$T19,1)<=199,"100-199 мм",IF(LARGE($R19:$T19,1)<=299,"200-299 мм",IF(LARGE($R19:$T19,1)<=399,"300-399 мм",IF(LARGE($R19:$T19,1)<=499,"400-499 мм",IF(LARGE($R19:$T19,1)<=599,"500-599 мм",IF(LARGE($R19:$T19,1)<=699,"600-699 мм",IF(LARGE($R19:$T19,1)<=999,"700-999 мм","1000+ мм"))))))))) -> 100-199 мм | Y19: =IF(LARGE($R19:$T19,2)="","",IF(LARGE($R19:$T19,2)<=99,"10-99 мм",IF(LARGE($R19:$T19,2)<=199,"100-199 мм",IF(LARGE($R19:$T19,2)<=299,"200-299 мм",IF(LARGE($R19:$T19,2)<=399,"300-399 мм",IF(LARGE($R19:$T19,2)<=499,"400-499 мм",IF(LARGE($R19:$T19,2)<=599,"500-599 мм",IF(LARGE($R19:$T19,2)<=699,"600-699 мм",IF(LARGE($R19:$T19,2)<=999,"700-999 мм","1000+ мм"))))))))) -> 100-199 мм | Z19: =IF(SMALL($R19:$T19,1)="","",IF(SMALL($R19:$T19,1)<=99,"10-99 мм",IF(SMALL($R19:$T19,1)<=199,"100-199 мм",IF(SMALL($R19:$T19,1)<=299,"200-299 мм",IF(SMALL($R19:$T19,1)<=399,"300-399 мм",IF(SMALL($R19:$T19,1)<=499,"400-499 мм",IF(SMALL($R19:$T19,1)<=599,"500-599 мм",IF(SMALL($R19:$T19,1)<=699,"600-699 мм",IF(SMALL($R19:$T19,1)<=999,"700-999 мм","1000+ мм"))))))))) -> 10-99 мм | AA19: =IF(G19="","",IF(G19="Л","Лист гофрокартона",IF(G19="КД","Крышка-дно",IF(G19="С","Самосборные",IF(G19="Ч","Четырехклапанные",IF(G19="А","Архивные","Неизвестно")))))) -> Самосборные | AB19: 1.73 | AC19: =IF(O19="","",IF(O19<=1,"0-1 литров",IF(O19<=3,"2-3 литра",IF(O19<=5,"4-5 литра",IF(O19<=7,"6-7 литра",IF(O19<=9,"8-9 литров",IF(O19<=14,"10-14 литров",IF(O19<=19,"15-19 литров",IF(O19<=29,"20-29 литров",IF(O19<=49,"30-49 литров",IF(O19<=59,"50-59 литров",IF(O19<=70,"60-69 литров",IF(O19<=79,"70-79 литров",IF(O19<=89,"80-89 литров",IF(O19<=99,"90-99 литров",IF(O19<=200,"100-200 литров","200+ литров")))))))))))))))) -> 0-1 литров
A20: 0.28 | B20: =A20*1.2 -> 0.336 | C20: 20 | D20: У | E20: 110х110х87 | G20: С | H20: 0215 | I20: В | J20: х | K20: K20 | N20: =IF(D20="","",IF(LEFT(D20,1)="0",0,1)) -> 1 | O20: =ROUND(R20*S20*T20/1000000,2) -> 1.05 | P20: =IF(O20="","", IF(O20<1,"0,1-0,9 литров", IF(O20<2,"1-1,9 литра", IF(O20<3,"2-2,9 литра", IF(O20<4,"3-3,9 литра", IF(O20<6,"4-5,9 литра",IF(O20<8,"6-7,9 литра",IF(O20<10,"8-9,9 литров",IF(O20<15,"10-14,9 литров",IF(O20<20,"15-19,9 литров",IF(O20<30,"20-29 литров",IF(O20<50,"30-49 литров",IF(O20<60,"50-59 литров",IF(O20<70,"60-69 литров",IF(O20<80,"70-79 литров",IF(O20<90,"80-89 литров",IF(O20<100,"90-99 литров",IF(O20<200,"100-200 литров","200+ литров")))))))))))))))))) -> 1-1,9 литра | Q20: =IF(O20="","",IF(O20<1,"<1 л",IF(O20<2,"1-2 л",IF(O20<3,"2-3 л",IF(O20<5,"3-5 л",IF(O20<10,"5-10 л",IF(O20<20,"10-20 л",IF(O20<50,"20-50 л",IF(O20<100,"50-100 л","100+ л"))))))))) -> 1-2 л | R20: =IF(E20="","",--LEFT(E20,FIND("х",E20)-1)) -> 110 | S20: =IF(E20="","",--MID(E20,FIND("х",E20)+1,FIND("х",E20,FIND("х",E20)+1)-FIND("х",E20)-1)) -> 110 | T20: =IF(E20="","",--RIGHT(E20,LEN(E20)-FIND("х",E20,FIND("х",E20)+1))) -> 87 | U20: =(2*(R20+S20)+60)*(S20+T20+8)/1000000 -> 0.1025 | V20: =IF(OR(AND(R20>=2*S20,R20>=2*T20),AND(S20>=2*R20,S20>=2*T20),AND(T20>=2*R20,T20>=2*S20)),"Длинные","") | W20: =IF(OR(AND(R20<=S20/2,R20<=T20/2),AND(S20<=R20/2,S20<=T20/2),AND(T20<=R20/2,T20<=S20/2)),"Плоские","") | X20: =IF(LARGE($R20:$T20,1)="","",IF(LARGE($R20:$T20,1)<=99,"10-99 мм",IF(LARGE($R20:$T20,1)<=199,"100-199 мм",IF(LARGE($R20:$T20,1)<=299,"200-299 мм",IF(LARGE($R20:$T20,1)<=399,"300-399 мм",IF(LARGE($R20:$T20,1)<=499,"400-499 мм",IF(LARGE($R20:$T20,1)<=599,"500-599 мм",IF(LARGE($R20:$T20,1)<=699,"600-699 мм",IF(LARGE($R20:$T20,1)<=999,"700-999 мм","1000+ мм"))))))))) -> 100-199 мм | Y20: =IF(LARGE($R20:$T20,2)="","",IF(LARGE($R20:$T20,2)<=99,"10-99 мм",IF(LARGE($R20:$T20,2)<=199,"100-199 мм",IF(LARGE($R20:$T20,2)<=299,"200-299 мм",IF(LARGE($R20:$T20,2)<=399,"300-399 мм",IF(LARGE($R20:$T20,2)<=499,"400-499 мм",IF(LARGE($R20:$T20,2)<=599,"500-599 мм",IF(LARGE($R20:$T20,2)<=699,"600-699 мм",IF(LARGE($R20:$T20,2)<=999,"700-999 мм","1000+ мм"))))))))) -> 100-199 мм | Z20: =IF(SMALL($R20:$T20,1)="","",IF(SMALL($R20:$T20,1)<=99,"10-99 мм",IF(SMALL($R20:$T20,1)<=199,"100-199 мм",IF(SMALL($R20:$T20,1)<=299,"200-299 мм",IF(SMALL($R20:$T20,1)<=399,"300-399 мм",IF(SMALL($R20:$T20,1)<=499,"400-499 мм",IF(SMALL($R20:$T20,1)<=599,"500-599 мм",IF(SMALL($R20:$T20,1)<=699,"600-699 мм",IF(SMALL($R20:$T20,1)<=999,"700-999 мм","1000+ мм"))))))))) -> 10-99 мм | AA20: =IF(G20="","",IF(G20="Л","Лист гофрокартона",IF(G20="КД","Крышка-дно",IF(G20="С","Самосборные",IF(G20="Ч","Четырехклапанные",IF(G20="А","Архивные","Неизвестно")))))) -> Самосборные | AB20: 1.73 | AC20: =IF(O20="","",IF(O20<=1,"0-1 литров",IF(O20<=3,"2-3 литра",IF(O20<=5,"4-5 литра",IF(O20<=7,"6-7 литра",IF(O20<=9,"8-9 литров",IF(O20<=14,"10-14 литров",IF(O20<=19,"15-19 литров",IF(O20<=29,"20-29 литров",IF(O20<=49,"30-49 литров",IF(O20<=59,"50-59 литров",IF(O20<=70,"60-69 литров",IF(O20<=79,"70-79 литров",IF(O20<=89,"80-89 литров",IF(O20<=99,"90-99 литров",IF(O20<=200,"100-200 литров","200+ литров")))))))))))))))) -> 2-3 литра
A21: 0.17 | B21: =A21*1.2 -> 0.204 | C21: 21 | D21: У | E21: 50х50х170 | G21: С | H21: 0215 | I21: Е | J21: х | K21: K21 | N21: =IF(D21="","",IF(LEFT(D21,1)="0",0,1)) -> 1 | O21: =ROUND(R21*S21*T21/1000000,2) -> 0.43 | P21: =IF(O21="","", IF(O21<1,"0,1-0,9 литров", IF(O21<2,"1-1,9 литра", IF(O21<3,"2-2,9 литра", IF(O21<4,"3-3,9 литра", IF(O21<6,"4-5,9 литра",IF(O21<8,"6-7,9 литра",IF(O21<10,"8-9,9 литров",IF(O21<15,"10-14,9 литров",IF(O21<20,"15-19,9 литров",IF(O21<30,"20-29 литров",IF(O21<50,"30-49 литров",IF(O21<60,"50-59 литров",IF(O21<70,"60-69 литров",IF(O21<80,"70-79 литров",IF(O21<90,"80-89 литров",IF(O21<100,"90-99 литров",IF(O21<200,"100-200 литров","200+ литров")))))))))))))))))) -> 0,1-0,9 литров | Q21: =IF(O21="","",IF(O21<1,"<1 л",IF(O21<2,"1-2 л",IF(O21<3,"2-3 л",IF(O21<5,"3-5 л",IF(O21<10,"5-10 л",IF(O21<20,"10-20 л",IF(O21<50,"20-50 л",IF(O21<100,"50-100 л","100+ л"))))))))) -> <1 л | R21: =IF(E21="","",--LEFT(E21,FIND("х",E21)-1)) -> 50 | S21: =IF(E21="","",--MID(E21,FIND("х",E21)+1,FIND("х",E21,FIND("х",E21)+1)-FIND("х",E21)-1)) -> 50 | T21: =IF(E21="","",--RIGHT(E21,LEN(E21)-FIND("х",E21,FIND("х",E21)+1))) -> 170 | U21: =(2*(R21+S21)+60)*(S21+T21+8)/1000000 -> 0.05928 | V21: =IF(OR(AND(R21>=2*S21,R21>=2*T21),AND(S21>=2*R21,S21>=2*T21),AND(T21>=2*R21,T21>=2*S21)),"Длинные","") -> Длинные | W21: =IF(OR(AND(R21<=S21/2,R21<=T21/2),AND(S21<=R21/2,S21<=T21/2),AND(T21<=R21/2,T21<=S21/2)),"Плоские","") | X21: =IF(LARGE($R21:$T21,1)="","",IF(LARGE($R21:$T21,1)<=99,"10-99 мм",IF(LARGE($R21:$T21,1)<=199,"100-199 мм",IF(LARGE($R21:$T21,1)<=299,"200-299 мм",IF(LARGE($R21:$T21,1)<=399,"300-399 мм",IF(LARGE($R21:$T21,1)<=499,"400-499 мм",IF(LARGE($R21:$T21,1)<=599,"500-599 мм",IF(LARGE($R21:$T21,1)<=699,"600-699 мм",IF(LARGE($R21:$T21,1)<=999,"700-999 мм","1000+ мм"))))))))) -> 100-199 мм | Y21: =IF(LARGE($R21:$T21,2)="","",IF(LARGE($R21:$T21,2)<=99,"10-99 мм",IF(LARGE($R21:$T21,2)<=199,"100-199 мм",IF(LARGE($R21:$T21,2)<=299,"200-299 мм",IF(LARGE($R21:$T21,2)<=399,"300-399 мм",IF(LARGE($R21:$T21,2)<=499,"400-499 мм",IF(LARGE($R21:$T21,2)<=599,"500-599 мм",IF(LARGE($R21:$T21,2)<=699,"600-699 мм",IF(LARGE($R21:$T21,2)<=999,"700-999 мм","1000+ мм"))))))))) -> 10-99 мм | Z21: =IF(SMALL($R21:$T21,1)="","",IF(SMALL($R21:$T21,1)<=99,"10-99 мм",IF(SMALL($R21:$T21,1)<=199,"100-199 мм",IF(SMALL($R21:$T21,1)<=299,"200-299 мм",IF(SMALL($R21:$T21,1)<=399,"300-399 мм",IF(SMALL($R21:$T21,1)<=499,"400-499 мм",IF(SMALL($R21:$T21,1)<=599,"500-599 мм",IF(SMALL($R21:$T21,1)<=699,"600-699 мм",IF(SMALL($R21:$T21,1)<=999,"700-999 мм","1000+ мм"))))))))) -> 10-99 мм | AA21: =IF(G21="","",IF(G21="Л","Лист гофрокартона",IF(G21="КД","Крышка-дно",IF(G21="С","Самосборные",IF(G21="Ч","Четырехклапанные",IF(G21="А","Архивные","Неизвестно")))))) -> Самосборные | AB21: 1.73 | AC21: =IF(O21="","",IF(O21<=1,"0-1 литров",IF(O21<=3,"2-3 литра",IF(O21<=5,"4-5 литра",IF(O21<=7,"6-7 литра",IF(O21<=9,"8-9 литров",IF(O21<=14,"10-14 литров",IF(O21<=19,"15-19 литров",IF(O21<=29,"20-29 литров",IF(O21<=49,"30-49 литров",IF(O21<=59,"50-59 литров",IF(O21<=70,"60-69 литров",IF(O21<=79,"70-79 литров",IF(O21<=89,"80-89 литров",IF(O21<=99,"90-99 литров",IF(O21<=200,"100-200 литров","200+ литров")))))))))))))))) -> 0-1 литров
... A32: 0.41 | B32: =A32*1.2 -> 0.492 | C32: 32 | D32: У | E32: 130х80х100 | G32: С | H32: 0215 | I32: В | J32: х | K32: K32 | N32: =IF(D32="","",IF(LEFT(D32,1)="0",0,1)) -> 1 | O32: =ROUND(R32*S32*T32/1000000,2) -> 1.04 | P32: =IF(O32="","", IF(O32<1,"0,1-0,9 литров", IF(O32<2,"1-1,9 литра", IF(O32<3,"2-2,9 литра", IF(O32<4,"3-3,9 литра", IF(O32<6,"4-5,9 литра",IF(O32<8,"6-7,9 литра",IF(O32<10,"8-9,9 литров",IF(O32<15,"10-14,9 литров",IF(O32<20,"15-19,9 литров",IF(O32<30,"20-29 литров",IF(O32<50,"30-49 литров",IF(O32<60,"50-59 литров",IF(O32<70,"60-69 литров",IF(O32<80,"70-79 литров",IF(O32<90,"80-89 литров",IF(O32<100,"90-99 литров",IF(O32<200,"100-200 литров","200+ литров")))))))))))))))))) -> 1-1,9 литра | Q32: =IF(O32="","",IF(O32<1,"<1 л",IF(O32<2,"1-2 л",IF(O32<3,"2-3 л",IF(O32<5,"3-5 л",IF(O32<10,"5-10 л",IF(O32<20,"10-20 л",IF(O32<50,"20-50 л",IF(O32<100,"50-100 л","100+ л"))))))))) -> 1-2 л | R32: =IF(E32="","",--LEFT(E32,FIND("х",E32)-1)) -> 130 | S32: =IF(E32="","",--MID(E32,FIND("х",E32)+1,FIND("х",E32,FIND("х",E32)+1)-FIND("х",E32)-1)) -> 80 | T32: =IF(E32="","",--RIGHT(E32,LEN(E32)-FIND("х",E32,FIND("х",E32)+1))) -> 100 | U32: =(2*(R32+S32)+60)*(S32+T32+8)/1000000 -> 0.09024 | V32: =IF(OR(AND(R32>=2*S32,R32>=2*T32),AND(S32>=2*R32,S32>=2*T32),AND(T32>=2*R32,T32>=2*S32)),"Длинные","") | W32: =IF(OR(AND(R32<=S32/2,R32<=T32/2),AND(S32<=R32/2,S32<=T32/2),AND(T32<=R32/2,T32<=S32/2)),"Плоские","") | X32: =IF(LARGE($R32:$T32,1)="","",IF(LARGE($R32:$T32,1)<=99,"10-99 мм",IF(LARGE($R32:$T32,1)<=199,"100-199 мм",IF(LARGE($R32:$T32,1)<=299,"200-299 мм",IF(LARGE($R32:$T32,1)<=399,"300-399 мм",IF(LARGE($R32:$T32,1)<=499,"400-499 мм",IF(LARGE($R32:$T32,1)<=599,"500-599 мм",IF(LARGE($R32:$T32,1)<=699,"600-699 мм",IF(LARGE($R32:$T32,1)<=999,"700-999 мм","1000+ мм"))))))))) -> 100-199 мм | Y32: =IF(LARGE($R32:$T32,2)="","",IF(LARGE($R32:$T32,2)<=99,"10-99 мм",IF(LARGE($R32:$T32,2)<=199,"100-199 мм",IF(LARGE($R32:$T32,2)<=299,"200-299 мм",IF(LARGE($R32:$T32,2)<=399,"300-399 мм",IF(LARGE($R32:$T32,2)<=499,"400-499 мм",IF(LARGE($R32:$T32,2)<=599,"500-599 мм",IF(LARGE($R32:$T32,2)<=699,"600-699 мм",IF(LARGE($R32:$T32,2)<=999,"700-999 мм","1000+ мм"))))))))) -> 100-199 мм | Z32: =IF(SMALL($R32:$T32,1)="","",IF(SMALL($R32:$T32,1)<=99,"10-99 мм",IF(SMALL($R32:$T32,1)<=199,"100-199 мм",IF(SMALL($R32:$T32,1)<=299,"200-299 мм",IF(SMALL($R32:$T32,1)<=399,"300-399 мм",IF(SMALL($R32:$T32,1)<=499,"400-499 мм",IF(SMALL($R32:$T32,1)<=599,"500-599 мм",IF(SMALL($R32:$T32,1)<=699,"600-699 мм",IF(SMALL($R32:$T32,1)<=999,"700-999 мм","1000+ мм"))))))))) -> 10-99 мм | AA32: =IF(G32="","",IF(G32="Л","Лист гофрокартона",IF(G32="КД","Крышка-дно",IF(G32="С","Самосборные",IF(G32="Ч","Четырехклапанные",IF(G32="А","Архивные","Неизвестно")))))) -> Самосборные | AB32: 1.73 | AC32: =IF(O32="","",IF(O32<=1,"0-1 литров",IF(O32<=3,"2-3 литра",IF(O32<=5,"4-5 литра",IF(O32<=7,"6-7 литра",IF(O32<=9,"8-9 литров",IF(O32<=14,"10-14 литров",IF(O32<=19,"15-19 литров",IF(O32<=29,"20-29 литров",IF(O32<=49,"30-49 литров",IF(O32<=59,"50-59 литров",IF(O32<=70,"60-69 литров",IF(O32<=79,"70-79 литров",IF(O32<=89,"80-89 литров",IF(O32<=99,"90-99 литров",IF(O32<=200,"100-200 литров","200+ литров")))))))))))))))) -> 2-3 литра
A33: 0.77 | B33: =A33*1.2 -> 0.924 | C33: 33 | D33: У | E33: 250х170х90 | F33: временная расспродажа | G33: С | H33: 0427 | I33: В | J33: х | K33: K33 | L33: Sale | N33: =IF(D33="","",IF(LEFT(D33,1)="0",0,1)) -> 1 | O33: =ROUND(R33*S33*T33/1000000,2) -> 3.83 | P33: =IF(O33="","", IF(O33<1,"0,1-0,9 литров", IF(O33<2,"1-1,9 литра", IF(O33<3,"2-2,9 литра", IF(O33<4,"3-3,9 литра", IF(O33<6,"4-5,9 литра",IF(O33<8,"6-7,9 литра",IF(O33<10,"8-9,9 литров",IF(O33<15,"10-14,9 литров",IF(O33<20,"15-19,9 литров",IF(O33<30,"20-29 литров",IF(O33<50,"30-49 литров",IF(O33<60,"50-59 литров",IF(O33<70,"60-69 литров",IF(O33<80,"70-79 литров",IF(O33<90,"80-89 литров",IF(O33<100,"90-99 литров",IF(O33<200,"100-200 литров","200+ литров")))))))))))))))))) -> 3-3,9 литра | Q33: =IF(O33="","",IF(O33<1,"<1 л",IF(O33<2,"1-2 л",IF(O33<3,"2-3 л",IF(O33<5,"3-5 л",IF(O33<10,"5-10 л",IF(O33<20,"10-20 л",IF(O33<50,"20-50 л",IF(O33<100,"50-100 л","100+ л"))))))))) -> 3-5 л | R33: =IF(E33="","",--LEFT(E33,FIND("х",E33)-1)) -> 250 | S33: =IF(E33="","",--MID(E33,FIND("х",E33)+1,FIND("х",E33,FIND("х",E33)+1)-FIND("х",E33)-1)) -> 170 | T33: =IF(E33="","",--RIGHT(E33,LEN(E33)-FIND("х",E33,FIND("х",E33)+1))) -> 90 | U33: =(2*(R33+S33)+60)*(S33+T33+8)/1000000 -> 0.2412 | V33: =IF(OR(AND(R33>=2*S33,R33>=2*T33),AND(S33>=2*R33,S33>=2*T33),AND(T33>=2*R33,T33>=2*S33)),"Длинные","") | W33: =IF(OR(AND(R33<=S33/2,R33<=T33/2),AND(S33<=R33/2,S33<=T33/2),AND(T33<=R33/2,T33<=S33/2)),"Плоские","") | X33: =IF(LARGE($R33:$T33,1)="","",IF(LARGE($R33:$T33,1)<=99,"10-99 мм",IF(LARGE($R33:$T33,1)<=199,"100-199 мм",IF(LARGE($R33:$T33,1)<=299,"200-299 мм",IF(LARGE($R33:$T33,1)<=399,"300-399 мм",IF(LARGE($R33:$T33,1)<=499,"400-499 мм",IF(LARGE($R33:$T33,1)<=599,"500-599 мм",IF(LARGE($R33:$T33,1)<=699,"600-699 мм",IF(LARGE($R33:$T33,1)<=999,"700-999 мм","1000+ мм"))))))))) -> 200-299 мм | Y33: =IF(LARGE($R33:$T33,2)="","",IF(LARGE($R33:$T33,2)<=99,"10-99 мм",IF(LARGE($R33:$T33,2)<=199,"100-199 мм",IF(LARGE($R33:$T33,2)<=299,"200-299 мм",IF(LARGE($R33:$T33,2)<=399,"300-399 мм",IF(LARGE($R33:$T33,2)<=499,"400-499 мм",IF(LARGE($R33:$T33,2)<=599,"500-599 мм",IF(LARGE($R33:$T33,2)<=699,"600-699 мм",IF(LARGE($R33:$T33,2)<=999,"700-999 мм","1000+ мм"))))))))) -> 100-199 мм | Z33: =IF(SMALL($R33:$T33,1)="","",IF(SMALL($R33:$T33,1)<=99,"10-99 мм",IF(SMALL($R33:$T33,1)<=199,"100-199 мм",IF(SMALL($R33:$T33,1)<=299,"200-299 мм",IF(SMALL($R33:$T33,1)<=399,"300-399 мм",IF(SMALL($R33:$T33,1)<=499,"400-499 мм",IF(SMALL($R33:$T33,1)<=599,"500-599 мм",IF(SMALL($R33:$T33,1)<=699,"600-699 мм",IF(SMALL($R33:$T33,1)<=999,"700-999 мм","1000+ мм"))))))))) -> 10-99 мм | AA33: =IF(G33="","",IF(G33="Л","Лист гофрокартона",IF(G33="КД","Крышка-дно",IF(G33="С","Самосборные",IF(G33="Ч","Четырехклапанные",IF(G33="А","Архивные","Неизвестно")))))) -> Самосборные | AB33: 1.73 | AC33: =IF(O33="","",IF(O33<=1,"0-1 литров",IF(O33<=3,"2-3 литра",IF(O33<=5,"4-5 литра",IF(O33<=7,"6-7 литра",IF(O33<=9,"8-9 литров",IF(O33<=14,"10-14 литров",IF(O33<=19,"15-19 литров",IF(O33<=29,"20-29 литров",IF(O33<=49,"30-49 литров",IF(O33<=59,"50-59 литров",IF(O33<=70,"60-69 литров",IF(O33<=79,"70-79 литров",IF(O33<=89,"80-89 литров",IF(O33<=99,"90-99 литров",IF(O33<=200,"100-200 литров","200+ литров")))))))))))))))) -> 4-5 литра
A34: 0.31 | B34: =A34*1.2 -> 0.372 | C34: 34 | D34: У | E34: 200х80х80 | G34: С | H34: 0471 | I34: В | J34: х | K34: K34 | N34: =IF(D34="","",IF(LEFT(D34,1)="0",0,1)) -> 1 | O34: =ROUND(R34*S34*T34/1000000,2) -> 1.28 | P34: =IF(O34="","", IF(O34<1,"0,1-0,9 литров", IF(O34<2,"1-1,9 литра", IF(O34<3,"2-2,9 литра", IF(O34<4,"3-3,9 литра", IF(O34<6,"4-5,9 литра",IF(O34<8,"6-7,9 литра",IF(O34<10,"8-9,9 литров",IF(O34<15,"10-14,9 литров",IF(O34<20,"15-19,9 литров",IF(O34<30,"20-29 литров",IF(O34<50,"30-49 литров",IF(O34<60,"50-59 литров",IF(O34<70,"60-69 литров",IF(O34<80,"70-79 литров",IF(O34<90,"80-89 литров",IF(O34<100,"90-99 литров",IF(O34<200,"100-200 литров","200+ литров")))))))))))))))))) -> 1-1,9 литра | Q34: =IF(O34="","",IF(O34<1,"<1 л",IF(O34<2,"1-2 л",IF(O34<3,"2-3 л",IF(O34<5,"3-5 л",IF(O34<10,"5-10 л",IF(O34<20,"10-20 л",IF(O34<50,"20-50 л",IF(O34<100,"50-100 л","100+ л"))))))))) -> 1-2 л | R34: =IF(E34="","",--LEFT(E34,FIND("х",E34)-1)) -> 200 | S34: =IF(E34="","",--MID(E34,FIND("х",E34)+1,FIND("х",E34,FIND("х",E34)+1)-FIND("х",E34)-1)) -> 80 | T34: =IF(E34="","",--RIGHT(E34,LEN(E34)-FIND("х",E34,FIND("х",E34)+1))) -> 80 | U34: =(2*(R34+S34)+60)*(S34+T34+8)/1000000 -> 0.10416 | V34: =IF(OR(AND(R34>=2*S34,R34>=2*T34),AND(S34>=2*R34,S34>=2*T34),AND(T34>=2*R34,T34>=2*S34)),"Длинные","") -> Длинные | W34: =IF(OR(AND(R34<=S34/2,R34<=T34/2),AND(S34<=R34/2,S34<=T34/2),AND(T34<=R34/2,T34<=S34/2)),"Плоские","") | X34: =IF(LARGE($R34:$T34,1)="","",IF(LARGE($R34:$T34,1)<=99,"10-99 мм",IF(LARGE($R34:$T34,1)<=199,"100-199 мм",IF(LARGE($R34:$T34,1)<=299,"200-299 мм",IF(LARGE($R34:$T34,1)<=399,"300-399 мм",IF(LARGE($R34:$T34,1)<=499,"400-499 мм",IF(LARGE($R34:$T34,1)<=599,"500-599 мм",IF(LARGE($R34:$T34,1)<=699,"600-699 мм",IF(LARGE($R34:$T34,1)<=999,"700-999 мм","1000+ мм"))))))))) -> 200-299 мм | Y34: =IF(LARGE($R34:$T34,2)="","",IF(LARGE($R34:$T34,2)<=99,"10-99 мм",IF(LARGE($R34:$T34,2)<=199,"100-199 мм",IF(LARGE($R34:$T34,2)<=299,"200-299 мм",IF(LARGE($R34:$T34,2)<=399,"300-399 мм",IF(LARGE($R34:$T34,2)<=499,"400-499 мм",IF(LARGE($R34:$T34,2)<=599,"500-599 мм",IF(LARGE($R34:$T34,2)<=699,"600-699 мм",IF(LARGE($R34:$T34,2)<=999,"700-999 мм","1000+ мм"))))))))) -> 10-99 мм | Z34: =IF(SMALL($R34:$T34,1)="","",IF(SMALL($R34:$T34,1)<=99,"10-99 мм",IF(SMALL($R34:$T34,1)<=199,"100-199 мм",IF(SMALL($R34:$T34,1)<=299,"200-299 мм",IF(SMALL($R34:$T34,1)<=399,"300-399 мм",IF(SMALL($R34:$T34,1)<=499,"400-499 мм",IF(SMALL($R34:$T34,1)<=599,"500-599 мм",IF(SMALL($R34:$T34,1)<=699,"600-699 мм",IF(SMALL($R34:$T34,1)<=999,"700-999 мм","1000+ мм"))))))))) -> 10-99 мм | AA34: =IF(G34="","",IF(G34="Л","Лист гофрокартона",IF(G34="КД","Крышка-дно",IF(G34="С","Самосборные",IF(G34="Ч","Четырехклапанные",IF(G34="А","Архивные","Неизвестно")))))) -> Самосборные | AB34: 1.73 | AC34: =IF(O34="","",IF(O34<=1,"0-1 литров",IF(O34<=3,"2-3 литра",IF(O34<=5,"4-5 литра",IF(O34<=7,"6-7 литра",IF(O34<=9,"8-9 литров",IF(O34<=14,"10-14 литров",IF(O34<=19,"15-19 литров",IF(O34<=29,"20-29 литров",IF(O34<=49,"30-49 литров",IF(O34<=59,"50-59 литров",IF(O34<=70,"60-69 литров",IF(O34<=79,"70-79 литров",IF(O34<=89,"80-89 литров",IF(O34<=99,"90-99 литров",IF(O34<=200,"100-200 литров","200+ литров")))))))))))))))) -> 2-3 литра
A35: 0.83 | B35: =A35*1.2 -> 0.996 | C35: 35 | D35: У | E35: 690х170х55 | G35: С | H35: 0427 | I35: В | J35: х | K35: K35 | N35: =IF(D35="","",IF(LEFT(D35,1)="0",0,1)) -> 1 | O35: =ROUND(R35*S35*T35/1000000,2) -> 6.45 | P35: =IF(O35="","", IF(O35<1,"0,1-0,9 литров", IF(O35<2,"1-1,9 литра", IF(O35<3,"2-2,9 литра", IF(O35<4,"3-3,9 литра", IF(O35<6,"4-5,9 литра",IF(O35<8,"6-7,9 литра",IF(O35<10,"8-9,9 литров",IF(O35<15,"10-14,9 литров",IF(O35<20,"15-19,9 литров",IF(O35<30,"20-29 литров",IF(O35<50,"30-49 литров",IF(O35<60,"50-59 литров",IF(O35<70,"60-69 литров",IF(O35<80,"70-79 литров",IF(O35<90,"80-89 литров",IF(O35<100,"90-99 литров",IF(O35<200,"100-200 литров","200+ литров")))))))))))))))))) -> 6-7,9 литра | Q35: =IF(O35="","",IF(O35<1,"<1 л",IF(O35<2,"1-2 л",IF(O35<3,"2-3 л",IF(O35<5,"3-5 л",IF(O35<10,"5-10 л",IF(O35<20,"10-20 л",IF(O35<50,"20-50 л",IF(O35<100,"50-100 л","100+ л"))))))))) -> 5-10 л | R35: =IF(E35="","",--LEFT(E35,FIND("х",E35)-1)) -> 690 | S35: =IF(E35="","",--MID(E35,FIND("х",E35)+1,FIND("х",E35,FIND("х",E35)+1)-FIND("х",E35)-1)) -> 170 | T35: =IF(E35="","",--RIGHT(E35,LEN(E35)-FIND("х",E35,FIND("х",E35)+1))) -> 55 | U35: =(2*(R35+S35)+60)*(S35+T35+8)/1000000 -> 0.41474 | V35: =IF(OR(AND(R35>=2*S35,R35>=2*T35),AND(S35>=2*R35,S35>=2*T35),AND(T35>=2*R35,T35>=2*S35)),"Длинные","") -> Длинные | W35: =IF(OR(AND(R35<=S35/2,R35<=T35/2),AND(S35<=R35/2,S35<=T35/2),AND(T35<=R35/2,T35<=S35/2)),"Плоские","") -> Плоские | X35: =IF(LARGE($R35:$T35,1)="","",IF(LARGE($R35:$T35,1)<=99,"10-99 мм",IF(LARGE($R35:$T35,1)<=199,"100-199 мм",IF(LARGE($R35:$T35,1)<=299,"200-299 мм",IF(LARGE($R35:$T35,1)<=399,"300-399 мм",IF(LARGE($R35:$T35,1)<=499,"400-499 мм",IF(LARGE($R35:$T35,1)<=599,"500-599 мм",IF(LARGE($R35:$T35,1)<=699,"600-699 мм",IF(LARGE($R35:$T35,1)<=999,"700-999 мм","1000+ мм"))))))))) -> 600-699 мм | Y35: =IF(LARGE($R35:$T35,2)="","",IF(LARGE($R35:$T35,2)<=99,"10-99 мм",IF(LARGE($R35:$T35,2)<=199,"100-199 мм",IF(LARGE($R35:$T35,2)<=299,"200-299 мм",IF(LARGE($R35:$T35,2)<=399,"300-399 мм",IF(LARGE($R35:$T35,2)<=499,"400-499 мм",IF(LARGE($R35:$T35,2)<=599,"500-599 мм",IF(LARGE($R35:$T35,2)<=699,"600-699 мм",IF(LARGE($R35:$T35,2)<=999,"700-999 мм","1000+ мм"))))))))) -> 100-199 мм | Z35: =IF(SMALL($R35:$T35,1)="","",IF(SMALL($R35:$T35,1)<=99,"10-99 мм",IF(SMALL($R35:$T35,1)<=199,"100-199 мм",IF(SMALL($R35:$T35,1)<=299,"200-299 мм",IF(SMALL($R35:$T35,1)<=399,"300-399 мм",IF(SMALL($R35:$T35,1)<=499,"400-499 мм",IF(SMALL($R35:$T35,1)<=599,"500-599 мм",IF(SMALL($R35:$T35,1)<=699,"600-699 мм",IF(SMALL($R35:$T35,1)<=999,"700-999 мм","1000+ мм"))))))))) -> 10-99 мм | AA35: =IF(G35="","",IF(G35="Л","Лист гофрокартона",IF(G35="КД","Крышка-дно",IF(G35="С","Самосборные",IF(G35="Ч","Четырехклапанные",IF(G35="А","Архивные","Неизвестно")))))) -> Самосборные | AB35: 1.73 | AC35: =IF(O35="","",IF(O35<=1,"0-1 литров",IF(O35<=3,"2-3 литра",IF(O35<=5,"4-5 литра",IF(O35<=7,"6-7 литра",IF(O35<=9,"8-9 литров",IF(O35<=14,"10-14 литров",IF(O35<=19,"15-19 литров",IF(O35<=29,"20-29 литров",IF(O35<=49,"30-49 литров",IF(O35<=59,"50-59 литров",IF(O35<=70,"60-69 литров",IF(O35<=79,"70-79 литров",IF(O35<=89,"80-89 литров",IF(O35<=99,"90-99 литров",IF(O35<=200,"100-200 литров","200+ литров")))))))))))))))) -> 6-7 литра
A36: 1.46 | B36: =A36*1.2 -> 1.752 | C36: 36 | D36: У | E36: 1110х115х105 | G36: С | H36: 0427 | I36: В | J36: х | K36: K36 | N36: =IF(D36="","",IF(LEFT(D36,1)="0",0,1)) -> 1 | O36: =ROUND(R36*S36*T36/1000000,2) -> 13.4 | P36: =IF(O36="","", IF(O36<1,"0,1-0,9 литров", IF(O36<2,"1-1,9 литра", IF(O36<3,"2-2,9 литра", IF(O36<4,"3-3,9 литра", IF(O36<6,"4-5,9 литра",IF(O36<8,"6-7,9 литра",IF(O36<10,"8-9,9 литров",IF(O36<15,"10-14,9 литров",IF(O36<20,"15-19,9 литров",IF(O36<30,"20-29 литров",IF(O36<50,"30-49 литров",IF(O36<60,"50-59 литров",IF(O36<70,"60-69 литров",IF(O36<80,"70-79 литров",IF(O36<90,"80-89 литров",IF(O36<100,"90-99 литров",IF(O36<200,"100-200 литров","200+ литров")))))))))))))))))) -> 10-14,9 литров | Q36: =IF(O36="","",IF(O36<1,"<1 л",IF(O36<2,"1-2 л",IF(O36<3,"2-3 л",IF(O36<5,"3-5 л",IF(O36<10,"5-10 л",IF(O36<20,"10-20 л",IF(O36<50,"20-50 л",IF(O36<100,"50-100 л","100+ л"))))))))) -> 10-20 л | R36: =IF(E36="","",--LEFT(E36,FIND("х",E36)-1)) -> 1110 | S36: =IF(E36="","",--MID(E36,FIND("х",E36)+1,FIND("х",E36,FIND("х",E36)+1)-FIND("х",E36)-1)) -> 115 | T36: =IF(E36="","",--RIGHT(E36,LEN(E36)-FIND("х",E36,FIND("х",E36)+1))) -> 105 | U36: =(2*(R36+S36)+60)*(S36+T36+8)/1000000 -> 0.57228 | V36: =IF(OR(AND(R36>=2*S36,R36>=2*T36),AND(S36>=2*R36,S36>=2*T36),AND(T36>=2*R36,T36>=2*S36)),"Длинные","") -> Длинные | W36: =IF(OR(AND(R36<=S36/2,R36<=T36/2),AND(S36<=R36/2,S36<=T36/2),AND(T36<=R36/2,T36<=S36/2)),"Плоские","") | X36: =IF(LARGE($R36:$T36,1)="","",IF(LARGE($R36:$T36,1)<=99,"10-99 мм",IF(LARGE($R36:$T36,1)<=199,"100-199 мм",IF(LARGE($R36:$T36,1)<=299,"200-299 мм",IF(LARGE($R36:$T36,1)<=399,"300-399 мм",IF(LARGE($R36:$T36,1)<=499,"400-499 мм",IF(LARGE($R36:$T36,1)<=599,"500-599 мм",IF(LARGE($R36:$T36,1)<=699,"600-699 мм",IF(LARGE($R36:$T36,1)<=999,"700-999 мм","1000+ мм"))))))))) -> 1000+ мм | Y36: =IF(LARGE($R36:$T36,2)="","",IF(LARGE($R36:$T36,2)<=99,"10-99 мм",IF(LARGE($R36:$T36,2)<=199,"100-199 мм",IF(LARGE($R36:$T36,2)<=299,"200-299 мм",IF(LARGE($R36:$T36,2)<=399,"300-399 мм",IF(LARGE($R36:$T36,2)<=499,"400-499 мм",IF(LARGE($R36:$T36,2)<=599,"500-599 мм",IF(LARGE($R36:$T36,2)<=699,"600-699 мм",IF(LARGE($R36:$T36,2)<=999,"700-999 мм","1000+ мм"))))))))) -> 100-199 мм | Z36: =IF(SMALL($R36:$T36,1)="","",IF(SMALL($R36:$T36,1)<=99,"10-99 мм",IF(SMALL($R36:$T36,1)<=199,"100-199 мм",IF(SMALL($R36:$T36,1)<=299,"200-299 мм",IF(SMALL($R36:$T36,1)<=399,"300-399 мм",IF(SMALL($R36:$T36,1)<=499,"400-499 мм",IF(SMALL($R36:$T36,1)<=599,"500-599 мм",IF(SMALL($R36:$T36,1)<=699,"600-699 мм",IF(SMALL($R36:$T36,1)<=999,"700-999 мм","1000+ мм"))))))))) -> 100-199 мм | AA36: =IF(G36="","",IF(G36="Л","Лист гофрокартона",IF(G36="КД","Крышка-дно",IF(G36="С","Самосборные",IF(G36="Ч","Четырехклапанные",IF(G36="А","Архивные","Неизвестно")))))) -> Самосборные | AB36: 1.73 | AC36: =IF(O36="","",IF(O36<=1,"0-1 литров",IF(O36<=3,"2-3 литра",IF(O36<=5,"4-5 литра",IF(O36<=7,"6-7 литра",IF(O36<=9,"8-9 литров",IF(O36<=14,"10-14 литров",IF(O36<=19,"15-19 литров",IF(O36<=29,"20-29 литров",IF(O36<=49,"30-49 литров",IF(O36<=59,"50-59 литров",IF(O36<=70,"60-69 литров",IF(O36<=79,"70-79 литров",IF(O36<=89,"80-89 литров",IF(O36<=99,"90-99 литров",IF(O36<=200,"100-200 литров","200+ литров")))))))))))))))) -> 10-14 литров
A37: 1.46 | B37: =A37*1.2 -> 1.752 | C37: 37 | D37: У | E37: 500х500х65 | G37: С | H37: 0426 | I37: В | J37: х | K37: K37 | N37: =IF(D37="","",IF(LEFT(D37,1)="0",0,1)) -> 1 | O37: =ROUND(R37*S37*T37/1000000,2) -> 16.25 | P37: =IF(O37="","", IF(O37<1,"0,1-0,9 литров", IF(O37<2,"1-1,9 литра", IF(O37<3,"2-2,9 литра", IF(O37<4,"3-3,9 литра", IF(O37<6,"4-5,9 литра",IF(O37<8,"6-7,9 литра",IF(O37<10,"8-9,9 литров",IF(O37<15,"10-14,9 литров",IF(O37<20,"15-19,9 литров",IF(O37<30,"20-29 литров",IF(O37<50,"30-49 литров",IF(O37<60,"50-59 литров",IF(O37<70,"60-69 литров",IF(O37<80,"70-79 литров",IF(O37<90,"80-89 литров",IF(O37<100,"90-99 литров",IF(O37<200,"100-200 литров","200+ литров")))))))))))))))))) -> 15-19,9 литров | Q37: =IF(O37="","",IF(O37<1,"<1 л",IF(O37<2,"1-2 л",IF(O37<3,"2-3 л",IF(O37<5,"3-5 л",IF(O37<10,"5-10 л",IF(O37<20,"10-20 л",IF(O37<50,"20-50 л",IF(O37<100,"50-100 л","100+ л"))))))))) -> 10-20 л | R37: =IF(E37="","",--LEFT(E37,FIND("х",E37)-1)) -> 500 | S37: =IF(E37="","",--MID(E37,FIND("х",E37)+1,FIND("х",E37,FIND("х",E37)+1)-FIND("х",E37)-1)) -> 500 | T37: =IF(E37="","",--RIGHT(E37,LEN(E37)-FIND("х",E37,FIND("х",E37)+1))) -> 65 | U37: =(2*(R37+S37)+60)*(S37+T37+8)/1000000 -> 1.18038 | V37: =IF(OR(AND(R37>=2*S37,R37>=2*T37),AND(S37>=2*R37,S37>=2*T37),AND(T37>=2*R37,T37>=2*S37)),"Длинные","") | W37: =IF(OR(AND(R37<=S37/2,R37<=T37/2),AND(S37<=R37/2,S37<=T37/2),AND(T37<=R37/2,T37<=S37/2)),"Плоские","") -> Плоские | X37: =IF(LARGE($R37:$T37,1)="","",IF(LARGE($R37:$T37,1)<=99,"10-99 мм",IF(LARGE($R37:$T37,1)<=199,"100-199 мм",IF(LARGE($R37:$T37,1)<=299,"200-299 мм",IF(LARGE($R37:$T37,1)<=399,"300-399 мм",IF(LARGE($R37:$T37,1)<=499,"400-499 мм",IF(LARGE($R37:$T37,1)<=599,"500-599 мм",IF(LARGE($R37:$T37,1)<=699,"600-699 мм",IF(LARGE($R37:$T37,1)<=999,"700-999 мм","1000+ мм"))))))))) -> 500-599 мм | Y37: =IF(LARGE($R37:$T37,2)="","",IF(LARGE($R37:$T37,2)<=99,"10-99 мм",IF(LARGE($R37:$T37,2)<=199,"100-199 мм",IF(LARGE($R37:$T37,2)<=299,"200-299 мм",IF(LARGE($R37:$T37,2)<=399,"300-399 мм",IF(LARGE($R37:$T37,2)<=499,"400-499 мм",IF(LARGE($R37:$T37,2)<=599,"500-599 мм",IF(LARGE($R37:$T37,2)<=699,"600-699 мм",IF(LARGE($R37:$T37,2)<=999,"700-999 мм","1000+ мм"))))))))) -> 500-599 мм | Z37: =IF(SMALL($R37:$T37,1)="","",IF(SMALL($R37:$T37,1)<=99,"10-99 мм",IF(SMALL($R37:$T37,1)<=199,"100-199 мм",IF(SMALL($R37:$T37,1)<=299,"200-299 мм",IF(SMALL($R37:$T37,1)<=399,"300-399 мм",IF(SMALL($R37:$T37,1)<=499,"400-499 мм",IF(SMALL($R37:$T37,1)<=599,"500-599 мм",IF(SMALL($R37:$T37,1)<=699,"600-699 мм",IF(SMALL($R37:$T37,1)<=999,"700-999 мм","1000+ мм"))))))))) -> 10-99 мм | AA37: =IF(G37="","",IF(G37="Л","Лист гофрокартона",IF(G37="КД","Крышка-дно",IF(G37="С","Самосборные",IF(G37="Ч","Четырехклапанные",IF(G37="А","Архивные","Неизвестно")))))) -> Самосборные | AB37: 1.73 | AC37: =IF(O37="","",IF(O37<=1,"0-1 литров",IF(O37<=3,"2-3 литра",IF(O37<=5,"4-5 литра",IF(O37<=7,"6-7 литра",IF(O37<=9,"8-9 литров",IF(O37<=14,"10-14 литров",IF(O37<=19,"15-19 литров",IF(O37<=29,"20-29 литров",IF(O37<=49,"30-49 литров",IF(O37<=59,"50-59 литров",IF(O37<=70,"60-69 литров",IF(O37<=79,"70-79 литров",IF(O37<=89,"80-89 литров",IF(O37<=99,"90-99 литров",IF(O37<=200,"100-200 литров","200+ литров")))))))))))))))) -> 15-19 литров
A38: 0.73 | B38: =A38*1.2 -> 0.876 | C38: 38 | D38: У | E38: 300х215х65 | G38: С | H38: 0427 | I38: В | J38: х | K38: K38 | N38: =IF(D38="","",IF(LEFT(D38,1)="0",0,1)) -> 1 | O38: =ROUND(R38*S38*T38/1000000,2) -> 4.19 | P38: =IF(O38="","", IF(O38<1,"0,1-0,9 литров", IF(O38<2,"1-1,9 литра", IF(O38<3,"2-2,9 литра", IF(O38<4,"3-3,9 литра", IF(O38<6,"4-5,9 литра",IF(O38<8,"6-7,9 литра",IF(O38<10,"8-9,9 литров",IF(O38<15,"10-14,9 литров",IF(O38<20,"15-19,9 литров",IF(O38<30,"20-29 литров",IF(O38<50,"30-49 литров",IF(O38<60,"50-59 литров",IF(O38<70,"60-69 литров",IF(O38<80,"70-79 литров",IF(O38<90,"80-89 литров",IF(O38<100,"90-99 литров",IF(O38<200,"100-200 литров","200+ литров")))))))))))))))))) -> 4-5,9 литра | Q38: =IF(O38="","",IF(O38<1,"<1 л",IF(O38<2,"1-2 л",IF(O38<3,"2-3 л",IF(O38<5,"3-5 л",IF(O38<10,"5-10 л",IF(O38<20,"10-20 л",IF(O38<50,"20-50 л",IF(O38<100,"50-100 л","100+ л"))))))))) -> 3-5 л | R38: =IF(E38="","",--LEFT(E38,FIND("х",E38)-1)) -> 300 | S38: =IF(E38="","",--MID(E38,FIND("х",E38)+1,FIND("х",E38,FIND("х",E38)+1)-FIND("х",E38)-1)) -> 215 | T38: =IF(E38="","",--RIGHT(E38,LEN(E38)-FIND("х",E38,FIND("х",E38)+1))) -> 65 | U38: =(2*(R38+S38)+60)*(S38+T38+8)/1000000 -> 0.31392 | V38: =IF(OR(AND(R38>=2*S38,R38>=2*T38),AND(S38>=2*R38,S38>=2*T38),AND(T38>=2*R38,T38>=2*S38)),"Длинные","") | W38: =IF(OR(AND(R38<=S38/2,R38<=T38/2),AND(S38<=R38/2,S38<=T38/2),AND(T38<=R38/2,T38<=S38/2)),"Плоские","") -> Плоские | X38: =IF(LARGE($R38:$T38,1)="","",IF(LARGE($R38:$T38,1)<=99,"10-99 мм",IF(LARGE($R38:$T38,1)<=199,"100-199 мм",IF(LARGE($R38:$T38,1)<=299,"200-299 мм",IF(LARGE($R38:$T38,1)<=399,"300-399 мм",IF(LARGE($R38:$T38,1)<=499,"400-499 мм",IF(LARGE($R38:$T38,1)<=599,"500-599 мм",IF(LARGE($R38:$T38,1)<=699,"600-699 мм",IF(LARGE($R38:$T38,1)<=999,"700-999 мм","1000+ мм"))))))))) -> 300-399 мм | Y38: =IF(LARGE($R38:$T38,2)="","",IF(LARGE($R38:$T38,2)<=99,"10-99 мм",IF(LARGE($R38:$T38,2)<=199,"100-199 мм",IF(LARGE($R38:$T38,2)<=299,"200-299 мм",IF(LARGE($R38:$T38,2)<=399,"300-399 мм",IF(LARGE($R38:$T38,2)<=499,"400-499 мм",IF(LARGE($R38:$T38,2)<=599,"500-599 мм",IF(LARGE($R38:$T38,2)<=699,"600-699 мм",IF(LARGE($R38:$T38,2)<=999,"700-999 мм","1000+ мм"))))))))) -> 200-299 мм | Z38: =IF(SMALL($R38:$T38,1)="","",IF(SMALL($R38:$T38,1)<=99,"10-99 мм",IF(SMALL($R38:$T38,1)<=199,"100-199 мм",IF(SMALL($R38:$T38,1)<=299,"200-299 мм",IF(SMALL($R38:$T38,1)<=399,"300-399 мм",IF(SMALL($R38:$T38,1)<=499,"400-499 мм",IF(SMALL($R38:$T38,1)<=599,"500-599 мм",IF(SMALL($R38:$T38,1)<=699,"600-699 мм",IF(SMALL($R38:$T38,1)<=999,"700-999 мм","1000+ мм"))))))))) -> 10-99 мм | AA38: =IF(G38="","",IF(G38="Л","Лист гофрокартона",IF(G38="КД","Крышка-дно",IF(G38="С","Самосборные",IF(G38="Ч","Четырехклапанные",IF(G38="А","Архивные","Неизвестно")))))) -> Самосборные | AB38: 1.73 | AC38: =IF(O38="","",IF(O38<=1,"0-1 литров",IF(O38<=3,"2-3 литра",IF(O38<=5,"4-5 литра",IF(O38<=7,"6-7 литра",IF(O38<=9,"8-9 литров",IF(O38<=14,"10-14 литров",IF(O38<=19,"15-19 литров",IF(O38<=29,"20-29 литров",IF(O38<=49,"30-49 литров",IF(O38<=59,"50-59 литров",IF(O38<=70,"60-69 литров",IF(O38<=79,"70-79 литров",IF(O38<=89,"80-89 литров",IF(O38<=99,"90-99 литров",IF(O38<=200,"100-200 литров","200+ литров")))))))))))))))) -> 4-5 литра
A39: 0.94 | B39: =A39*1.2 -> 1.128 | C39: 39 | D39: У | E39: 120х100х890 | G39: С | H39: 0201 | I39: В | J39: х | K39: K39 | N39: =IF(D39="","",IF(LEFT(D39,1)="0",0,1)) -> 1 | O39: =ROUND(R39*S39*T39/1000000,2) -> 10.68 | P39: =IF(O39="","", IF(O39<1,"0,1-0,9 литров", IF(O39<2,"1-1,9 литра", IF(O39<3,"2-2,9 литра", IF(O39<4,"3-3,9 литра", IF(O39<6,"4-5,9 литра",IF(O39<8,"6-7,9 литра",IF(O39<10,"8-9,9 литров",IF(O39<15,"10-14,9 литров",IF(O39<20,"15-19,9 литров",IF(O39<30,"20-29 литров",IF(O39<50,"30-49 литров",IF(O39<60,"50-59 литров",IF(O39<70,"60-69 литров",IF(O39<80,"70-79 литров",IF(O39<90,"80-89 литров",IF(O39<100,"90-99 литров",IF(O39<200,"100-200 литров","200+ литров")))))))))))))))))) -> 10-14,9 литров | Q39: =IF(O39="","",IF(O39<1,"<1 л",IF(O39<2,"1-2 л",IF(O39<3,"2-3 л",IF(O39<5,"3-5 л",IF(O39<10,"5-10 л",IF(O39<20,"10-20 л",IF(O39<50,"20-50 л",IF(O39<100,"50-100 л","100+ л"))))))))) -> 10-20 л | R39: =IF(E39="","",--LEFT(E39,FIND("х",E39)-1)) -> 120 | S39: =IF(E39="","",--MID(E39,FIND("х",E39)+1,FIND("х",E39,FIND("х",E39)+1)-FIND("х",E39)-1)) -> 100 | T39: =IF(E39="","",--RIGHT(E39,LEN(E39)-FIND("х",E39,FIND("х",E39)+1))) -> 890 | U39: =(2*(R39+S39)+60)*(S39+T39+8)/1000000 -> 0.499 | V39: =IF(OR(AND(R39>=2*S39,R39>=2*T39),AND(S39>=2*R39,S39>=2*T39),AND(T39>=2*R39,T39>=2*S39)),"Длинные","") -> Длинные | W39: =IF(OR(AND(R39<=S39/2,R39<=T39/2),AND(S39<=R39/2,S39<=T39/2),AND(T39<=R39/2,T39<=S39/2)),"Плоские","") | X39: =IF(LARGE($R39:$T39,1)="","",IF(LARGE($R39:$T39,1)<=99,"10-99 мм",IF(LARGE($R39:$T39,1)<=199,"100-199 мм",IF(LARGE($R39:$T39,1)<=299,"200-299 мм",IF(LARGE($R39:$T39,1)<=399,"300-399 мм",IF(LARGE($R39:$T39,1)<=499,"400-499 мм",IF(LARGE($R39:$T39,1)<=599,"500-599 мм",IF(LARGE($R39:$T39,1)<=699,"600-699 мм",IF(LARGE($R39:$T39,1)<=999,"700-999 мм","1000+ мм"))))))))) -> 700-999 мм | Y39: =IF(LARGE($R39:$T39,2)="","",IF(LARGE($R39:$T39,2)<=99,"10-99 мм",IF(LARGE($R39:$T39,2)<=199,"100-199 мм",IF(LARGE($R39:$T39,2)<=299,"200-299 мм",IF(LARGE($R39:$T39,2)<=399,"300-399 мм",IF(LARGE($R39:$T39,2)<=499,"400-499 мм",IF(LARGE($R39:$T39,2)<=599,"500-599 мм",IF(LARGE($R39:$T39,2)<=699,"600-699 мм",IF(LARGE($R39:$T39,2)<=999,"700-999 мм","1000+ мм"))))))))) -> 100-199 мм | Z39: =IF(SMALL($R39:$T39,1)="","",IF(SMALL($R39:$T39,1)<=99,"10-99 мм",IF(SMALL($R39:$T39,1)<=199,"100-199 мм",IF(SMALL($R39:$T39,1)<=299,"200-299 мм",IF(SMALL($R39:$T39,1)<=399,"300-399 мм",IF(SMALL($R39:$T39,1)<=499,"400-499 мм",IF(SMALL($R39:$T39,1)<=599,"500-599 мм",IF(SMALL($R39:$T39,1)<=699,"600-699 мм",IF(SMALL($R39:$T39,1)<=999,"700-999 мм","1000+ мм"))))))))) -> 100-199 мм | AA39: =IF(G39="","",IF(G39="Л","Лист гофрокартона",IF(G39="КД","Крышка-дно",IF(G39="С","Самосборные",IF(G39="Ч","Четырехклапанные",IF(G39="А","Архивные","Неизвестно")))))) -> Самосборные | AB39: 1.73 | AC39: =IF(O39="","",IF(O39<=1,"0-1 литров",IF(O39<=3,"2-3 литра",IF(O39<=5,"4-5 литра",IF(O39<=7,"6-7 литра",IF(O39<=9,"8-9 литров",IF(O39<=14,"10-14 литров",IF(O39<=19,"15-19 литров",IF(O39<=29,"20-29 литров",IF(O39<=49,"30-49 литров",IF(O39<=59,"50-59 литров",IF(O39<=70,"60-69 литров",IF(O39<=79,"70-79 литров",IF(O39<=89,"80-89 литров",IF(O39<=99,"90-99 литров",IF(O39<=200,"100-200 литров","200+ литров")))))))))))))))) -> 10-14 литров
A40: 0.63 | B40: =A40*1.2 -> 0.756 | C40: 40 | D40: У | E40: 55х55х425 | G40: С | H40: 0215 | I40: В | J40: х | K40: K40 | N40: =IF(D40="","",IF(LEFT(D40,1)="0",0,1)) -> 1 | O40: =ROUND(R40*S40*T40/1000000,2) -> 1.29 | P40: =IF(O40="","", IF(O40<1,"0,1-0,9 литров", IF(O40<2,"1-1,9 литра", IF(O40<3,"2-2,9 литра", IF(O40<4,"3-3,9 литра", IF(O40<6,"4-5,9 литра",IF(O40<8,"6-7,9 литра",IF(O40<10,"8-9,9 литров",IF(O40<15,"10-14,9 литров",IF(O40<20,"15-19,9 литров",IF(O40<30,"20-29 литров",IF(O40<50,"30-49 литров",IF(O40<60,"50-59 литров",IF(O40<70,"60-69 литров",IF(O40<80,"70-79 литров",IF(O40<90,"80-89 литров",IF(O40<100,"90-99 литров",IF(O40<200,"100-200 литров","200+ литров")))))))))))))))))) -> 1-1,9 литра | Q40: =IF(O40="","",IF(O40<1,"<1 л",IF(O40<2,"1-2 л",IF(O40<3,"2-3 л",IF(O40<5,"3-5 л",IF(O40<10,"5-10 л",IF(O40<20,"10-20 л",IF(O40<50,"20-50 л",IF(O40<100,"50-100 л","100+ л"))))))))) -> 1-2 л | R40: =IF(E40="","",--LEFT(E40,FIND("х",E40)-1)) -> 55 | S40: =IF(E40="","",--MID(E40,FIND("х",E40)+1,FIND("х",E40,FIND("х",E40)+1)-FIND("х",E40)-1)) -> 55 | T40: =IF(E40="","",--RIGHT(E40,LEN(E40)-FIND("х",E40,FIND("х",E40)+1))) -> 425 | U40: =(2*(R40+S40)+60)*(S40+T40+8)/1000000 -> 0.13664 | V40: =IF(OR(AND(R40>=2*S40,R40>=2*T40),AND(S40>=2*R40,S40>=2*T40),AND(T40>=2*R40,T40>=2*S40)),"Длинные","") -> Длинные | W40: =IF(OR(AND(R40<=S40/2,R40<=T40/2),AND(S40<=R40/2,S40<=T40/2),AND(T40<=R40/2,T40<=S40/2)),"Плоские","") | X40: =IF(LARGE($R40:$T40,1)="","",IF(LARGE($R40:$T40,1)<=99,"10-99 мм",IF(LARGE($R40:$T40,1)<=199,"100-199 мм",IF(LARGE($R40:$T40,1)<=299,"200-299 мм",IF(LARGE($R40:$T40,1)<=399,"300-399 мм",IF(LARGE($R40:$T40,1)<=499,"400-499 мм",IF(LARGE($R40:$T40,1)<=599,"500-599 мм",IF(LARGE($R40:$T40,1)<=699,"600-699 мм",IF(LARGE($R40:$T40,1)<=999,"700-999 мм","1000+ мм"))))))))) -> 400-499 мм | Y40: =IF(LARGE($R40:$T40,2)="","",IF(LARGE($R40:$T40,2)<=99,"10-99 мм",IF(LARGE($R40:$T40,2)<=199,"100-199 мм",IF(LARGE($R40:$T40,2)<=299,"200-299 мм",IF(LARGE($R40:$T40,2)<=399,"300-399 мм",IF(LARGE($R40:$T40,2)<=499,"400-499 мм",IF(LARGE($R40:$T40,2)<=599,"500-599 мм",IF(LARGE($R40:$T40,2)<=699,"600-699 мм",IF(LARGE($R40:$T40,2)<=999,"700-999 мм","1000+ мм"))))))))) -> 10-99 мм | Z40: =IF(SMALL($R40:$T40,1)="","",IF(SMALL($R40:$T40,1)<=99,"10-99 мм",IF(SMALL($R40:$T40,1)<=199,"100-199 мм",IF(SMALL($R40:$T40,1)<=299,"200-299 мм",IF(SMALL($R40:$T40,1)<=399,"300-399 мм",IF(SMALL($R40:$T40,1)<=499,"400-499 мм",IF(SMALL($R40:$T40,1)<=599,"500-599 мм",IF(SMALL($R40:$T40,1)<=699,"600-699 мм",IF(SMALL($R40:$T40,1)<=999,"700-999 мм","1000+ мм"))))))))) -> 10-99 мм | AA40: =IF(G40="","",IF(G40="Л","Лист гофрокартона",IF(G40="КД","Крышка-дно",IF(G40="С","Самосборные",IF(G40="Ч","Четырехклапанные",IF(G40="А","Архивные","Неизвестно")))))) -> Самосборные | AB40: 1.73 | AC40: =IF(O40="","",IF(O40<=1,"0-1 литров",IF(O40<=3,"2-3 литра",IF(O40<=5,"4-5 литра",IF(O40<=7,"6-7 литра",IF(O40<=9,"8-9 литров",IF(O40<=14,"10-14 литров",IF(O40<=19,"15-19 литров",IF(O40<=29,"20-29 литров",IF(O40<=49,"30-49 литров",IF(O40<=59,"50-59 литров",IF(O40<=70,"60-69 литров",IF(O40<=79,"70-79 литров",IF(O40<=89,"80-89 литров",IF(O40<=99,"90-99 литров",IF(O40<=200,"100-200 литров","200+ литров")))))))))))))))) -> 2-3 литра
A41: 0.6 | B41: =A41*1.2 -> 0.72 | C41: 41 | D41: У | E41: 245х140х110 | G41: С | H41: 0427 | I41: В | J41: х | K41: K41 | N41: =IF(D41="","",IF(LEFT(D41,1)="0",0,1)) -> 1 | O41: =ROUND(R41*S41*T41/1000000,2) -> 3.77 | P41: =IF(O41="","", IF(O41<1,"0,1-0,9 литров", IF(O41<2,"1-1,9 литра", IF(O41<3,"2-2,9 литра", IF(O41<4,"3-3,9 литра", IF(O41<6,"4-5,9 литра",IF(O41<8,"6-7,9 литра",IF(O41<10,"8-9,9 литров",IF(O41<15,"10-14,9 литров",IF(O41<20,"15-19,9 литров",IF(O41<30,"20-29 литров",IF(O41<50,"30-49 литров",IF(O41<60,"50-59 литров",IF(O41<70,"60-69 литров",IF(O41<80,"70-79 литров",IF(O41<90,"80-89 литров",IF(O41<100,"90-99 литров",IF(O41<200,"100-200 литров","200+ литров")))))))))))))))))) -> 3-3,9 литра | Q41: =IF(O41="","",IF(O41<1,"<1 л",IF(O41<2,"1-2 л",IF(O41<3,"2-3 л",IF(O41<5,"3-5 л",IF(O41<10,"5-10 л",IF(O41<20,"10-20 л",IF(O41<50,"20-50 л",IF(O41<100,"50-100 л","100+ л"))))))))) -> 3-5 л | R41: =IF(E41="","",--LEFT(E41,FIND("х",E41)-1)) -> 245 | S41: =IF(E41="","",--MID(E41,FIND("х",E41)+1,FIND("х",E41,FIND("х",E41)+1)-FIND("х",E41)-1)) -> 140 | T41: =IF(E41="","",--RIGHT(E41,LEN(E41)-FIND("х",E41,FIND("х",E41)+1))) -> 110 | U41: =(2*(R41+S41)+60)*(S41+T41+8)/1000000 -> 0.21414 | V41: =IF(OR(AND(R41>=2*S41,R41>=2*T41),AND(S41>=2*R41,S41>=2*T41),AND(T41>=2*R41,T41>=2*S41)),"Длинные","") | W41: =IF(OR(AND(R41<=S41/2,R41<=T41/2),AND(S41<=R41/2,S41<=T41/2),AND(T41<=R41/2,T41<=S41/2)),"Плоские","") | X41: =IF(LARGE($R41:$T41,1)="","",IF(LARGE($R41:$T41,1)<=99,"10-99 мм",IF(LARGE($R41:$T41,1)<=199,"100-199 мм",IF(LARGE($R41:$T41,1)<=299,"200-299 мм",IF(LARGE($R41:$T41,1)<=399,"300-399 мм",IF(LARGE($R41:$T41,1)<=499,"400-499 мм",IF(LARGE($R41:$T41,1)<=599,"500-599 мм",IF(LARGE($R41:$T41,1)<=699,"600-699 мм",IF(LARGE($R41:$T41,1)<=999,"700-999 мм","1000+ мм"))))))))) -> 200-299 мм | Y41: =IF(LARGE($R41:$T41,2)="","",IF(LARGE($R41:$T41,2)<=99,"10-99 мм",IF(LARGE($R41:$T41,2)<=199,"100-199 мм",IF(LARGE($R41:$T41,2)<=299,"200-299 мм",IF(LARGE($R41:$T41,2)<=399,"300-399 мм",IF(LARGE($R41:$T41,2)<=499,"400-499 мм",IF(LARGE($R41:$T41,2)<=599,"500-599 мм",IF(LARGE($R41:$T41,2)<=699,"600-699 мм",IF(LARGE($R41:$T41,2)<=999,"700-999 мм","1000+ мм"))))))))) -> 100-199 мм | Z41: =IF(SMALL($R41:$T41,1)="","",IF(SMALL($R41:$T41,1)<=99,"10-99 мм",IF(SMALL($R41:$T41,1)<=199,"100-199 мм",IF(SMALL($R41:$T41,1)<=299,"200-299 мм",IF(SMALL($R41:$T41,1)<=399,"300-399 мм",IF(SMALL($R41:$T41,1)<=499,"400-499 мм",IF(SMALL($R41:$T41,1)<=599,"500-599 мм",IF(SMALL($R41:$T41,1)<=699,"600-699 мм",IF(SMALL($R41:$T41,1)<=999,"700-999 мм","1000+ мм"))))))))) -> 100-199 мм | AA41: =IF(G41="","",IF(G41="Л","Лист гофрокартона",IF(G41="КД","Крышка-дно",IF(G41="С","Самосборные",IF(G41="Ч","Четырехклапанные",IF(G41="А","Архивные","Неизвестно")))))) -> Самосборные | AB41: 1.73 | AC41: =IF(O41="","",IF(O41<=1,"0-1 литров",IF(O41<=3,"2-3 литра",IF(O41<=5,"4-5 литра",IF(O41<=7,"6-7 литра",IF(O41<=9,"8-9 литров",IF(O41<=14,"10-14 литров",IF(O41<=19,"15-19 литров",IF(O41<=29,"20-29 литров",IF(O41<=49,"30-49 литров",IF(O41<=59,"50-59 литров",IF(O41<=70,"60-69 литров",IF(O41<=79,"70-79 литров",IF(O41<=89,"80-89 литров",IF(O41<=99,"90-99 литров",IF(O41<=200,"100-200 литров","200+ литров")))))))))))))))) -> 4-5 литра
A42: 1 | B42: =A42*1.2 -> 1.2 | C42: 42 | D42: У | E42: 450х220х192 | G42: С | H42: 0201 | I42: В | J42: х | K42: K42 | N42: =IF(D42="","",IF(LEFT(D42,1)="0",0,1)) -> 1 | O42: =ROUND(R42*S42*T42/1000000,2) -> 19.01 | P42: =IF(O42="","", IF(O42<1,"0,1-0,9 литров", IF(O42<2,"1-1,9 литра", IF(O42<3,"2-2,9 литра", IF(O42<4,"3-3,9 литра", IF(O42<6,"4-5,9 литра",IF(O42<8,"6-7,9 литра",IF(O42<10,"8-9,9 литров",IF(O42<15,"10-14,9 литров",IF(O42<20,"15-19,9 литров",IF(O42<30,"20-29 литров",IF(O42<50,"30-49 литров",IF(O42<60,"50-59 литров",IF(O42<70,"60-69 литров",IF(O42<80,"70-79 литров",IF(O42<90,"80-89 литров",IF(O42<100,"90-99 литров",IF(O42<200,"100-200 литров","200+ литров")))))))))))))))))) -> 15-19,9 литров | Q42: =IF(O42="","",IF(O42<1,"<1 л",IF(O42<2,"1-2 л",IF(O42<3,"2-3 л",IF(O42<5,"3-5 л",IF(O42<10,"5-10 л",IF(O42<20,"10-20 л",IF(O42<50,"20-50 л",IF(O42<100,"50-100 л","100+ л"))))))))) -> 10-20 л | R42: =IF(E42="","",--LEFT(E42,FIND("х",E42)-1)) -> 450 | S42: =IF(E42="","",--MID(E42,FIND("х",E42)+1,FIND("х",E42,FIND("х",E42)+1)-FIND("х",E42)-1)) -> 220 | T42: =IF(E42="","",--RIGHT(E42,LEN(E42)-FIND("х",E42,FIND("х",E42)+1))) -> 192 | U42: =(2*(R42+S42)+60)*(S42+T42+8)/1000000 -> 0.588 | V42: =IF(OR(AND(R42>=2*S42,R42>=2*T42),AND(S42>=2*R42,S42>=2*T42),AND(T42>=2*R42,T42>=2*S42)),"Длинные","") -> Длинные | W42: =IF(OR(AND(R42<=S42/2,R42<=T42/2),AND(S42<=R42/2,S42<=T42/2),AND(T42<=R42/2,T42<=S42/2)),"Плоские","") | X42: =IF(LARGE($R42:$T42,1)="","",IF(LARGE($R42:$T42,1)<=99,"10-99 мм",IF(LARGE($R42:$T42,1)<=199,"100-199 мм",IF(LARGE($R42:$T42,1)<=299,"200-299 мм",IF(LARGE($R42:$T42,1)<=399,"300-399 мм",IF(LARGE($R42:$T42,1)<=499,"400-499 мм",IF(LARGE($R42:$T42,1)<=599,"500-599 мм",IF(LARGE($R42:$T42,1)<=699,"600-699 мм",IF(LARGE($R42:$T42,1)<=999,"700-999 мм","1000+ мм"))))))))) -> 400-499 мм | Y42: =IF(LARGE($R42:$T42,2)="","",IF(LARGE($R42:$T42,2)<=99,"10-99 мм",IF(LARGE($R42:$T42,2)<=199,"100-199 мм",IF(LARGE($R42:$T42,2)<=299,"200-299 мм",IF(LARGE($R42:$T42,2)<=399,"300-399 мм",IF(LARGE($R42:$T42,2)<=499,"400-499 мм",IF(LARGE($R42:$T42,2)<=599,"500-599 мм",IF(LARGE($R42:$T42,2)<=699,"600-699 мм",IF(LARGE($R42:$T42,2)<=999,"700-999 мм","1000+ мм"))))))))) -> 200-299 мм | Z42: =IF(SMALL($R42:$T42,1)="","",IF(SMALL($R42:$T42,1)<=99,"10-99 мм",IF(SMALL($R42:$T42,1)<=199,"100-199 мм",IF(SMALL($R42:$T42,1)<=299,"200-299 мм",IF(SMALL($R42:$T42,1)<=399,"300-399 мм",IF(SMALL($R42:$T42,1)<=499,"400-499 мм",IF(SMALL($R42:$T42,1)<=599,"500-599 мм",IF(SMALL($R42:$T42,1)<=699,"600-699 мм",IF(SMALL($R42:$T42,1)<=999,"700-999 мм","1000+ мм"))))))))) -> 100-199 мм | AA42: =IF(G42="","",IF(G42="Л","Лист гофрокартона",IF(G42="КД","Крышка-дно",IF(G42="С","Самосборные",IF(G42="Ч","Четырехклапанные",IF(G42="А","Архивные","Неизвестно")))))) -> Самосборные | AB42: 1.73 | AC42: =IF(O42="","",IF(O42<=1,"0-1 литров",IF(O42<=3,"2-3 литра",IF(O42<=5,"4-5 литра",IF(O42<=7,"6-7 литра",IF(O42<=9,"8-9 литров",IF(O42<=14,"10-14 литров",IF(O42<=19,"15-19 литров",IF(O42<=29,"20-29 литров",IF(O42<=49,"30-49 литров",IF(O42<=59,"50-59 литров",IF(O42<=70,"60-69 литров",IF(O42<=79,"70-79 литров",IF(O42<=89,"80-89 литров",IF(O42<=99,"90-99 литров",IF(O42<=200,"100-200 литров","200+ литров")))))))))))))))) -> 20-29 литров
A43: 0.53 | B43: =A43*1.2 -> 0.636 | C43: 43 | D43: У | E43: 200х80х100 | G43: С | H43: 0215 | I43: В | J43: х | K43: K43 | N43: =IF(D43="","",IF(LEFT(D43,1)="0",0,1)) -> 1 | O43: =ROUND(R43*S43*T43/1000000,2) -> 1.6 | P43: =IF(O43="","", IF(O43<1,"0,1-0,9 литров", IF(O43<2,"1-1,9 литра", IF(O43<3,"2-2,9 литра", IF(O43<4,"3-3,9 литра", IF(O43<6,"4-5,9 литра",IF(O43<8,"6-7,9 литра",IF(O43<10,"8-9,9 литров",IF(O43<15,"10-14,9 литров",IF(O43<20,"15-19,9 литров",IF(O43<30,"20-29 литров",IF(O43<50,"30-49 литров",IF(O43<60,"50-59 литров",IF(O43<70,"60-69 литров",IF(O43<80,"70-79 литров",IF(O43<90,"80-89 литров",IF(O43<100,"90-99 литров",IF(O43<200,"100-200 литров","200+ литров")))))))))))))))))) -> 1-1,9 литра | Q43: =IF(O43="","",IF(O43<1,"<1 л",IF(O43<2,"1-2 л",IF(O43<3,"2-3 л",IF(O43<5,"3-5 л",IF(O43<10,"5-10 л",IF(O43<20,"10-20 л",IF(O43<50,"20-50 л",IF(O43<100,"50-100 л","100+ л"))))))))) -> 1-2 л | R43: =IF(E43="","",--LEFT(E43,FIND("х",E43)-1)) -> 200 | S43: =IF(E43="","",--MID(E43,FIND("х",E43)+1,FIND("х",E43,FIND("х",E43)+1)-FIND("х",E43)-1)) -> 80 | T43: =IF(E43="","",--RIGHT(E43,LEN(E43)-FIND("х",E43,FIND("х",E43)+1))) -> 100 | U43: =(2*(R43+S43)+60)*(S43+T43+8)/1000000 -> 0.11656 | V43: =IF(OR(AND(R43>=2*S43,R43>=2*T43),AND(S43>=2*R43,S43>=2*T43),AND(T43>=2*R43,T43>=2*S43)),"Длинные","") -> Длинные | W43: =IF(OR(AND(R43<=S43/2,R43<=T43/2),AND(S43<=R43/2,S43<=T43/2),AND(T43<=R43/2,T43<=S43/2)),"Плоские","") | X43: =IF(LARGE($R43:$T43,1)="","",IF(LARGE($R43:$T43,1)<=99,"10-99 мм",IF(LARGE($R43:$T43,1)<=199,"100-199 мм",IF(LARGE($R43:$T43,1)<=299,"200-299 мм",IF(LARGE($R43:$T43,1)<=399,"300-399 мм",IF(LARGE($R43:$T43,1)<=499,"400-499 мм",IF(LARGE($R43:$T43,1)<=599,"500-599 мм",IF(LARGE($R43:$T43,1)<=699,"600-699 мм",IF(LARGE($R43:$T43,1)<=999,"700-999 мм","1000+ мм"))))))))) -> 200-299 мм | Y43: =IF(LARGE($R43:$T43,2)="","",IF(LARGE($R43:$T43,2)<=99,"10-99 мм",IF(LARGE($R43:$T43,2)<=199,"100-199 мм",IF(LARGE($R43:$T43,2)<=299,"200-299 мм",IF(LARGE($R43:$T43,2)<=399,"300-399 мм",IF(LARGE($R43:$T43,2)<=499,"400-499 мм",IF(LARGE($R43:$T43,2)<=599,"500-599 мм",IF(LARGE($R43:$T43,2)<=699,"600-699 мм",IF(LARGE($R43:$T43,2)<=999,"700-999 мм","1000+ мм"))))))))) -> 100-199 мм | Z43: =IF(SMALL($R43:$T43,1)="","",IF(SMALL($R43:$T43,1)<=99,"10-99 мм",IF(SMALL($R43:$T43,1)<=199,"100-199 мм",IF(SMALL($R43:$T43,1)<=299,"200-299 мм",IF(SMALL($R43:$T43,1)<=399,"300-399 мм",IF(SMALL($R43:$T43,1)<=499,"400-499 мм",IF(SMALL($R43:$T43,1)<=599,"500-599 мм",IF(SMALL($R43:$T43,1)<=699,"600-699 мм",IF(SMALL($R43:$T43,1)<=999,"700-999 мм","1000+ мм"))))))))) -> 10-99 мм | AA43: =IF(G43="","",IF(G43="Л","Лист гофрокартона",IF(G43="КД","Крышка-дно",IF(G43="С","Самосборные",IF(G43="Ч","Четырехклапанные",IF(G43="А","Архивные","Неизвестно")))))) -> Самосборные | AB43: 1.73 | AC43: =IF(O43="","",IF(O43<=1,"0-1 литров",IF(O43<=3,"2-3 литра",IF(O43<=5,"4-5 литра",IF(O43<=7,"6-7 литра",IF(O43<=9,"8-9 литров",IF(O43<=14,"10-14 литров",IF(O43<=19,"15-19 литров",IF(O43<=29,"20-29 литров",IF(O43<=49,"30-49 литров",IF(O43<=59,"50-59 литров",IF(O43<=70,"60-69 литров",IF(O43<=79,"70-79 литров",IF(O43<=89,"80-89 литров",IF(O43<=99,"90-99 литров",IF(O43<=200,"100-200 литров","200+ литров")))))))))))))))) -> 2-3 литра
A44: 1.7 | B44: =A44*1.2 -> 2.04 | C44: 44 | D44: У | E44: 573х333х85 | G44: С | H44: 0427 | I44: В | J44: х | K44: K44 | N44: =IF(D44="","",IF(LEFT(D44,1)="0",0,1)) -> 1 | O44: =ROUND(R44*S44*T44/1000000,2) -> 16.22 | P44: =IF(O44="","", IF(O44<1,"0,1-0,9 литров", IF(O44<2,"1-1,9 литра", IF(O44<3,"2-2,9 литра", IF(O44<4,"3-3,9 литра", IF(O44<6,"4-5,9 литра",IF(O44<8,"6-7,9 литра",IF(O44<10,"8-9,9 литров",IF(O44<15,"10-14,9 литров",IF(O44<20,"15-19,9 литров",IF(O44<30,"20-29 литров",IF(O44<50,"30-49 литров",IF(O44<60,"50-59 литров",IF(O44<70,"60-69 литров",IF(O44<80,"70-79 литров",IF(O44<90,"80-89 литров",IF(O44<100,"90-99 литров",IF(O44<200,"100-200 литров","200+ литров")))))))))))))))))) -> 15-19,9 литров | Q44: =IF(O44="","",IF(O44<1,"<1 л",IF(O44<2,"1-2 л",IF(O44<3,"2-3 л",IF(O44<5,"3-5 л",IF(O44<10,"5-10 л",IF(O44<20,"10-20 л",IF(O44<50,"20-50 л",IF(O44<100,"50-100 л","100+ л"))))))))) -> 10-20 л | R44: =IF(E44="","",--LEFT(E44,FIND("х",E44)-1)) -> 573 | S44: =IF(E44="","",--MID(E44,FIND("х",E44)+1,FIND("х",E44,FIND("х",E44)+1)-FIND("х",E44)-1)) -> 333 | T44: =IF(E44="","",--RIGHT(E44,LEN(E44)-FIND("х",E44,FIND("х",E44)+1))) -> 85 | U44: =(2*(R44+S44)+60)*(S44+T44+8)/1000000 -> 0.797472 | V44: =IF(OR(AND(R44>=2*S44,R44>=2*T44),AND(S44>=2*R44,S44>=2*T44),AND(T44>=2*R44,T44>=2*S44)),"Длинные","") | W44: =IF(OR(AND(R44<=S44/2,R44<=T44/2),AND(S44<=R44/2,S44<=T44/2),AND(T44<=R44/2,T44<=S44/2)),"Плоские","") -> Плоские | X44: =IF(LARGE($R44:$T44,1)="","",IF(LARGE($R44:$T44,1)<=99,"10-99 мм",IF(LARGE($R44:$T44,1)<=199,"100-199 мм",IF(LARGE($R44:$T44,1)<=299,"200-299 мм",IF(LARGE($R44:$T44,1)<=399,"300-399 мм",IF(LARGE($R44:$T44,1)<=499,"400-499 мм",IF(LARGE($R44:$T44,1)<=599,"500-599 мм",IF(LARGE($R44:$T44,1)<=699,"600-699 мм",IF(LARGE($R44:$T44,1)<=999,"700-999 мм","1000+ мм"))))))))) -> 500-599 мм | Y44: =IF(LARGE($R44:$T44,2)="","",IF(LARGE($R44:$T44,2)<=99,"10-99 мм",IF(LARGE($R44:$T44,2)<=199,"100-199 мм",IF(LARGE($R44:$T44,2)<=299,"200-299 мм",IF(LARGE($R44:$T44,2)<=399,"300-399 мм",IF(LARGE($R44:$T44,2)<=499,"400-499 мм",IF(LARGE($R44:$T44,2)<=599,"500-599 мм",IF(LARGE($R44:$T44,2)<=699,"600-699 мм",IF(LARGE($R44:$T44,2)<=999,"700-999 мм","1000+ мм"))))))))) -> 300-399 мм | Z44: =IF(SMALL($R44:$T44,1)="","",IF(SMALL($R44:$T44,1)<=99,"10-99 мм",IF(SMALL($R44:$T44,1)<=199,"100-199 мм",IF(SMALL($R44:$T44,1)<=299,"200-299 мм",IF(SMALL($R44:$T44,1)<=399,"300-399 мм",IF(SMALL($R44:$T44,1)<=499,"400-499 мм",IF(SMALL($R44:$T44,1)<=599,"500-599 мм",IF(SMALL($R44:$T44,1)<=699,"600-699 мм",IF(SMALL($R44:$T44,1)<=999,"700-999 мм","1000+ мм"))))))))) -> 10-99 мм | AA44: =IF(G44="","",IF(G44="Л","Лист гофрокартона",IF(G44="КД","Крышка-дно",IF(G44="С","Самосборные",IF(G44="Ч","Четырехклапанные",IF(G44="А","Архивные","Неизвестно")))))) -> Самосборные | AB44: 1.73 | AC44: =IF(O44="","",IF(O44<=1,"0-1 литров",IF(O44<=3,"2-3 литра",IF(O44<=5,"4-5 литра",IF(O44<=7,"6-7 литра",IF(O44<=9,"8-9 литров",IF(O44<=14,"10-14 литров",IF(O44<=19,"15-19 литров",IF(O44<=29,"20-29 литров",IF(O44<=49,"30-49 литров",IF(O44<=59,"50-59 литров",IF(O44<=70,"60-69 литров",IF(O44<=79,"70-79 литров",IF(O44<=89,"80-89 литров",IF(O44<=99,"90-99 литров",IF(O44<=200,"100-200 литров","200+ литров")))))))))))))))) -> 15-19 литров
A45: 0.85 | B45: =A45*1.2 -> 1.02 | C45: 45 | D45: У | E45: 380х155х125 | G45: С | H45: 0215 | I45: В | J45: х | K45: K45 | N45: =IF(D45="","",IF(LEFT(D45,1)="0",0,1)) -> 1 | O45: =ROUND(R45*S45*T45/1000000,2) -> 7.36 | P45: =IF(O45="","", IF(O45<1,"0,1-0,9 литров", IF(O45<2,"1-1,9 литра", IF(O45<3,"2-2,9 литра", IF(O45<4,"3-3,9 литра", IF(O45<6,"4-5,9 литра",IF(O45<8,"6-7,9 литра",IF(O45<10,"8-9,9 литров",IF(O45<15,"10-14,9 литров",IF(O45<20,"15-19,9 литров",IF(O45<30,"20-29 литров",IF(O45<50,"30-49 литров",IF(O45<60,"50-59 литров",IF(O45<70,"60-69 литров",IF(O45<80,"70-79 литров",IF(O45<90,"80-89 литров",IF(O45<100,"90-99 литров",IF(O45<200,"100-200 литров","200+ литров")))))))))))))))))) -> 6-7,9 литра | Q45: =IF(O45="","",IF(O45<1,"<1 л",IF(O45<2,"1-2 л",IF(O45<3,"2-3 л",IF(O45<5,"3-5 л",IF(O45<10,"5-10 л",IF(O45<20,"10-20 л",IF(O45<50,"20-50 л",IF(O45<100,"50-100 л","100+ л"))))))))) -> 5-10 л | R45: =IF(E45="","",--LEFT(E45,FIND("х",E45)-1)) -> 380 | S45: =IF(E45="","",--MID(E45,FIND("х",E45)+1,FIND("х",E45,FIND("х",E45)+1)-FIND("х",E45)-1)) -> 155 | T45: =IF(E45="","",--RIGHT(E45,LEN(E45)-FIND("х",E45,FIND("х",E45)+1))) -> 125 | U45: =(2*(R45+S45)+60)*(S45+T45+8)/1000000 -> 0.32544 | V45: =IF(OR(AND(R45>=2*S45,R45>=2*T45),AND(S45>=2*R45,S45>=2*T45),AND(T45>=2*R45,T45>=2*S45)),"Длинные","") -> Длинные | W45: =IF(OR(AND(R45<=S45/2,R45<=T45/2),AND(S45<=R45/2,S45<=T45/2),AND(T45<=R45/2,T45<=S45/2)),"Плоские","") | X45: =IF(LARGE($R45:$T45,1)="","",IF(LARGE($R45:$T45,1)<=99,"10-99 мм",IF(LARGE($R45:$T45,1)<=199,"100-199 мм",IF(LARGE($R45:$T45,1)<=299,"200-299 мм",IF(LARGE($R45:$T45,1)<=399,"300-399 мм",IF(LARGE($R45:$T45,1)<=499,"400-499 мм",IF(LARGE($R45:$T45,1)<=599,"500-599 мм",IF(LARGE($R45:$T45,1)<=699,"600-699 мм",IF(LARGE($R45:$T45,1)<=999,"700-999 мм","1000+ мм"))))))))) -> 300-399 мм | Y45: =IF(LARGE($R45:$T45,2)="","",IF(LARGE($R45:$T45,2)<=99,"10-99 мм",IF(LARGE($R45:$T45,2)<=199,"100-199 мм",IF(LARGE($R45:$T45,2)<=299,"200-299 мм",IF(LARGE($R45:$T45,2)<=399,"300-399 мм",IF(LARGE($R45:$T45,2)<=499,"400-499 мм",IF(LARGE($R45:$T45,2)<=599,"500-599 мм",IF(LARGE($R45:$T45,2)<=699,"600-699 мм",IF(LARGE($R45:$T45,2)<=999,"700-999 мм","1000+ мм"))))))))) -> 100-199 мм | Z45: =IF(SMALL($R45:$T45,1)="","",IF(SMALL($R45:$T45,1)<=99,"10-99 мм",IF(SMALL($R45:$T45,1)<=199,"100-199 мм",IF(SMALL($R45:$T45,1)<=299,"200-299 мм",IF(SMALL($R45:$T45,1)<=399,"300-399 мм",IF(SMALL($R45:$T45,1)<=499,"400-499 мм",IF(SMALL($R45:$T45,1)<=599,"500-599 мм",IF(SMALL($R45:$T45,1)<=699,"600-699 мм",IF(SMALL($R45:$T45,1)<=999,"700-999 мм","1000+ мм"))))))))) -> 100-199 мм | AA45: =IF(G45="","",IF(G45="Л","Лист гофрокартона",IF(G45="КД","Крышка-дно",IF(G45="С","Самосборные",IF(G45="Ч","Четырехклапанные",IF(G45="А","Архивные","Неизвестно")))))) -> Самосборные | AB45: 1.73 | AC45: =IF(O45="","",IF(O45<=1,"0-1 литров",IF(O45<=3,"2-3 литра",IF(O45<=5,"4-5 литра",IF(O45<=7,"6-7 литра",IF(O45<=9,"8-9 литров",IF(O45<=14,"10-14 литров",IF(O45<=19,"15-19 литров",IF(O45<=29,"20-29 литров",IF(O45<=49,"30-49 литров",IF(O45<=59,"50-59 литров",IF(O45<=70,"60-69 литров",IF(O45<=79,"70-79 литров",IF(O45<=89,"80-89 литров",IF(O45<=99,"90-99 литров",IF(O45<=200,"100-200 литров","200+ литров")))))))))))))))) -> 8-9 литров
... A57: 2.01 | B57: =A57*1.2 -> 2.412 | C57: 57 | D57: У | E57: 440х330х386 | G57: Ч | H57: 0201 | I57: В | J57: х | K57: K57 | N57: =IF(D57="","",IF(LEFT(D57,1)="0",0,1)) -> 1 | O57: =ROUND(R57*S57*T57/1000000,2) -> 56.05 | P57: =IF(O57="","", IF(O57<1,"0,1-0,9 литров", IF(O57<2,"1-1,9 литра", IF(O57<3,"2-2,9 литра", IF(O57<4,"3-3,9 литра", IF(O57<6,"4-5,9 литра",IF(O57<8,"6-7,9 литра",IF(O57<10,"8-9,9 литров",IF(O57<15,"10-14,9 литров",IF(O57<20,"15-19,9 литров",IF(O57<30,"20-29 литров",IF(O57<50,"30-49 литров",IF(O57<60,"50-59 литров",IF(O57<70,"60-69 литров",IF(O57<80,"70-79 литров",IF(O57<90,"80-89 литров",IF(O57<100,"90-99 литров",IF(O57<200,"100-200 литров","200+ литров")))))))))))))))))) -> 50-59 литров | Q57: =IF(O57="","",IF(O57<1,"<1 л",IF(O57<2,"1-2 л",IF(O57<3,"2-3 л",IF(O57<5,"3-5 л",IF(O57<10,"5-10 л",IF(O57<20,"10-20 л",IF(O57<50,"20-50 л",IF(O57<100,"50-100 л","100+ л"))))))))) -> 50-100 л | R57: =IF(E57="","",--LEFT(E57,FIND("х",E57)-1)) -> 440 | S57: =IF(E57="","",--MID(E57,FIND("х",E57)+1,FIND("х",E57,FIND("х",E57)+1)-FIND("х",E57)-1)) -> 330 | T57: =IF(E57="","",--RIGHT(E57,LEN(E57)-FIND("х",E57,FIND("х",E57)+1))) -> 386 | U57: =(2*(R57+S57)+60)*(S57+T57+8)/1000000 -> 1.1584 | V57: =IF(OR(AND(R57>=2*S57,R57>=2*T57),AND(S57>=2*R57,S57>=2*T57),AND(T57>=2*R57,T57>=2*S57)),"Длинные","") | W57: =IF(OR(AND(R57<=S57/2,R57<=T57/2),AND(S57<=R57/2,S57<=T57/2),AND(T57<=R57/2,T57<=S57/2)),"Плоские","") | X57: =IF(LARGE($R57:$T57,1)="","",IF(LARGE($R57:$T57,1)<=99,"10-99 мм",IF(LARGE($R57:$T57,1)<=199,"100-199 мм",IF(LARGE($R57:$T57,1)<=299,"200-299 мм",IF(LARGE($R57:$T57,1)<=399,"300-399 мм",IF(LARGE($R57:$T57,1)<=499,"400-499 мм",IF(LARGE($R57:$T57,1)<=599,"500-599 мм",IF(LARGE($R57:$T57,1)<=699,"600-699 мм",IF(LARGE($R57:$T57,1)<=999,"700-999 мм","1000+ мм"))))))))) -> 400-499 мм | Y57: =IF(LARGE($R57:$T57,2)="","",IF(LARGE($R57:$T57,2)<=99,"10-99 мм",IF(LARGE($R57:$T57,2)<=199,"100-199 мм",IF(LARGE($R57:$T57,2)<=299,"200-299 мм",IF(LARGE($R57:$T57,2)<=399,"300-399 мм",IF(LARGE($R57:$T57,2)<=499,"400-499 мм",IF(LARGE($R57:$T57,2)<=599,"500-599 мм",IF(LARGE($R57:$T57,2)<=699,"600-699 мм",IF(LARGE($R57:$T57,2)<=999,"700-999 мм","1000+ мм"))))))))) -> 300-399 мм | Z57: =IF(SMALL($R57:$T57,1)="","",IF(SMALL($R57:$T57,1)<=99,"10-99 мм",IF(SMALL($R57:$T57,1)<=199,"100-199 мм",IF(SMALL($R57:$T57,1)<=299,"200-299 мм",IF(SMALL($R57:$T57,1)<=399,"300-399 мм",IF(SMALL($R57:$T57,1)<=499,"400-499 мм",IF(SMALL($R57:$T57,1)<=599,"500-599 мм",IF(SMALL($R57:$T57,1)<=699,"600-699 мм",IF(SMALL($R57:$T57,1)<=999,"700-999 мм","1000+ мм"))))))))) -> 300-399 мм | AA57: =IF(G57="","",IF(G57="Л","Лист гофрокартона",IF(G57="КД","Крышка-дно",IF(G57="С","Самосборные",IF(G57="Ч","Четырехклапанные",IF(G57="А","Архивные","Неизвестно")))))) -> Четырехклапанные | AB57: 1.73 | AC57: =IF(O57="","",IF(O57<=1,"0-1 литров",IF(O57<=3,"2-3 литра",IF(O57<=5,"4-5 литра",IF(O57<=7,"6-7 литра",IF(O57<=9,"8-9 литров",IF(O57<=14,"10-14 литров",IF(O57<=19,"15-19 литров",IF(O57<=29,"20-29 литров",IF(O57<=49,"30-49 литров",IF(O57<=59,"50-59 литров",IF(O57<=70,"60-69 литров",IF(O57<=79,"70-79 литров",IF(O57<=89,"80-89 литров",IF(O57<=99,"90-99 литров",IF(O57<=200,"100-200 литров","200+ литров")))))))))))))))) -> 50-59 литров
A58: 6.55 | B58: =A58*1.2 -> 7.86 | C58: 58 | D58: У | E58: 795х510х870 | F58: П32 | G58: Ч | H58: 0200 | I58: ВС | J58: х | K58: K58 | N58: =IF(D58="","",IF(LEFT(D58,1)="0",0,1)) -> 1 | O58: =ROUND(R58*S58*T58/1000000,2) -> 352.74 | P58: =IF(O58="","", IF(O58<1,"0,1-0,9 литров", IF(O58<2,"1-1,9 литра", IF(O58<3,"2-2,9 литра", IF(O58<4,"3-3,9 литра", IF(O58<6,"4-5,9 литра",IF(O58<8,"6-7,9 литра",IF(O58<10,"8-9,9 литров",IF(O58<15,"10-14,9 литров",IF(O58<20,"15-19,9 литров",IF(O58<30,"20-29 литров",IF(O58<50,"30-49 литров",IF(O58<60,"50-59 литров",IF(O58<70,"60-69 литров",IF(O58<80,"70-79 литров",IF(O58<90,"80-89 литров",IF(O58<100,"90-99 литров",IF(O58<200,"100-200 литров","200+ литров")))))))))))))))))) -> 200+ литров | Q58: =IF(O58="","",IF(O58<1,"<1 л",IF(O58<2,"1-2 л",IF(O58<3,"2-3 л",IF(O58<5,"3-5 л",IF(O58<10,"5-10 л",IF(O58<20,"10-20 л",IF(O58<50,"20-50 л",IF(O58<100,"50-100 л","100+ л"))))))))) -> 100+ л | R58: =IF(E58="","",--LEFT(E58,FIND("х",E58)-1)) -> 795 | S58: =IF(E58="","",--MID(E58,FIND("х",E58)+1,FIND("х",E58,FIND("х",E58)+1)-FIND("х",E58)-1)) -> 510 | T58: =IF(E58="","",--RIGHT(E58,LEN(E58)-FIND("х",E58,FIND("х",E58)+1))) -> 870 | U58: =(2*(R58+S58)+60)*(S58+T58+8)/1000000 -> 3.70596 | V58: =IF(OR(AND(R58>=2*S58,R58>=2*T58),AND(S58>=2*R58,S58>=2*T58),AND(T58>=2*R58,T58>=2*S58)),"Длинные","") | W58: =IF(OR(AND(R58<=S58/2,R58<=T58/2),AND(S58<=R58/2,S58<=T58/2),AND(T58<=R58/2,T58<=S58/2)),"Плоские","") | X58: =IF(LARGE($R58:$T58,1)="","",IF(LARGE($R58:$T58,1)<=99,"10-99 мм",IF(LARGE($R58:$T58,1)<=199,"100-199 мм",IF(LARGE($R58:$T58,1)<=299,"200-299 мм",IF(LARGE($R58:$T58,1)<=399,"300-399 мм",IF(LARGE($R58:$T58,1)<=499,"400-499 мм",IF(LARGE($R58:$T58,1)<=599,"500-599 мм",IF(LARGE($R58:$T58,1)<=699,"600-699 мм",IF(LARGE($R58:$T58,1)<=999,"700-999 мм","1000+ мм"))))))))) -> 700-999 мм | Y58: =IF(LARGE($R58:$T58,2)="","",IF(LARGE($R58:$T58,2)<=99,"10-99 мм",IF(LARGE($R58:$T58,2)<=199,"100-199 мм",IF(LARGE($R58:$T58,2)<=299,"200-299 мм",IF(LARGE($R58:$T58,2)<=399,"300-399 мм",IF(LARGE($R58:$T58,2)<=499,"400-499 мм",IF(LARGE($R58:$T58,2)<=599,"500-599 мм",IF(LARGE($R58:$T58,2)<=699,"600-699 мм",IF(LARGE($R58:$T58,2)<=999,"700-999 мм","1000+ мм"))))))))) -> 700-999 мм | Z58: =IF(SMALL($R58:$T58,1)="","",IF(SMALL($R58:$T58,1)<=99,"10-99 мм",IF(SMALL($R58:$T58,1)<=199,"100-199 мм",IF(SMALL($R58:$T58,1)<=299,"200-299 мм",IF(SMALL($R58:$T58,1)<=399,"300-399 мм",IF(SMALL($R58:$T58,1)<=499,"400-499 мм",IF(SMALL($R58:$T58,1)<=599,"500-599 мм",IF(SMALL($R58:$T58,1)<=699,"600-699 мм",IF(SMALL($R58:$T58,1)<=999,"700-999 мм","1000+ мм"))))))))) -> 500-599 мм | AA58: =IF(G58="","",IF(G58="Л","Лист гофрокартона",IF(G58="КД","Крышка-дно",IF(G58="С","Самосборные",IF(G58="Ч","Четырехклапанные",IF(G58="А","Архивные","Неизвестно")))))) -> Четырехклапанные | AB58: 1.73 | AC58: =IF(O58="","",IF(O58<=1,"0-1 литров",IF(O58<=3,"2-3 литра",IF(O58<=5,"4-5 литра",IF(O58<=7,"6-7 литра",IF(O58<=9,"8-9 литров",IF(O58<=14,"10-14 литров",IF(O58<=19,"15-19 литров",IF(O58<=29,"20-29 литров",IF(O58<=49,"30-49 литров",IF(O58<=59,"50-59 литров",IF(O58<=70,"60-69 литров",IF(O58<=79,"70-79 литров",IF(O58<=89,"80-89 литров",IF(O58<=99,"90-99 литров",IF(O58<=200,"100-200 литров","200+ литров")))))))))))))))) -> 200+ литров
A59: 7.76 | B59: =A59*1.2 -> 9.312 | C59: 59 | D59: У | E59: 795х510х870 | F59: + кр П32 | G59: Ч | H59: 0312 | I59: ВС | J59: х | K59: K59 | N59: =IF(D59="","",IF(LEFT(D59,1)="0",0,1)) -> 1 | O59: =ROUND(R59*S59*T59/1000000,2) -> 352.74 | P59: =IF(O59="","", IF(O59<1,"0,1-0,9 литров", IF(O59<2,"1-1,9 литра", IF(O59<3,"2-2,9 литра", IF(O59<4,"3-3,9 литра", IF(O59<6,"4-5,9 литра",IF(O59<8,"6-7,9 литра",IF(O59<10,"8-9,9 литров",IF(O59<15,"10-14,9 литров",IF(O59<20,"15-19,9 литров",IF(O59<30,"20-29 литров",IF(O59<50,"30-49 литров",IF(O59<60,"50-59 литров",IF(O59<70,"60-69 литров",IF(O59<80,"70-79 литров",IF(O59<90,"80-89 литров",IF(O59<100,"90-99 литров",IF(O59<200,"100-200 литров","200+ литров")))))))))))))))))) -> 200+ литров | Q59: =IF(O59="","",IF(O59<1,"<1 л",IF(O59<2,"1-2 л",IF(O59<3,"2-3 л",IF(O59<5,"3-5 л",IF(O59<10,"5-10 л",IF(O59<20,"10-20 л",IF(O59<50,"20-50 л",IF(O59<100,"50-100 л","100+ л"))))))))) -> 100+ л | R59: =IF(E59="","",--LEFT(E59,FIND("х",E59)-1)) -> 795 | S59: =IF(E59="","",--MID(E59,FIND("х",E59)+1,FIND("х",E59,FIND("х",E59)+1)-FIND("х",E59)-1)) -> 510 | T59: =IF(E59="","",--RIGHT(E59,LEN(E59)-FIND("х",E59,FIND("х",E59)+1))) -> 870 | U59: =(2*(R59+S59)+60)*(S59+T59+8)/1000000 -> 3.70596 | V59: =IF(OR(AND(R59>=2*S59,R59>=2*T59),AND(S59>=2*R59,S59>=2*T59),AND(T59>=2*R59,T59>=2*S59)),"Длинные","") | W59: =IF(OR(AND(R59<=S59/2,R59<=T59/2),AND(S59<=R59/2,S59<=T59/2),AND(T59<=R59/2,T59<=S59/2)),"Плоские","") | X59: =IF(LARGE($R59:$T59,1)="","",IF(LARGE($R59:$T59,1)<=99,"10-99 мм",IF(LARGE($R59:$T59,1)<=199,"100-199 мм",IF(LARGE($R59:$T59,1)<=299,"200-299 мм",IF(LARGE($R59:$T59,1)<=399,"300-399 мм",IF(LARGE($R59:$T59,1)<=499,"400-499 мм",IF(LARGE($R59:$T59,1)<=599,"500-599 мм",IF(LARGE($R59:$T59,1)<=699,"600-699 мм",IF(LARGE($R59:$T59,1)<=999,"700-999 мм","1000+ мм"))))))))) -> 700-999 мм | Y59: =IF(LARGE($R59:$T59,2)="","",IF(LARGE($R59:$T59,2)<=99,"10-99 мм",IF(LARGE($R59:$T59,2)<=199,"100-199 мм",IF(LARGE($R59:$T59,2)<=299,"200-299 мм",IF(LARGE($R59:$T59,2)<=399,"300-399 мм",IF(LARGE($R59:$T59,2)<=499,"400-499 мм",IF(LARGE($R59:$T59,2)<=599,"500-599 мм",IF(LARGE($R59:$T59,2)<=699,"600-699 мм",IF(LARGE($R59:$T59,2)<=999,"700-999 мм","1000+ мм"))))))))) -> 700-999 мм | Z59: =IF(SMALL($R59:$T59,1)="","",IF(SMALL($R59:$T59,1)<=99,"10-99 мм",IF(SMALL($R59:$T59,1)<=199,"100-199 мм",IF(SMALL($R59:$T59,1)<=299,"200-299 мм",IF(SMALL($R59:$T59,1)<=399,"300-399 мм",IF(SMALL($R59:$T59,1)<=499,"400-499 мм",IF(SMALL($R59:$T59,1)<=599,"500-599 мм",IF(SMALL($R59:$T59,1)<=699,"600-699 мм",IF(SMALL($R59:$T59,1)<=999,"700-999 мм","1000+ мм"))))))))) -> 500-599 мм | AA59: =IF(G59="","",IF(G59="Л","Лист гофрокартона",IF(G59="КД","Крышка-дно",IF(G59="С","Самосборные",IF(G59="Ч","Четырехклапанные",IF(G59="А","Архивные","Неизвестно")))))) -> Четырехклапанные | AB59: 1.73 | AC59: =IF(O59="","",IF(O59<=1,"0-1 литров",IF(O59<=3,"2-3 литра",IF(O59<=5,"4-5 литра",IF(O59<=7,"6-7 литра",IF(O59<=9,"8-9 литров",IF(O59<=14,"10-14 литров",IF(O59<=19,"15-19 литров",IF(O59<=29,"20-29 литров",IF(O59<=49,"30-49 литров",IF(O59<=59,"50-59 литров",IF(O59<=70,"60-69 литров",IF(O59<=79,"70-79 литров",IF(O59<=89,"80-89 литров",IF(O59<=99,"90-99 литров",IF(O59<=200,"100-200 литров","200+ литров")))))))))))))))) -> 200+ литров
A60: 5.46 | B60: =A60*1.2 -> 6.552 | C60: 60 | D60: У | E60: 795х510х870 | F60: Т22 | G60: Ч | H60: 0200 | I60: В | J60: х | K60: K60 | N60: =IF(D60="","",IF(LEFT(D60,1)="0",0,1)) -> 1 | O60: =ROUND(R60*S60*T60/1000000,2) -> 352.74 | P60: =IF(O60="","", IF(O60<1,"0,1-0,9 литров", IF(O60<2,"1-1,9 литра", IF(O60<3,"2-2,9 литра", IF(O60<4,"3-3,9 литра", IF(O60<6,"4-5,9 литра",IF(O60<8,"6-7,9 литра",IF(O60<10,"8-9,9 литров",IF(O60<15,"10-14,9 литров",IF(O60<20,"15-19,9 литров",IF(O60<30,"20-29 литров",IF(O60<50,"30-49 литров",IF(O60<60,"50-59 литров",IF(O60<70,"60-69 литров",IF(O60<80,"70-79 литров",IF(O60<90,"80-89 литров",IF(O60<100,"90-99 литров",IF(O60<200,"100-200 литров","200+ литров")))))))))))))))))) -> 200+ литров | Q60: =IF(O60="","",IF(O60<1,"<1 л",IF(O60<2,"1-2 л",IF(O60<3,"2-3 л",IF(O60<5,"3-5 л",IF(O60<10,"5-10 л",IF(O60<20,"10-20 л",IF(O60<50,"20-50 л",IF(O60<100,"50-100 л","100+ л"))))))))) -> 100+ л | R60: =IF(E60="","",--LEFT(E60,FIND("х",E60)-1)) -> 795 | S60: =IF(E60="","",--MID(E60,FIND("х",E60)+1,FIND("х",E60,FIND("х",E60)+1)-FIND("х",E60)-1)) -> 510 | T60: =IF(E60="","",--RIGHT(E60,LEN(E60)-FIND("х",E60,FIND("х",E60)+1))) -> 870 | U60: =(2*(R60+S60)+60)*(S60+T60+8)/1000000 -> 3.70596 | V60: =IF(OR(AND(R60>=2*S60,R60>=2*T60),AND(S60>=2*R60,S60>=2*T60),AND(T60>=2*R60,T60>=2*S60)),"Длинные","") | W60: =IF(OR(AND(R60<=S60/2,R60<=T60/2),AND(S60<=R60/2,S60<=T60/2),AND(T60<=R60/2,T60<=S60/2)),"Плоские","") | X60: =IF(LARGE($R60:$T60,1)="","",IF(LARGE($R60:$T60,1)<=99,"10-99 мм",IF(LARGE($R60:$T60,1)<=199,"100-199 мм",IF(LARGE($R60:$T60,1)<=299,"200-299 мм",IF(LARGE($R60:$T60,1)<=399,"300-399 мм",IF(LARGE($R60:$T60,1)<=499,"400-499 мм",IF(LARGE($R60:$T60,1)<=599,"500-599 мм",IF(LARGE($R60:$T60,1)<=699,"600-699 мм",IF(LARGE($R60:$T60,1)<=999,"700-999 мм","1000+ мм"))))))))) -> 700-999 мм | Y60: =IF(LARGE($R60:$T60,2)="","",IF(LARGE($R60:$T60,2)<=99,"10-99 мм",IF(LARGE($R60:$T60,2)<=199,"100-199 мм",IF(LARGE($R60:$T60,2)<=299,"200-299 мм",IF(LARGE($R60:$T60,2)<=399,"300-399 мм",IF(LARGE($R60:$T60,2)<=499,"400-499 мм",IF(LARGE($R60:$T60,2)<=599,"500-599 мм",IF(LARGE($R60:$T60,2)<=699,"600-699 мм",IF(LARGE($R60:$T60,2)<=999,"700-999 мм","1000+ мм"))))))))) -> 700-999 мм | Z60: =IF(SMALL($R60:$T60,1)="","",IF(SMALL($R60:$T60,1)<=99,"10-99 мм",IF(SMALL($R60:$T60,1)<=199,"100-199 мм",IF(SMALL($R60:$T60,1)<=299,"200-299 мм",IF(SMALL($R60:$T60,1)<=399,"300-399 мм",IF(SMALL($R60:$T60,1)<=499,"400-499 мм",IF(SMALL($R60:$T60,1)<=599,"500-599 мм",IF(SMALL($R60:$T60,1)<=699,"600-699 мм",IF(SMALL($R60:$T60,1)<=999,"700-999 мм","1000+ мм"))))))))) -> 500-599 мм | AA60: =IF(G60="","",IF(G60="Л","Лист гофрокартона",IF(G60="КД","Крышка-дно",IF(G60="С","Самосборные",IF(G60="Ч","Четырехклапанные",IF(G60="А","Архивные","Неизвестно")))))) -> Четырехклапанные | AB60: 1.73 | AC60: =IF(O60="","",IF(O60<=1,"0-1 литров",IF(O60<=3,"2-3 литра",IF(O60<=5,"4-5 литра",IF(O60<=7,"6-7 литра",IF(O60<=9,"8-9 литров",IF(O60<=14,"10-14 литров",IF(O60<=19,"15-19 литров",IF(O60<=29,"20-29 литров",IF(O60<=49,"30-49 литров",IF(O60<=59,"50-59 литров",IF(O60<=70,"60-69 литров",IF(O60<=79,"70-79 литров",IF(O60<=89,"80-89 литров",IF(O60<=99,"90-99 литров",IF(O60<=200,"100-200 литров","200+ литров")))))))))))))))) -> 200+ литров
A61: 6.43 | B61: =A61*1.2 -> 7.716 | C61: 61 | D61: У | E61: 795х510х870 | F61: +кр Т22 | G61: Ч | H61: 0312 | I61: В | J61: х | K61: K61 | N61: =IF(D61="","",IF(LEFT(D61,1)="0",0,1)) -> 1 | O61: =ROUND(R61*S61*T61/1000000,2) -> 352.74 | P61: =IF(O61="","", IF(O61<1,"0,1-0,9 литров", IF(O61<2,"1-1,9 литра", IF(O61<3,"2-2,9 литра", IF(O61<4,"3-3,9 литра", IF(O61<6,"4-5,9 литра",IF(O61<8,"6-7,9 литра",IF(O61<10,"8-9,9 литров",IF(O61<15,"10-14,9 литров",IF(O61<20,"15-19,9 литров",IF(O61<30,"20-29 литров",IF(O61<50,"30-49 литров",IF(O61<60,"50-59 литров",IF(O61<70,"60-69 литров",IF(O61<80,"70-79 литров",IF(O61<90,"80-89 литров",IF(O61<100,"90-99 литров",IF(O61<200,"100-200 литров","200+ литров")))))))))))))))))) -> 200+ литров | Q61: =IF(O61="","",IF(O61<1,"<1 л",IF(O61<2,"1-2 л",IF(O61<3,"2-3 л",IF(O61<5,"3-5 л",IF(O61<10,"5-10 л",IF(O61<20,"10-20 л",IF(O61<50,"20-50 л",IF(O61<100,"50-100 л","100+ л"))))))))) -> 100+ л | R61: =IF(E61="","",--LEFT(E61,FIND("х",E61)-1)) -> 795 | S61: =IF(E61="","",--MID(E61,FIND("х",E61)+1,FIND("х",E61,FIND("х",E61)+1)-FIND("х",E61)-1)) -> 510 | T61: =IF(E61="","",--RIGHT(E61,LEN(E61)-FIND("х",E61,FIND("х",E61)+1))) -> 870 | U61: =(2*(R61+S61)+60)*(S61+T61+8)/1000000 -> 3.70596 | V61: =IF(OR(AND(R61>=2*S61,R61>=2*T61),AND(S61>=2*R61,S61>=2*T61),AND(T61>=2*R61,T61>=2*S61)),"Длинные","") | W61: =IF(OR(AND(R61<=S61/2,R61<=T61/2),AND(S61<=R61/2,S61<=T61/2),AND(T61<=R61/2,T61<=S61/2)),"Плоские","") | X61: =IF(LARGE($R61:$T61,1)="","",IF(LARGE($R61:$T61,1)<=99,"10-99 мм",IF(LARGE($R61:$T61,1)<=199,"100-199 мм",IF(LARGE($R61:$T61,1)<=299,"200-299 мм",IF(LARGE($R61:$T61,1)<=399,"300-399 мм",IF(LARGE($R61:$T61,1)<=499,"400-499 мм",IF(LARGE($R61:$T61,1)<=599,"500-599 мм",IF(LARGE($R61:$T61,1)<=699,"600-699 мм",IF(LARGE($R61:$T61,1)<=999,"700-999 мм","1000+ мм"))))))))) -> 700-999 мм | Y61: =IF(LARGE($R61:$T61,2)="","",IF(LARGE($R61:$T61,2)<=99,"10-99 мм",IF(LARGE($R61:$T61,2)<=199,"100-199 мм",IF(LARGE($R61:$T61,2)<=299,"200-299 мм",IF(LARGE($R61:$T61,2)<=399,"300-399 мм",IF(LARGE($R61:$T61,2)<=499,"400-499 мм",IF(LARGE($R61:$T61,2)<=599,"500-599 мм",IF(LARGE($R61:$T61,2)<=699,"600-699 мм",IF(LARGE($R61:$T61,2)<=999,"700-999 мм","1000+ мм"))))))))) -> 700-999 мм | Z61: =IF(SMALL($R61:$T61,1)="","",IF(SMALL($R61:$T61,1)<=99,"10-99 мм",IF(SMALL($R61:$T61,1)<=199,"100-199 мм",IF(SMALL($R61:$T61,1)<=299,"200-299 мм",IF(SMALL($R61:$T61,1)<=399,"300-399 мм",IF(SMALL($R61:$T61,1)<=499,"400-499 мм",IF(SMALL($R61:$T61,1)<=599,"500-599 мм",IF(SMALL($R61:$T61,1)<=699,"600-699 мм",IF(SMALL($R61:$T61,1)<=999,"700-999 мм","1000+ мм"))))))))) -> 500-599 мм | AA61: =IF(G61="","",IF(G61="Л","Лист гофрокартона",IF(G61="КД","Крышка-дно",IF(G61="С","Самосборные",IF(G61="Ч","Четырехклапанные",IF(G61="А","Архивные","Неизвестно")))))) -> Четырехклапанные | AB61: 1.73 | AC61: =IF(O61="","",IF(O61<=1,"0-1 литров",IF(O61<=3,"2-3 литра",IF(O61<=5,"4-5 литра",IF(O61<=7,"6-7 литра",IF(O61<=9,"8-9 литров",IF(O61<=14,"10-14 литров",IF(O61<=19,"15-19 литров",IF(O61<=29,"20-29 литров",IF(O61<=49,"30-49 литров",IF(O61<=59,"50-59 литров",IF(O61<=70,"60-69 литров",IF(O61<=79,"70-79 литров",IF(O61<=89,"80-89 литров",IF(O61<=99,"90-99 литров",IF(O61<=200,"100-200 литров","200+ литров")))))))))))))))) -> 200+ литров
A62: 8.77 | B62: =A62*1.2 -> 10.524 | C62: 62 | D62: У | E62: 1100х700х1000 | F62: Т | G62: Ч | H62: 0200 | I62: В | J62: х | K62: K62 | N62: =IF(D62="","",IF(LEFT(D62,1)="0",0,1)) -> 1 | O62: =ROUND(R62*S62*T62/1000000,2) -> 770 | P62: =IF(O62="","", IF(O62<1,"0,1-0,9 литров", IF(O62<2,"1-1,9 литра", IF(O62<3,"2-2,9 литра", IF(O62<4,"3-3,9 литра", IF(O62<6,"4-5,9 литра",IF(O62<8,"6-7,9 литра",IF(O62<10,"8-9,9 литров",IF(O62<15,"10-14,9 литров",IF(O62<20,"15-19,9 литров",IF(O62<30,"20-29 литров",IF(O62<50,"30-49 литров",IF(O62<60,"50-59 литров",IF(O62<70,"60-69 литров",IF(O62<80,"70-79 литров",IF(O62<90,"80-89 литров",IF(O62<100,"90-99 литров",IF(O62<200,"100-200 литров","200+ литров")))))))))))))))))) -> 200+ литров | Q62: =IF(O62="","",IF(O62<1,"<1 л",IF(O62<2,"1-2 л",IF(O62<3,"2-3 л",IF(O62<5,"3-5 л",IF(O62<10,"5-10 л",IF(O62<20,"10-20 л",IF(O62<50,"20-50 л",IF(O62<100,"50-100 л","100+ л"))))))))) -> 100+ л | R62: =IF(E62="","",--LEFT(E62,FIND("х",E62)-1)) -> 1100 | S62: =IF(E62="","",--MID(E62,FIND("х",E62)+1,FIND("х",E62,FIND("х",E62)+1)-FIND("х",E62)-1)) -> 700 | T62: =IF(E62="","",--RIGHT(E62,LEN(E62)-FIND("х",E62,FIND("х",E62)+1))) -> 1000 | U62: =(2*(R62+S62)+60)*(S62+T62+8)/1000000 -> 6.25128 | V62: =IF(OR(AND(R62>=2*S62,R62>=2*T62),AND(S62>=2*R62,S62>=2*T62),AND(T62>=2*R62,T62>=2*S62)),"Длинные","") | W62: =IF(OR(AND(R62<=S62/2,R62<=T62/2),AND(S62<=R62/2,S62<=T62/2),AND(T62<=R62/2,T62<=S62/2)),"Плоские","") | X62: =IF(LARGE($R62:$T62,1)="","",IF(LARGE($R62:$T62,1)<=99,"10-99 мм",IF(LARGE($R62:$T62,1)<=199,"100-199 мм",IF(LARGE($R62:$T62,1)<=299,"200-299 мм",IF(LARGE($R62:$T62,1)<=399,"300-399 мм",IF(LARGE($R62:$T62,1)<=499,"400-499 мм",IF(LARGE($R62:$T62,1)<=599,"500-599 мм",IF(LARGE($R62:$T62,1)<=699,"600-699 мм",IF(LARGE($R62:$T62,1)<=999,"700-999 мм","1000+ мм"))))))))) -> 1000+ мм | Y62: =IF(LARGE($R62:$T62,2)="","",IF(LARGE($R62:$T62,2)<=99,"10-99 мм",IF(LARGE($R62:$T62,2)<=199,"100-199 мм",IF(LARGE($R62:$T62,2)<=299,"200-299 мм",IF(LARGE($R62:$T62,2)<=399,"300-399 мм",IF(LARGE($R62:$T62,2)<=499,"400-499 мм",IF(LARGE($R62:$T62,2)<=599,"500-599 мм",IF(LARGE($R62:$T62,2)<=699,"600-699 мм",IF(LARGE($R62:$T62,2)<=999,"700-999 мм","1000+ мм"))))))))) -> 1000+ мм | Z62: =IF(SMALL($R62:$T62,1)="","",IF(SMALL($R62:$T62,1)<=99,"10-99 мм",IF(SMALL($R62:$T62,1)<=199,"100-199 мм",IF(SMALL($R62:$T62,1)<=299,"200-299 мм",IF(SMALL($R62:$T62,1)<=399,"300-399 мм",IF(SMALL($R62:$T62,1)<=499,"400-499 мм",IF(SMALL($R62:$T62,1)<=599,"500-599 мм",IF(SMALL($R62:$T62,1)<=699,"600-699 мм",IF(SMALL($R62:$T62,1)<=999,"700-999 мм","1000+ мм"))))))))) -> 700-999 мм | AA62: =IF(G62="","",IF(G62="Л","Лист гофрокартона",IF(G62="КД","Крышка-дно",IF(G62="С","Самосборные",IF(G62="Ч","Четырехклапанные",IF(G62="А","Архивные","Неизвестно")))))) -> Четырехклапанные | AB62: 1.73 | AC62: =IF(O62="","",IF(O62<=1,"0-1 литров",IF(O62<=3,"2-3 литра",IF(O62<=5,"4-5 литра",IF(O62<=7,"6-7 литра",IF(O62<=9,"8-9 литров",IF(O62<=14,"10-14 литров",IF(O62<=19,"15-19 литров",IF(O62<=29,"20-29 литров",IF(O62<=49,"30-49 литров",IF(O62<=59,"50-59 литров",IF(O62<=70,"60-69 литров",IF(O62<=79,"70-79 литров",IF(O62<=89,"80-89 литров",IF(O62<=99,"90-99 литров",IF(O62<=200,"100-200 литров","200+ литров")))))))))))))))) -> 200+ литров
A63: 15.17 | B63: =A63*1.2 -> 18.204 | C63: 63 | D63: У | E63: 1100х700х1000 | F63: П | G63: Ч | H63: 0200 | I63: ВС | J63: х | K63: K63 | N63: =IF(D63="","",IF(LEFT(D63,1)="0",0,1)) -> 1 | O63: =ROUND(R63*S63*T63/1000000,2) -> 770 | P63: =IF(O63="","", IF(O63<1,"0,1-0,9 литров", IF(O63<2,"1-1,9 литра", IF(O63<3,"2-2,9 литра", IF(O63<4,"3-3,9 литра", IF(O63<6,"4-5,9 литра",IF(O63<8,"6-7,9 литра",IF(O63<10,"8-9,9 литров",IF(O63<15,"10-14,9 литров",IF(O63<20,"15-19,9 литров",IF(O63<30,"20-29 литров",IF(O63<50,"30-49 литров",IF(O63<60,"50-59 литров",IF(O63<70,"60-69 литров",IF(O63<80,"70-79 литров",IF(O63<90,"80-89 литров",IF(O63<100,"90-99 литров",IF(O63<200,"100-200 литров","200+ литров")))))))))))))))))) -> 200+ литров | Q63: =IF(O63="","",IF(O63<1,"<1 л",IF(O63<2,"1-2 л",IF(O63<3,"2-3 л",IF(O63<5,"3-5 л",IF(O63<10,"5-10 л",IF(O63<20,"10-20 л",IF(O63<50,"20-50 л",IF(O63<100,"50-100 л","100+ л"))))))))) -> 100+ л | R63: =IF(E63="","",--LEFT(E63,FIND("х",E63)-1)) -> 1100 | S63: =IF(E63="","",--MID(E63,FIND("х",E63)+1,FIND("х",E63,FIND("х",E63)+1)-FIND("х",E63)-1)) -> 700 | T63: =IF(E63="","",--RIGHT(E63,LEN(E63)-FIND("х",E63,FIND("х",E63)+1))) -> 1000 | U63: =(2*(R63+S63)+60)*(S63+T63+8)/1000000 -> 6.25128 | V63: =IF(OR(AND(R63>=2*S63,R63>=2*T63),AND(S63>=2*R63,S63>=2*T63),AND(T63>=2*R63,T63>=2*S63)),"Длинные","") | W63: =IF(OR(AND(R63<=S63/2,R63<=T63/2),AND(S63<=R63/2,S63<=T63/2),AND(T63<=R63/2,T63<=S63/2)),"Плоские","") | X63: =IF(LARGE($R63:$T63,1)="","",IF(LARGE($R63:$T63,1)<=99,"10-99 мм",IF(LARGE($R63:$T63,1)<=199,"100-199 мм",IF(LARGE($R63:$T63,1)<=299,"200-299 мм",IF(LARGE($R63:$T63,1)<=399,"300-399 мм",IF(LARGE($R63:$T63,1)<=499,"400-499 мм",IF(LARGE($R63:$T63,1)<=599,"500-599 мм",IF(LARGE($R63:$T63,1)<=699,"600-699 мм",IF(LARGE($R63:$T63,1)<=999,"700-999 мм","1000+ мм"))))))))) -> 1000+ мм | Y63: =IF(LARGE($R63:$T63,2)="","",IF(LARGE($R63:$T63,2)<=99,"10-99 мм",IF(LARGE($R63:$T63,2)<=199,"100-199 мм",IF(LARGE($R63:$T63,2)<=299,"200-299 мм",IF(LARGE($R63:$T63,2)<=399,"300-399 мм",IF(LARGE($R63:$T63,2)<=499,"400-499 мм",IF(LARGE($R63:$T63,2)<=599,"500-599 мм",IF(LARGE($R63:$T63,2)<=699,"600-699 мм",IF(LARGE($R63:$T63,2)<=999,"700-999 мм","1000+ мм"))))))))) -> 1000+ мм | Z63: =IF(SMALL($R63:$T63,1)="","",IF(SMALL($R63:$T63,1)<=99,"10-99 мм",IF(SMALL($R63:$T63,1)<=199,"100-199 мм",IF(SMALL($R63:$T63,1)<=299,"200-299 мм",IF(SMALL($R63:$T63,1)<=399,"300-399 мм",IF(SMALL($R63:$T63,1)<=499,"400-499 мм",IF(SMALL($R63:$T63,1)<=599,"500-599 мм",IF(SMALL($R63:$T63,1)<=699,"600-699 мм",IF(SMALL($R63:$T63,1)<=999,"700-999 мм","1000+ мм"))))))))) -> 700-999 мм | AA63: =IF(G63="","",IF(G63="Л","Лист гофрокартона",IF(G63="КД","Крышка-дно",IF(G63="С","Самосборные",IF(G63="Ч","Четырехклапанные",IF(G63="А","Архивные","Неизвестно")))))) -> Четырехклапанные | AB63: 1.73 | AC63: =IF(O63="","",IF(O63<=1,"0-1 литров",IF(O63<=3,"2-3 литра",IF(O63<=5,"4-5 литра",IF(O63<=7,"6-7 литра",IF(O63<=9,"8-9 литров",IF(O63<=14,"10-14 литров",IF(O63<=19,"15-19 литров",IF(O63<=29,"20-29 литров",IF(O63<=49,"30-49 литров",IF(O63<=59,"50-59 литров",IF(O63<=70,"60-69 литров",IF(O63<=79,"70-79 литров",IF(O63<=89,"80-89 литров",IF(O63<=99,"90-99 литров",IF(O63<=200,"100-200 литров","200+ литров")))))))))))))))) -> 200+ литров
A64: 10.56 | B64: =A64*1.2 -> 12.672 | C64: 64 | D64: У | E64: 1100х700х1000 | F64: Т +крышка | G64: Ч | H64: 0312 | I64: В | J64: х | K64: K64 | N64: =IF(D64="","",IF(LEFT(D64,1)="0",0,1)) -> 1 | O64: =ROUND(R64*S64*T64/1000000,2) -> 770 | P64: =IF(O64="","", IF(O64<1,"0,1-0,9 литров", IF(O64<2,"1-1,9 литра", IF(O64<3,"2-2,9 литра", IF(O64<4,"3-3,9 литра", IF(O64<6,"4-5,9 литра",IF(O64<8,"6-7,9 литра",IF(O64<10,"8-9,9 литров",IF(O64<15,"10-14,9 литров",IF(O64<20,"15-19,9 литров",IF(O64<30,"20-29 литров",IF(O64<50,"30-49 литров",IF(O64<60,"50-59 литров",IF(O64<70,"60-69 литров",IF(O64<80,"70-79 литров",IF(O64<90,"80-89 литров",IF(O64<100,"90-99 литров",IF(O64<200,"100-200 литров","200+ литров")))))))))))))))))) -> 200+ литров | Q64: =IF(O64="","",IF(O64<1,"<1 л",IF(O64<2,"1-2 л",IF(O64<3,"2-3 л",IF(O64<5,"3-5 л",IF(O64<10,"5-10 л",IF(O64<20,"10-20 л",IF(O64<50,"20-50 л",IF(O64<100,"50-100 л","100+ л"))))))))) -> 100+ л | R64: =IF(E64="","",--LEFT(E64,FIND("х",E64)-1)) -> 1100 | S64: =IF(E64="","",--MID(E64,FIND("х",E64)+1,FIND("х",E64,FIND("х",E64)+1)-FIND("х",E64)-1)) -> 700 | T64: =IF(E64="","",--RIGHT(E64,LEN(E64)-FIND("х",E64,FIND("х",E64)+1))) -> 1000 | U64: =(2*(R64+S64)+60)*(S64+T64+8)/1000000 -> 6.25128 | V64: =IF(OR(AND(R64>=2*S64,R64>=2*T64),AND(S64>=2*R64,S64>=2*T64),AND(T64>=2*R64,T64>=2*S64)),"Длинные","") | W64: =IF(OR(AND(R64<=S64/2,R64<=T64/2),AND(S64<=R64/2,S64<=T64/2),AND(T64<=R64/2,T64<=S64/2)),"Плоские","") | X64: =IF(LARGE($R64:$T64,1)="","",IF(LARGE($R64:$T64,1)<=99,"10-99 мм",IF(LARGE($R64:$T64,1)<=199,"100-199 мм",IF(LARGE($R64:$T64,1)<=299,"200-299 мм",IF(LARGE($R64:$T64,1)<=399,"300-399 мм",IF(LARGE($R64:$T64,1)<=499,"400-499 мм",IF(LARGE($R64:$T64,1)<=599,"500-599 мм",IF(LARGE($R64:$T64,1)<=699,"600-699 мм",IF(LARGE($R64:$T64,1)<=999,"700-999 мм","1000+ мм"))))))))) -> 1000+ мм | Y64: =IF(LARGE($R64:$T64,2)="","",IF(LARGE($R64:$T64,2)<=99,"10-99 мм",IF(LARGE($R64:$T64,2)<=199,"100-199 мм",IF(LARGE($R64:$T64,2)<=299,"200-299 мм",IF(LARGE($R64:$T64,2)<=399,"300-399 мм",IF(LARGE($R64:$T64,2)<=499,"400-499 мм",IF(LARGE($R64:$T64,2)<=599,"500-599 мм",IF(LARGE($R64:$T64,2)<=699,"600-699 мм",IF(LARGE($R64:$T64,2)<=999,"700-999 мм","1000+ мм"))))))))) -> 1000+ мм | Z64: =IF(SMALL($R64:$T64,1)="","",IF(SMALL($R64:$T64,1)<=99,"10-99 мм",IF(SMALL($R64:$T64,1)<=199,"100-199 мм",IF(SMALL($R64:$T64,1)<=299,"200-299 мм",IF(SMALL($R64:$T64,1)<=399,"300-399 мм",IF(SMALL($R64:$T64,1)<=499,"400-499 мм",IF(SMALL($R64:$T64,1)<=599,"500-599 мм",IF(SMALL($R64:$T64,1)<=699,"600-699 мм",IF(SMALL($R64:$T64,1)<=999,"700-999 мм","1000+ мм"))))))))) -> 700-999 мм | AA64: =IF(G64="","",IF(G64="Л","Лист гофрокартона",IF(G64="КД","Крышка-дно",IF(G64="С","Самосборные",IF(G64="Ч","Четырехклапанные",IF(G64="А","Архивные","Неизвестно")))))) -> Четырехклапанные | AB64: 1.73 | AC64: =IF(O64="","",IF(O64<=1,"0-1 литров",IF(O64<=3,"2-3 литра",IF(O64<=5,"4-5 литра",IF(O64<=7,"6-7 литра",IF(O64<=9,"8-9 литров",IF(O64<=14,"10-14 литров",IF(O64<=19,"15-19 литров",IF(O64<=29,"20-29 литров",IF(O64<=49,"30-49 литров",IF(O64<=59,"50-59 литров",IF(O64<=70,"60-69 литров",IF(O64<=79,"70-79 литров",IF(O64<=89,"80-89 литров",IF(O64<=99,"90-99 литров",IF(O64<=200,"100-200 литров","200+ литров")))))))))))))))) -> 200+ литров
A65: 16.96 | B65: =A65*1.2 -> 20.352 | C65: 65 | D65: У | E65: 1100х700х1000 | F65: П +крышка | G65: Ч | H65: 0312 | I65: ВС | J65: х | K65: K65 | N65: =IF(D65="","",IF(LEFT(D65,1)="0",0,1)) -> 1 | O65: =ROUND(R65*S65*T65/1000000,2) -> 770 | P65: =IF(O65="","", IF(O65<1,"0,1-0,9 литров", IF(O65<2,"1-1,9 литра", IF(O65<3,"2-2,9 литра", IF(O65<4,"3-3,9 литра", IF(O65<6,"4-5,9 литра",IF(O65<8,"6-7,9 литра",IF(O65<10,"8-9,9 литров",IF(O65<15,"10-14,9 литров",IF(O65<20,"15-19,9 литров",IF(O65<30,"20-29 литров",IF(O65<50,"30-49 литров",IF(O65<60,"50-59 литров",IF(O65<70,"60-69 литров",IF(O65<80,"70-79 литров",IF(O65<90,"80-89 литров",IF(O65<100,"90-99 литров",IF(O65<200,"100-200 литров","200+ литров")))))))))))))))))) -> 200+ литров | Q65: =IF(O65="","",IF(O65<1,"<1 л",IF(O65<2,"1-2 л",IF(O65<3,"2-3 л",IF(O65<5,"3-5 л",IF(O65<10,"5-10 л",IF(O65<20,"10-20 л",IF(O65<50,"20-50 л",IF(O65<100,"50-100 л","100+ л"))))))))) -> 100+ л | R65: =IF(E65="","",--LEFT(E65,FIND("х",E65)-1)) -> 1100 | S65: =IF(E65="","",--MID(E65,FIND("х",E65)+1,FIND("х",E65,FIND("х",E65)+1)-FIND("х",E65)-1)) -> 700 | T65: =IF(E65="","",--RIGHT(E65,LEN(E65)-FIND("х",E65,FIND("х",E65)+1))) -> 1000 | U65: =(2*(R65+S65)+60)*(S65+T65+8)/1000000 -> 6.25128 | V65: =IF(OR(AND(R65>=2*S65,R65>=2*T65),AND(S65>=2*R65,S65>=2*T65),AND(T65>=2*R65,T65>=2*S65)),"Длинные","") | W65: =IF(OR(AND(R65<=S65/2,R65<=T65/2),AND(S65<=R65/2,S65<=T65/2),AND(T65<=R65/2,T65<=S65/2)),"Плоские","") | X65: =IF(LARGE($R65:$T65,1)="","",IF(LARGE($R65:$T65,1)<=99,"10-99 мм",IF(LARGE($R65:$T65,1)<=199,"100-199 мм",IF(LARGE($R65:$T65,1)<=299,"200-299 мм",IF(LARGE($R65:$T65,1)<=399,"300-399 мм",IF(LARGE($R65:$T65,1)<=499,"400-499 мм",IF(LARGE($R65:$T65,1)<=599,"500-599 мм",IF(LARGE($R65:$T65,1)<=699,"600-699 мм",IF(LARGE($R65:$T65,1)<=999,"700-999 мм","1000+ мм"))))))))) -> 1000+ мм | Y65: =IF(LARGE($R65:$T65,2)="","",IF(LARGE($R65:$T65,2)<=99,"10-99 мм",IF(LARGE($R65:$T65,2)<=199,"100-199 мм",IF(LARGE($R65:$T65,2)<=299,"200-299 мм",IF(LARGE($R65:$T65,2)<=399,"300-399 мм",IF(LARGE($R65:$T65,2)<=499,"400-499 мм",IF(LARGE($R65:$T65,2)<=599,"500-599 мм",IF(LARGE($R65:$T65,2)<=699,"600-699 мм",IF(LARGE($R65:$T65,2)<=999,"700-999 мм","1000+ мм"))))))))) -> 1000+ мм | Z65: =IF(SMALL($R65:$T65,1)="","",IF(SMALL($R65:$T65,1)<=99,"10-99 мм",IF(SMALL($R65:$T65,1)<=199,"100-199 мм",IF(SMALL($R65:$T65,1)<=299,"200-299 мм",IF(SMALL($R65:$T65,1)<=399,"300-399 мм",IF(SMALL($R65:$T65,1)<=499,"400-499 мм",IF(SMALL($R65:$T65,1)<=599,"500-599 мм",IF(SMALL($R65:$T65,1)<=699,"600-699 мм",IF(SMALL($R65:$T65,1)<=999,"700-999 мм","1000+ мм"))))))))) -> 700-999 мм | AA65: =IF(G65="","",IF(G65="Л","Лист гофрокартона",IF(G65="КД","Крышка-дно",IF(G65="С","Самосборные",IF(G65="Ч","Четырехклапанные",IF(G65="А","Архивные","Неизвестно")))))) -> Четырехклапанные | AB65: 1.73 | AC65: =IF(O65="","",IF(O65<=1,"0-1 литров",IF(O65<=3,"2-3 литра",IF(O65<=5,"4-5 литра",IF(O65<=7,"6-7 литра",IF(O65<=9,"8-9 литров",IF(O65<=14,"10-14 литров",IF(O65<=19,"15-19 литров",IF(O65<=29,"20-29 литров",IF(O65<=49,"30-49 литров",IF(O65<=59,"50-59 литров",IF(O65<=70,"60-69 литров",IF(O65<=79,"70-79 литров",IF(O65<=89,"80-89 литров",IF(O65<=99,"90-99 литров",IF(O65<=200,"100-200 литров","200+ литров")))))))))))))))) -> 200+ литров
A66: 0.85 | B66: =A66*1.2 -> 1.02 | C66: 66 | D66: У | E66: 340х420х25 | G66: С | H66: 0427 | I66: В | J66: х | K66: K66 | N66: =IF(D66="","",IF(LEFT(D66,1)="0",0,1)) -> 1 | O66: =ROUND(R66*S66*T66/1000000,2) -> 3.57 | P66: =IF(O66="","", IF(O66<1,"0,1-0,9 литров", IF(O66<2,"1-1,9 литра", IF(O66<3,"2-2,9 литра", IF(O66<4,"3-3,9 литра", IF(O66<6,"4-5,9 литра",IF(O66<8,"6-7,9 литра",IF(O66<10,"8-9,9 литров",IF(O66<15,"10-14,9 литров",IF(O66<20,"15-19,9 литров",IF(O66<30,"20-29 литров",IF(O66<50,"30-49 литров",IF(O66<60,"50-59 литров",IF(O66<70,"60-69 литров",IF(O66<80,"70-79 литров",IF(O66<90,"80-89 литров",IF(O66<100,"90-99 литров",IF(O66<200,"100-200 литров","200+ литров")))))))))))))))))) -> 3-3,9 литра | Q66: =IF(O66="","",IF(O66<1,"<1 л",IF(O66<2,"1-2 л",IF(O66<3,"2-3 л",IF(O66<5,"3-5 л",IF(O66<10,"5-10 л",IF(O66<20,"10-20 л",IF(O66<50,"20-50 л",IF(O66<100,"50-100 л","100+ л"))))))))) -> 3-5 л | R66: =IF(E66="","",--LEFT(E66,FIND("х",E66)-1)) -> 340 | S66: =IF(E66="","",--MID(E66,FIND("х",E66)+1,FIND("х",E66,FIND("х",E66)+1)-FIND("х",E66)-1)) -> 420 | T66: =IF(E66="","",--RIGHT(E66,LEN(E66)-FIND("х",E66,FIND("х",E66)+1))) -> 25 | U66: =(2*(R66+S66)+60)*(S66+T66+8)/1000000 -> 0.71574 | V66: =IF(OR(AND(R66>=2*S66,R66>=2*T66),AND(S66>=2*R66,S66>=2*T66),AND(T66>=2*R66,T66>=2*S66)),"Длинные","") | W66: =IF(OR(AND(R66<=S66/2,R66<=T66/2),AND(S66<=R66/2,S66<=T66/2),AND(T66<=R66/2,T66<=S66/2)),"Плоские","") -> Плоские | X66: =IF(LARGE($R66:$T66,1)="","",IF(LARGE($R66:$T66,1)<=99,"10-99 мм",IF(LARGE($R66:$T66,1)<=199,"100-199 мм",IF(LARGE($R66:$T66,1)<=299,"200-299 мм",IF(LARGE($R66:$T66,1)<=399,"300-399 мм",IF(LARGE($R66:$T66,1)<=499,"400-499 мм",IF(LARGE($R66:$T66,1)<=599,"500-599 мм",IF(LARGE($R66:$T66,1)<=699,"600-699 мм",IF(LARGE($R66:$T66,1)<=999,"700-999 мм","1000+ мм"))))))))) -> 400-499 мм | Y66: =IF(LARGE($R66:$T66,2)="","",IF(LARGE($R66:$T66,2)<=99,"10-99 мм",IF(LARGE($R66:$T66,2)<=199,"100-199 мм",IF(LARGE($R66:$T66,2)<=299,"200-299 мм",IF(LARGE($R66:$T66,2)<=399,"300-399 мм",IF(LARGE($R66:$T66,2)<=499,"400-499 мм",IF(LARGE($R66:$T66,2)<=599,"500-599 мм",IF(LARGE($R66:$T66,2)<=699,"600-699 мм",IF(LARGE($R66:$T66,2)<=999,"700-999 мм","1000+ мм"))))))))) -> 300-399 мм | Z66: =IF(SMALL($R66:$T66,1)="","",IF(SMALL($R66:$T66,1)<=99,"10-99 мм",IF(SMALL($R66:$T66,1)<=199,"100-199 мм",IF(SMALL($R66:$T66,1)<=299,"200-299 мм",IF(SMALL($R66:$T66,1)<=399,"300-399 мм",IF(SMALL($R66:$T66,1)<=499,"400-499 мм",IF(SMALL($R66:$T66,1)<=599,"500-599 мм",IF(SMALL($R66:$T66,1)<=699,"600-699 мм",IF(SMALL($R66:$T66,1)<=999,"700-999 мм","1000+ мм"))))))))) -> 10-99 мм | AA66: =IF(G66="","",IF(G66="Л","Лист гофрокартона",IF(G66="КД","Крышка-дно",IF(G66="С","Самосборные",IF(G66="Ч","Четырехклапанные",IF(G66="А","Архивные","Неизвестно")))))) -> Самосборные | AB66: 1.73 | AC66: =IF(O66="","",IF(O66<=1,"0-1 литров",IF(O66<=3,"2-3 литра",IF(O66<=5,"4-5 литра",IF(O66<=7,"6-7 литра",IF(O66<=9,"8-9 литров",IF(O66<=14,"10-14 литров",IF(O66<=19,"15-19 литров",IF(O66<=29,"20-29 литров",IF(O66<=49,"30-49 литров",IF(O66<=59,"50-59 литров",IF(O66<=70,"60-69 литров",IF(O66<=79,"70-79 литров",IF(O66<=89,"80-89 литров",IF(O66<=99,"90-99 литров",IF(O66<=200,"100-200 литров","200+ литров")))))))))))))))) -> 4-5 литра
A67: 1.28 | B67: =A67*1.2 -> 1.536 | C67: 67 | D67: У | E67: 440х440х85 | G67: С | H67: 0426 | I67: В | J67: х | K67: K67 | N67: =IF(D67="","",IF(LEFT(D67,1)="0",0,1)) -> 1 | O67: =ROUND(R67*S67*T67/1000000,2) -> 16.46 | P67: =IF(O67="","", IF(O67<1,"0,1-0,9 литров", IF(O67<2,"1-1,9 литра", IF(O67<3,"2-2,9 литра", IF(O67<4,"3-3,9 литра", IF(O67<6,"4-5,9 литра",IF(O67<8,"6-7,9 литра",IF(O67<10,"8-9,9 литров",IF(O67<15,"10-14,9 литров",IF(O67<20,"15-19,9 литров",IF(O67<30,"20-29 литров",IF(O67<50,"30-49 литров",IF(O67<60,"50-59 литров",IF(O67<70,"60-69 литров",IF(O67<80,"70-79 литров",IF(O67<90,"80-89 литров",IF(O67<100,"90-99 литров",IF(O67<200,"100-200 литров","200+ литров")))))))))))))))))) -> 15-19,9 литров | Q67: =IF(O67="","",IF(O67<1,"<1 л",IF(O67<2,"1-2 л",IF(O67<3,"2-3 л",IF(O67<5,"3-5 л",IF(O67<10,"5-10 л",IF(O67<20,"10-20 л",IF(O67<50,"20-50 л",IF(O67<100,"50-100 л","100+ л"))))))))) -> 10-20 л | R67: =IF(E67="","",--LEFT(E67,FIND("х",E67)-1)) -> 440 | S67: =IF(E67="","",--MID(E67,FIND("х",E67)+1,FIND("х",E67,FIND("х",E67)+1)-FIND("х",E67)-1)) -> 440 | T67: =IF(E67="","",--RIGHT(E67,LEN(E67)-FIND("х",E67,FIND("х",E67)+1))) -> 85 | U67: =(2*(R67+S67)+60)*(S67+T67+8)/1000000 -> 0.97006 | V67: =IF(OR(AND(R67>=2*S67,R67>=2*T67),AND(S67>=2*R67,S67>=2*T67),AND(T67>=2*R67,T67>=2*S67)),"Длинные","") | W67: =IF(OR(AND(R67<=S67/2,R67<=T67/2),AND(S67<=R67/2,S67<=T67/2),AND(T67<=R67/2,T67<=S67/2)),"Плоские","") -> Плоские | X67: =IF(LARGE($R67:$T67,1)="","",IF(LARGE($R67:$T67,1)<=99,"10-99 мм",IF(LARGE($R67:$T67,1)<=199,"100-199 мм",IF(LARGE($R67:$T67,1)<=299,"200-299 мм",IF(LARGE($R67:$T67,1)<=399,"300-399 мм",IF(LARGE($R67:$T67,1)<=499,"400-499 мм",IF(LARGE($R67:$T67,1)<=599,"500-599 мм",IF(LARGE($R67:$T67,1)<=699,"600-699 мм",IF(LARGE($R67:$T67,1)<=999,"700-999 мм","1000+ мм"))))))))) -> 400-499 мм | Y67: =IF(LARGE($R67:$T67,2)="","",IF(LARGE($R67:$T67,2)<=99,"10-99 мм",IF(LARGE($R67:$T67,2)<=199,"100-199 мм",IF(LARGE($R67:$T67,2)<=299,"200-299 мм",IF(LARGE($R67:$T67,2)<=399,"300-399 мм",IF(LARGE($R67:$T67,2)<=499,"400-499 мм",IF(LARGE($R67:$T67,2)<=599,"500-599 мм",IF(LARGE($R67:$T67,2)<=699,"600-699 мм",IF(LARGE($R67:$T67,2)<=999,"700-999 мм","1000+ мм"))))))))) -> 400-499 мм | Z67: =IF(SMALL($R67:$T67,1)="","",IF(SMALL($R67:$T67,1)<=99,"10-99 мм",IF(SMALL($R67:$T67,1)<=199,"100-199 мм",IF(SMALL($R67:$T67,1)<=299,"200-299 мм",IF(SMALL($R67:$T67,1)<=399,"300-399 мм",IF(SMALL($R67:$T67,1)<=499,"400-499 мм",IF(SMALL($R67:$T67,1)<=599,"500-599 мм",IF(SMALL($R67:$T67,1)<=699,"600-699 мм",IF(SMALL($R67:$T67,1)<=999,"700-999 мм","1000+ мм"))))))))) -> 10-99 мм | AA67: =IF(G67="","",IF(G67="Л","Лист гофрокартона",IF(G67="КД","Крышка-дно",IF(G67="С","Самосборные",IF(G67="Ч","Четырехклапанные",IF(G67="А","Архивные","Неизвестно")))))) -> Самосборные | AB67: 1.73 | AC67: =IF(O67="","",IF(O67<=1,"0-1 литров",IF(O67<=3,"2-3 литра",IF(O67<=5,"4-5 литра",IF(O67<=7,"6-7 литра",IF(O67<=9,"8-9 литров",IF(O67<=14,"10-14 литров",IF(O67<=19,"15-19 литров",IF(O67<=29,"20-29 литров",IF(O67<=49,"30-49 литров",IF(O67<=59,"50-59 литров",IF(O67<=70,"60-69 литров",IF(O67<=79,"70-79 литров",IF(O67<=89,"80-89 литров",IF(O67<=99,"90-99 литров",IF(O67<=200,"100-200 литров","200+ литров")))))))))))))))) -> 15-19 литров
A68: 0.87 | B68: =A68*1.2 -> 1.044 | C68: 68 | D68: У | E68: 450х350х40 | G68: С | H68: 0426 | I68: В | J68: х | K68: K68 | N68: =IF(D68="","",IF(LEFT(D68,1)="0",0,1)) -> 1 | O68: =ROUND(R68*S68*T68/1000000,2) -> 6.3 | P68: =IF(O68="","", IF(O68<1,"0,1-0,9 литров", IF(O68<2,"1-1,9 литра", IF(O68<3,"2-2,9 литра", IF(O68<4,"3-3,9 литра", IF(O68<6,"4-5,9 литра",IF(O68<8,"6-7,9 литра",IF(O68<10,"8-9,9 литров",IF(O68<15,"10-14,9 литров",IF(O68<20,"15-19,9 литров",IF(O68<30,"20-29 литров",IF(O68<50,"30-49 литров",IF(O68<60,"50-59 литров",IF(O68<70,"60-69 литров",IF(O68<80,"70-79 литров",IF(O68<90,"80-89 литров",IF(O68<100,"90-99 литров",IF(O68<200,"100-200 литров","200+ литров")))))))))))))))))) -> 6-7,9 литра | Q68: =IF(O68="","",IF(O68<1,"<1 л",IF(O68<2,"1-2 л",IF(O68<3,"2-3 л",IF(O68<5,"3-5 л",IF(O68<10,"5-10 л",IF(O68<20,"10-20 л",IF(O68<50,"20-50 л",IF(O68<100,"50-100 л","100+ л"))))))))) -> 5-10 л | R68: =IF(E68="","",--LEFT(E68,FIND("х",E68)-1)) -> 450 | S68: =IF(E68="","",--MID(E68,FIND("х",E68)+1,FIND("х",E68,FIND("х",E68)+1)-FIND("х",E68)-1)) -> 350 | T68: =IF(E68="","",--RIGHT(E68,LEN(E68)-FIND("х",E68,FIND("х",E68)+1))) -> 40 | U68: =(2*(R68+S68)+60)*(S68+T68+8)/1000000 -> 0.66068 | V68: =IF(OR(AND(R68>=2*S68,R68>=2*T68),AND(S68>=2*R68,S68>=2*T68),AND(T68>=2*R68,T68>=2*S68)),"Длинные","") | W68: =IF(OR(AND(R68<=S68/2,R68<=T68/2),AND(S68<=R68/2,S68<=T68/2),AND(T68<=R68/2,T68<=S68/2)),"Плоские","") -> Плоские | X68: =IF(LARGE($R68:$T68,1)="","",IF(LARGE($R68:$T68,1)<=99,"10-99 мм",IF(LARGE($R68:$T68,1)<=199,"100-199 мм",IF(LARGE($R68:$T68,1)<=299,"200-299 мм",IF(LARGE($R68:$T68,1)<=399,"300-399 мм",IF(LARGE($R68:$T68,1)<=499,"400-499 мм",IF(LARGE($R68:$T68,1)<=599,"500-599 мм",IF(LARGE($R68:$T68,1)<=699,"600-699 мм",IF(LARGE($R68:$T68,1)<=999,"700-999 мм","1000+ мм"))))))))) -> 400-499 мм | Y68: =IF(LARGE($R68:$T68,2)="","",IF(LARGE($R68:$T68,2)<=99,"10-99 мм",IF(LARGE($R68:$T68,2)<=199,"100-199 мм",IF(LARGE($R68:$T68,2)<=299,"200-299 мм",IF(LARGE($R68:$T68,2)<=399,"300-399 мм",IF(LARGE($R68:$T68,2)<=499,"400-499 мм",IF(LARGE($R68:$T68,2)<=599,"500-599 мм",IF(LARGE($R68:$T68,2)<=699,"600-699 мм",IF(LARGE($R68:$T68,2)<=999,"700-999 мм","1000+ мм"))))))))) -> 300-399 мм | Z68: =IF(SMALL($R68:$T68,1)="","",IF(SMALL($R68:$T68,1)<=99,"10-99 мм",IF(SMALL($R68:$T68,1)<=199,"100-199 мм",IF(SMALL($R68:$T68,1)<=299,"200-299 мм",IF(SMALL($R68:$T68,1)<=399,"300-399 мм",IF(SMALL($R68:$T68,1)<=499,"400-499 мм",IF(SMALL($R68:$T68,1)<=599,"500-599 мм",IF(SMALL($R68:$T68,1)<=699,"600-699 мм",IF(SMALL($R68:$T68,1)<=999,"700-999 мм","1000+ мм"))))))))) -> 10-99 мм | AA68: =IF(G68="","",IF(G68="Л","Лист гофрокартона",IF(G68="КД","Крышка-дно",IF(G68="С","Самосборные",IF(G68="Ч","Четырехклапанные",IF(G68="А","Архивные","Неизвестно")))))) -> Самосборные | AB68: 1.73 | AC68: =IF(O68="","",IF(O68<=1,"0-1 литров",IF(O68<=3,"2-3 литра",IF(O68<=5,"4-5 литра",IF(O68<=7,"6-7 литра",IF(O68<=9,"8-9 литров",IF(O68<=14,"10-14 литров",IF(O68<=19,"15-19 литров",IF(O68<=29,"20-29 литров",IF(O68<=49,"30-49 литров",IF(O68<=59,"50-59 литров",IF(O68<=70,"60-69 литров",IF(O68<=79,"70-79 литров",IF(O68<=89,"80-89 литров",IF(O68<=99,"90-99 литров",IF(O68<=200,"100-200 литров","200+ литров")))))))))))))))) -> 6-7 литра
A69: 1.42 | B69: =A69*1.2 -> 1.704 | C69: 69 | D69: У | E69: 1050х180х70 | G69: С | H69: 0427 | I69: В | J69: х | K69: K69 | N69: =IF(D69="","",IF(LEFT(D69,1)="0",0,1)) -> 1 | O69: =ROUND(R69*S69*T69/1000000,2) -> 13.23 | P69: =IF(O69="","", IF(O69<1,"0,1-0,9 литров", IF(O69<2,"1-1,9 литра", IF(O69<3,"2-2,9 литра", IF(O69<4,"3-3,9 литра", IF(O69<6,"4-5,9 литра",IF(O69<8,"6-7,9 литра",IF(O69<10,"8-9,9 литров",IF(O69<15,"10-14,9 литров",IF(O69<20,"15-19,9 литров",IF(O69<30,"20-29 литров",IF(O69<50,"30-49 литров",IF(O69<60,"50-59 литров",IF(O69<70,"60-69 литров",IF(O69<80,"70-79 литров",IF(O69<90,"80-89 литров",IF(O69<100,"90-99 литров",IF(O69<200,"100-200 литров","200+ литров")))))))))))))))))) -> 10-14,9 литров | Q69: =IF(O69="","",IF(O69<1,"<1 л",IF(O69<2,"1-2 л",IF(O69<3,"2-3 л",IF(O69<5,"3-5 л",IF(O69<10,"5-10 л",IF(O69<20,"10-20 л",IF(O69<50,"20-50 л",IF(O69<100,"50-100 л","100+ л"))))))))) -> 10-20 л | R69: =IF(E69="","",--LEFT(E69,FIND("х",E69)-1)) -> 1050 | S69: =IF(E69="","",--MID(E69,FIND("х",E69)+1,FIND("х",E69,FIND("х",E69)+1)-FIND("х",E69)-1)) -> 180 | T69: =IF(E69="","",--RIGHT(E69,LEN(E69)-FIND("х",E69,FIND("х",E69)+1))) -> 70 | U69: =(2*(R69+S69)+60)*(S69+T69+8)/1000000 -> 0.65016 | V69: =IF(OR(AND(R69>=2*S69,R69>=2*T69),AND(S69>=2*R69,S69>=2*T69),AND(T69>=2*R69,T69>=2*S69)),"Длинные","") -> Длинные | W69: =IF(OR(AND(R69<=S69/2,R69<=T69/2),AND(S69<=R69/2,S69<=T69/2),AND(T69<=R69/2,T69<=S69/2)),"Плоские","") -> Плоские | X69: =IF(LARGE($R69:$T69,1)="","",IF(LARGE($R69:$T69,1)<=99,"10-99 мм",IF(LARGE($R69:$T69,1)<=199,"100-199 мм",IF(LARGE($R69:$T69,1)<=299,"200-299 мм",IF(LARGE($R69:$T69,1)<=399,"300-399 мм",IF(LARGE($R69:$T69,1)<=499,"400-499 мм",IF(LARGE($R69:$T69,1)<=599,"500-599 мм",IF(LARGE($R69:$T69,1)<=699,"600-699 мм",IF(LARGE($R69:$T69,1)<=999,"700-999 мм","1000+ мм"))))))))) -> 1000+ мм | Y69: =IF(LARGE($R69:$T69,2)="","",IF(LARGE($R69:$T69,2)<=99,"10-99 мм",IF(LARGE($R69:$T69,2)<=199,"100-199 мм",IF(LARGE($R69:$T69,2)<=299,"200-299 мм",IF(LARGE($R69:$T69,2)<=399,"300-399 мм",IF(LARGE($R69:$T69,2)<=499,"400-499 мм",IF(LARGE($R69:$T69,2)<=599,"500-599 мм",IF(LARGE($R69:$T69,2)<=699,"600-699 мм",IF(LARGE($R69:$T69,2)<=999,"700-999 мм","1000+ мм"))))))))) -> 100-199 мм | Z69: =IF(SMALL($R69:$T69,1)="","",IF(SMALL($R69:$T69,1)<=99,"10-99 мм",IF(SMALL($R69:$T69,1)<=199,"100-199 мм",IF(SMALL($R69:$T69,1)<=299,"200-299 мм",IF(SMALL($R69:$T69,1)<=399,"300-399 мм",IF(SMALL($R69:$T69,1)<=499,"400-499 мм",IF(SMALL($R69:$T69,1)<=599,"500-599 мм",IF(SMALL($R69:$T69,1)<=699,"600-699 мм",IF(SMALL($R69:$T69,1)<=999,"700-999 мм","1000+ мм"))))))))) -> 10-99 мм | AA69: =IF(G69="","",IF(G69="Л","Лист гофрокартона",IF(G69="КД","Крышка-дно",IF(G69="С","Самосборные",IF(G69="Ч","Четырехклапанные",IF(G69="А","Архивные","Неизвестно")))))) -> Самосборные | AB69: 1.73 | AC69: =IF(O69="","",IF(O69<=1,"0-1 литров",IF(O69<=3,"2-3 литра",IF(O69<=5,"4-5 литра",IF(O69<=7,"6-7 литра",IF(O69<=9,"8-9 литров",IF(O69<=14,"10-14 литров",IF(O69<=19,"15-19 литров",IF(O69<=29,"20-29 литров",IF(O69<=49,"30-49 литров",IF(O69<=59,"50-59 литров",IF(O69<=70,"60-69 литров",IF(O69<=79,"70-79 литров",IF(O69<=89,"80-89 литров",IF(O69<=99,"90-99 литров",IF(O69<=200,"100-200 литров","200+ литров")))))))))))))))) -> 10-14 литров
A70: 0.22 | B70: =A70*1.2 -> 0.264 | C70: 70 | D70: У | E70: 305х55х55 | G70: С | H70: 0471 | I70: В | J70: х | K70: K70 | N70: =IF(D70="","",IF(LEFT(D70,1)="0",0,1)) -> 1 | O70: =ROUND(R70*S70*T70/1000000,2) -> 0.92 | P70: =IF(O70="","", IF(O70<1,"0,1-0,9 литров", IF(O70<2,"1-1,9 литра", IF(O70<3,"2-2,9 литра", IF(O70<4,"3-3,9 литра", IF(O70<6,"4-5,9 литра",IF(O70<8,"6-7,9 литра",IF(O70<10,"8-9,9 литров",IF(O70<15,"10-14,9 литров",IF(O70<20,"15-19,9 литров",IF(O70<30,"20-29 литров",IF(O70<50,"30-49 литров",IF(O70<60,"50-59 литров",IF(O70<70,"60-69 литров",IF(O70<80,"70-79 литров",IF(O70<90,"80-89 литров",IF(O70<100,"90-99 литров",IF(O70<200,"100-200 литров","200+ литров")))))))))))))))))) -> 0,1-0,9 литров | Q70: =IF(O70="","",IF(O70<1,"<1 л",IF(O70<2,"1-2 л",IF(O70<3,"2-3 л",IF(O70<5,"3-5 л",IF(O70<10,"5-10 л",IF(O70<20,"10-20 л",IF(O70<50,"20-50 л",IF(O70<100,"50-100 л","100+ л"))))))))) -> <1 л | R70: =IF(E70="","",--LEFT(E70,FIND("х",E70)-1)) -> 305 | S70: =IF(E70="","",--MID(E70,FIND("х",E70)+1,FIND("х",E70,FIND("х",E70)+1)-FIND("х",E70)-1)) -> 55 | T70: =IF(E70="","",--RIGHT(E70,LEN(E70)-FIND("х",E70,FIND("х",E70)+1))) -> 55 | U70: =(2*(R70+S70)+60)*(S70+T70+8)/1000000 -> 0.09204 | V70: =IF(OR(AND(R70>=2*S70,R70>=2*T70),AND(S70>=2*R70,S70>=2*T70),AND(T70>=2*R70,T70>=2*S70)),"Длинные","") -> Длинные | W70: =IF(OR(AND(R70<=S70/2,R70<=T70/2),AND(S70<=R70/2,S70<=T70/2),AND(T70<=R70/2,T70<=S70/2)),"Плоские","") | X70: =IF(LARGE($R70:$T70,1)="","",IF(LARGE($R70:$T70,1)<=99,"10-99 мм",IF(LARGE($R70:$T70,1)<=199,"100-199 мм",IF(LARGE($R70:$T70,1)<=299,"200-299 мм",IF(LARGE($R70:$T70,1)<=399,"300-399 мм",IF(LARGE($R70:$T70,1)<=499,"400-499 мм",IF(LARGE($R70:$T70,1)<=599,"500-599 мм",IF(LARGE($R70:$T70,1)<=699,"600-699 мм",IF(LARGE($R70:$T70,1)<=999,"700-999 мм","1000+ мм"))))))))) -> 300-399 мм | Y70: =IF(LARGE($R70:$T70,2)="","",IF(LARGE($R70:$T70,2)<=99,"10-99 мм",IF(LARGE($R70:$T70,2)<=199,"100-199 мм",IF(LARGE($R70:$T70,2)<=299,"200-299 мм",IF(LARGE($R70:$T70,2)<=399,"300-399 мм",IF(LARGE($R70:$T70,2)<=499,"400-499 мм",IF(LARGE($R70:$T70,2)<=599,"500-599 мм",IF(LARGE($R70:$T70,2)<=699,"600-699 мм",IF(LARGE($R70:$T70,2)<=999,"700-999 мм","1000+ мм"))))))))) -> 10-99 мм | Z70: =IF(SMALL($R70:$T70,1)="","",IF(SMALL($R70:$T70,1)<=99,"10-99 мм",IF(SMALL($R70:$T70,1)<=199,"100-199 мм",IF(SMALL($R70:$T70,1)<=299,"200-299 мм",IF(SMALL($R70:$T70,1)<=399,"300-399 мм",IF(SMALL($R70:$T70,1)<=499,"400-499 мм",IF(SMALL($R70:$T70,1)<=599,"500-599 мм",IF(SMALL($R70:$T70,1)<=699,"600-699 мм",IF(SMALL($R70:$T70,1)<=999,"700-999 мм","1000+ мм"))))))))) -> 10-99 мм | AA70: =IF(G70="","",IF(G70="Л","Лист гофрокартона",IF(G70="КД","Крышка-дно",IF(G70="С","Самосборные",IF(G70="Ч","Четырехклапанные",IF(G70="А","Архивные","Неизвестно")))))) -> Самосборные | AB70: 1.73 | AC70: =IF(O70="","",IF(O70<=1,"0-1 литров",IF(O70<=3,"2-3 литра",IF(O70<=5,"4-5 литра",IF(O70<=7,"6-7 литра",IF(O70<=9,"8-9 литров",IF(O70<=14,"10-14 литров",IF(O70<=19,"15-19 литров",IF(O70<=29,"20-29 литров",IF(O70<=49,"30-49 литров",IF(O70<=59,"50-59 литров",IF(O70<=70,"60-69 литров",IF(O70<=79,"70-79 литров",IF(O70<=89,"80-89 литров",IF(O70<=99,"90-99 литров",IF(O70<=200,"100-200 литров","200+ литров")))))))))))))))) -> 0-1 литров
A71: 0.77 | B71: =A71*1.2 -> 0.924 | C71: 71 | D71: У | E71: 370х140х130 | G71: С | H71: 0215 | I71: В | J71: х | K71: K71 | N71: =IF(D71="","",IF(LEFT(D71,1)="0",0,1)) -> 1 | O71: =ROUND(R71*S71*T71/1000000,2) -> 6.73 | P71: =IF(O71="","", IF(O71<1,"0,1-0,9 литров", IF(O71<2,"1-1,9 литра", IF(O71<3,"2-2,9 литра", IF(O71<4,"3-3,9 литра", IF(O71<6,"4-5,9 литра",IF(O71<8,"6-7,9 литра",IF(O71<10,"8-9,9 литров",IF(O71<15,"10-14,9 литров",IF(O71<20,"15-19,9 литров",IF(O71<30,"20-29 литров",IF(O71<50,"30-49 литров",IF(O71<60,"50-59 литров",IF(O71<70,"60-69 литров",IF(O71<80,"70-79 литров",IF(O71<90,"80-89 литров",IF(O71<100,"90-99 литров",IF(O71<200,"100-200 литров","200+ литров")))))))))))))))))) -> 6-7,9 литра | Q71: =IF(O71="","",IF(O71<1,"<1 л",IF(O71<2,"1-2 л",IF(O71<3,"2-3 л",IF(O71<5,"3-5 л",IF(O71<10,"5-10 л",IF(O71<20,"10-20 л",IF(O71<50,"20-50 л",IF(O71<100,"50-100 л","100+ л"))))))))) -> 5-10 л | R71: =IF(E71="","",--LEFT(E71,FIND("х",E71)-1)) -> 370 | S71: =IF(E71="","",--MID(E71,FIND("х",E71)+1,FIND("х",E71,FIND("х",E71)+1)-FIND("х",E71)-1)) -> 140 | T71: =IF(E71="","",--RIGHT(E71,LEN(E71)-FIND("х",E71,FIND("х",E71)+1))) -> 130 | U71: =(2*(R71+S71)+60)*(S71+T71+8)/1000000 -> 0.30024 | V71: =IF(OR(AND(R71>=2*S71,R71>=2*T71),AND(S71>=2*R71,S71>=2*T71),AND(T71>=2*R71,T71>=2*S71)),"Длинные","") -> Длинные | W71: =IF(OR(AND(R71<=S71/2,R71<=T71/2),AND(S71<=R71/2,S71<=T71/2),AND(T71<=R71/2,T71<=S71/2)),"Плоские","") | X71: =IF(LARGE($R71:$T71,1)="","",IF(LARGE($R71:$T71,1)<=99,"10-99 мм",IF(LARGE($R71:$T71,1)<=199,"100-199 мм",IF(LARGE($R71:$T71,1)<=299,"200-299 мм",IF(LARGE($R71:$T71,1)<=399,"300-399 мм",IF(LARGE($R71:$T71,1)<=499,"400-499 мм",IF(LARGE($R71:$T71,1)<=599,"500-599 мм",IF(LARGE($R71:$T71,1)<=699,"600-699 мм",IF(LARGE($R71:$T71,1)<=999,"700-999 мм","1000+ мм"))))))))) -> 300-399 мм | Y71: =IF(LARGE($R71:$T71,2)="","",IF(LARGE($R71:$T71,2)<=99,"10-99 мм",IF(LARGE($R71:$T71,2)<=199,"100-199 мм",IF(LARGE($R71:$T71,2)<=299,"200-299 мм",IF(LARGE($R71:$T71,2)<=399,"300-399 мм",IF(LARGE($R71:$T71,2)<=499,"400-499 мм",IF(LARGE($R71:$T71,2)<=599,"500-599 мм",IF(LARGE($R71:$T71,2)<=699,"600-699 мм",IF(LARGE($R71:$T71,2)<=999,"700-999 мм","1000+ мм"))))))))) -> 100-199 мм | Z71: =IF(SMALL($R71:$T71,1)="","",IF(SMALL($R71:$T71,1)<=99,"10-99 мм",IF(SMALL($R71:$T71,1)<=199,"100-199 мм",IF(SMALL($R71:$T71,1)<=299,"200-299 мм",IF(SMALL($R71:$T71,1)<=399,"300-399 мм",IF(SMALL($R71:$T71,1)<=499,"400-499 мм",IF(SMALL($R71:$T71,1)<=599,"500-599 мм",IF(SMALL($R71:$T71,1)<=699,"600-699 мм",IF(SMALL($R71:$T71,1)<=999,"700-999 мм","1000+ мм"))))))))) -> 100-199 мм | AA71: =IF(G71="","",IF(G71="Л","Лист гофрокартона",IF(G71="КД","Крышка-дно",IF(G71="С","Самосборные",IF(G71="Ч","Четырехклапанные",IF(G71="А","Архивные","Неизвестно")))))) -> Самосборные | AB71: 1.73 | AC71: =IF(O71="","",IF(O71<=1,"0-1 литров",IF(O71<=3,"2-3 литра",IF(O71<=5,"4-5 литра",IF(O71<=7,"6-7 литра",IF(O71<=9,"8-9 литров",IF(O71<=14,"10-14 литров",IF(O71<=19,"15-19 литров",IF(O71<=29,"20-29 литров",IF(O71<=49,"30-49 литров",IF(O71<=59,"50-59 литров",IF(O71<=70,"60-69 литров",IF(O71<=79,"70-79 литров",IF(O71<=89,"80-89 литров",IF(O71<=99,"90-99 литров",IF(O71<=200,"100-200 литров","200+ литров")))))))))))))))) -> 6-7 литра
A72: 0.44 | B72: =A72*1.2 -> 0.528 | C72: 72 | D72: У | E72: 178х118х152 | G72: С | H72: 0215 | I72: В | J72: х | K72: K72 | N72: =IF(D72="","",IF(LEFT(D72,1)="0",0,1)) -> 1 | O72: =ROUND(R72*S72*T72/1000000,2) -> 3.19 | P72: =IF(O72="","", IF(O72<1,"0,1-0,9 литров", IF(O72<2,"1-1,9 литра", IF(O72<3,"2-2,9 литра", IF(O72<4,"3-3,9 литра", IF(O72<6,"4-5,9 литра",IF(O72<8,"6-7,9 литра",IF(O72<10,"8-9,9 литров",IF(O72<15,"10-14,9 литров",IF(O72<20,"15-19,9 литров",IF(O72<30,"20-29 литров",IF(O72<50,"30-49 литров",IF(O72<60,"50-59 литров",IF(O72<70,"60-69 литров",IF(O72<80,"70-79 литров",IF(O72<90,"80-89 литров",IF(O72<100,"90-99 литров",IF(O72<200,"100-200 литров","200+ литров")))))))))))))))))) -> 3-3,9 литра | Q72: =IF(O72="","",IF(O72<1,"<1 л",IF(O72<2,"1-2 л",IF(O72<3,"2-3 л",IF(O72<5,"3-5 л",IF(O72<10,"5-10 л",IF(O72<20,"10-20 л",IF(O72<50,"20-50 л",IF(O72<100,"50-100 л","100+ л"))))))))) -> 3-5 л | R72: =IF(E72="","",--LEFT(E72,FIND("х",E72)-1)) -> 178 | S72: =IF(E72="","",--MID(E72,FIND("х",E72)+1,FIND("х",E72,FIND("х",E72)+1)-FIND("х",E72)-1)) -> 118 | T72: =IF(E72="","",--RIGHT(E72,LEN(E72)-FIND("х",E72,FIND("х",E72)+1))) -> 152 | U72: =(2*(R72+S72)+60)*(S72+T72+8)/1000000 -> 0.181256 | V72: =IF(OR(AND(R72>=2*S72,R72>=2*T72),AND(S72>=2*R72,S72>=2*T72),AND(T72>=2*R72,T72>=2*S72)),"Длинные","") | W72: =IF(OR(AND(R72<=S72/2,R72<=T72/2),AND(S72<=R72/2,S72<=T72/2),AND(T72<=R72/2,T72<=S72/2)),"Плоские","") | X72: =IF(LARGE($R72:$T72,1)="","",IF(LARGE($R72:$T72,1)<=99,"10-99 мм",IF(LARGE($R72:$T72,1)<=199,"100-199 мм",IF(LARGE($R72:$T72,1)<=299,"200-299 мм",IF(LARGE($R72:$T72,1)<=399,"300-399 мм",IF(LARGE($R72:$T72,1)<=499,"400-499 мм",IF(LARGE($R72:$T72,1)<=599,"500-599 мм",IF(LARGE($R72:$T72,1)<=699,"600-699 мм",IF(LARGE($R72:$T72,1)<=999,"700-999 мм","1000+ мм"))))))))) -> 100-199 мм | Y72: =IF(LARGE($R72:$T72,2)="","",IF(LARGE($R72:$T72,2)<=99,"10-99 мм",IF(LARGE($R72:$T72,2)<=199,"100-199 мм",IF(LARGE($R72:$T72,2)<=299,"200-299 мм",IF(LARGE($R72:$T72,2)<=399,"300-399 мм",IF(LARGE($R72:$T72,2)<=499,"400-499 мм",IF(LARGE($R72:$T72,2)<=599,"500-599 мм",IF(LARGE($R72:$T72,2)<=699,"600-699 мм",IF(LARGE($R72:$T72,2)<=999,"700-999 мм","1000+ мм"))))))))) -> 100-199 мм | Z72: =IF(SMALL($R72:$T72,1)="","",IF(SMALL($R72:$T72,1)<=99,"10-99 мм",IF(SMALL($R72:$T72,1)<=199,"100-199 мм",IF(SMALL($R72:$T72,1)<=299,"200-299 мм",IF(SMALL($R72:$T72,1)<=399,"300-399 мм",IF(SMALL($R72:$T72,1)<=499,"400-499 мм",IF(SMALL($R72:$T72,1)<=599,"500-599 мм",IF(SMALL($R72:$T72,1)<=699,"600-699 мм",IF(SMALL($R72:$T72,1)<=999,"700-999 мм","1000+ мм"))))))))) -> 100-199 мм | AA72: =IF(G72="","",IF(G72="Л","Лист гофрокартона",IF(G72="КД","Крышка-дно",IF(G72="С","Самосборные",IF(G72="Ч","Четырехклапанные",IF(G72="А","Архивные","Неизвестно")))))) -> Самосборные | AB72: 1.73 | AC72: =IF(O72="","",IF(O72<=1,"0-1 литров",IF(O72<=3,"2-3 литра",IF(O72<=5,"4-5 литра",IF(O72<=7,"6-7 литра",IF(O72<=9,"8-9 литров",IF(O72<=14,"10-14 литров",IF(O72<=19,"15-19 литров",IF(O72<=29,"20-29 литров",IF(O72<=49,"30-49 литров",IF(O72<=59,"50-59 литров",IF(O72<=70,"60-69 литров",IF(O72<=79,"70-79 литров",IF(O72<=89,"80-89 литров",IF(O72<=99,"90-99 литров",IF(O72<=200,"100-200 литров","200+ литров")))))))))))))))) -> 4-5 литра
A73: 1.65 | B73: =A73*1.2 -> 1.98 | C73: 73 | D73: У | E73: 1100х250х100 | G73: С | H73: 0411 | I73: В | J73: х | K73: K73 | N73: =IF(D73="","",IF(LEFT(D73,1)="0",0,1)) -> 1 | O73: =ROUND(R73*S73*T73/1000000,2) -> 27.5 | P73: =IF(O73="","", IF(O73<1,"0,1-0,9 литров", IF(O73<2,"1-1,9 литра", IF(O73<3,"2-2,9 литра", IF(O73<4,"3-3,9 литра", IF(O73<6,"4-5,9 литра",IF(O73<8,"6-7,9 литра",IF(O73<10,"8-9,9 литров",IF(O73<15,"10-14,9 литров",IF(O73<20,"15-19,9 литров",IF(O73<30,"20-29 литров",IF(O73<50,"30-49 литров",IF(O73<60,"50-59 литров",IF(O73<70,"60-69 литров",IF(O73<80,"70-79 литров",IF(O73<90,"80-89 литров",IF(O73<100,"90-99 литров",IF(O73<200,"100-200 литров","200+ литров")))))))))))))))))) -> 20-29 литров | Q73: =IF(O73="","",IF(O73<1,"<1 л",IF(O73<2,"1-2 л",IF(O73<3,"2-3 л",IF(O73<5,"3-5 л",IF(O73<10,"5-10 л",IF(O73<20,"10-20 л",IF(O73<50,"20-50 л",IF(O73<100,"50-100 л","100+ л"))))))))) -> 20-50 л | R73: =IF(E73="","",--LEFT(E73,FIND("х",E73)-1)) -> 1100 | S73: =IF(E73="","",--MID(E73,FIND("х",E73)+1,FIND("х",E73,FIND("х",E73)+1)-FIND("х",E73)-1)) -> 250 | T73: =IF(E73="","",--RIGHT(E73,LEN(E73)-FIND("х",E73,FIND("х",E73)+1))) -> 100 | U73: =(2*(R73+S73)+60)*(S73+T73+8)/1000000 -> 0.98808 | V73: =IF(OR(AND(R73>=2*S73,R73>=2*T73),AND(S73>=2*R73,S73>=2*T73),AND(T73>=2*R73,T73>=2*S73)),"Длинные","") -> Длинные | W73: =IF(OR(AND(R73<=S73/2,R73<=T73/2),AND(S73<=R73/2,S73<=T73/2),AND(T73<=R73/2,T73<=S73/2)),"Плоские","") -> Плоские | X73: =IF(LARGE($R73:$T73,1)="","",IF(LARGE($R73:$T73,1)<=99,"10-99 мм",IF(LARGE($R73:$T73,1)<=199,"100-199 мм",IF(LARGE($R73:$T73,1)<=299,"200-299 мм",IF(LARGE($R73:$T73,1)<=399,"300-399 мм",IF(LARGE($R73:$T73,1)<=499,"400-499 мм",IF(LARGE($R73:$T73,1)<=599,"500-599 мм",IF(LARGE($R73:$T73,1)<=699,"600-699 мм",IF(LARGE($R73:$T73,1)<=999,"700-999 мм","1000+ мм"))))))))) -> 1000+ мм | Y73: =IF(LARGE($R73:$T73,2)="","",IF(LARGE($R73:$T73,2)<=99,"10-99 мм",IF(LARGE($R73:$T73,2)<=199,"100-199 мм",IF(LARGE($R73:$T73,2)<=299,"200-299 мм",IF(LARGE($R73:$T73,2)<=399,"300-399 мм",IF(LARGE($R73:$T73,2)<=499,"400-499 мм",IF(LARGE($R73:$T73,2)<=599,"500-599 мм",IF(LARGE($R73:$T73,2)<=699,"600-699 мм",IF(LARGE($R73:$T73,2)<=999,"700-999 мм","1000+ мм"))))))))) -> 200-299 мм | Z73: =IF(SMALL($R73:$T73,1)="","",IF(SMALL($R73:$T73,1)<=99,"10-99 мм",IF(SMALL($R73:$T73,1)<=199,"100-199 мм",IF(SMALL($R73:$T73,1)<=299,"200-299 мм",IF(SMALL($R73:$T73,1)<=399,"300-399 мм",IF(SMALL($R73:$T73,1)<=499,"400-499 мм",IF(SMALL($R73:$T73,1)<=599,"500-599 мм",IF(SMALL($R73:$T73,1)<=699,"600-699 мм",IF(SMALL($R73:$T73,1)<=999,"700-999 мм","1000+ мм"))))))))) -> 100-199 мм | AA73: =IF(G73="","",IF(G73="Л","Лист гофрокартона",IF(G73="КД","Крышка-дно",IF(G73="С","Самосборные",IF(G73="Ч","Четырехклапанные",IF(G73="А","Архивные","Неизвестно")))))) -> Самосборные | AB73: 1.73 | AC73: =IF(O73="","",IF(O73<=1,"0-1 литров",IF(O73<=3,"2-3 литра",IF(O73<=5,"4-5 литра",IF(O73<=7,"6-7 литра",IF(O73<=9,"8-9 литров",IF(O73<=14,"10-14 литров",IF(O73<=19,"15-19 литров",IF(O73<=29,"20-29 литров",IF(O73<=49,"30-49 литров",IF(O73<=59,"50-59 литров",IF(O73<=70,"60-69 литров",IF(O73<=79,"70-79 литров",IF(O73<=89,"80-89 литров",IF(O73<=99,"90-99 литров",IF(O73<=200,"100-200 литров","200+ литров")))))))))))))))) -> 20-29 литров
A74: 1.11 | B74: =A74*1.2 -> 1.332 | C74: 74 | D74: У | E74: 460х280х60 | G74: С | H74: 0427 | I74: В | J74: х | K74: K74 | N74: =IF(D74="","",IF(LEFT(D74,1)="0",0,1)) -> 1 | O74: =ROUND(R74*S74*T74/1000000,2) -> 7.73 | P74: =IF(O74="","", IF(O74<1,"0,1-0,9 литров", IF(O74<2,"1-1,9 литра", IF(O74<3,"2-2,9 литра", IF(O74<4,"3-3,9 литра", IF(O74<6,"4-5,9 литра",IF(O74<8,"6-7,9 литра",IF(O74<10,"8-9,9 литров",IF(O74<15,"10-14,9 литров",IF(O74<20,"15-19,9 литров",IF(O74<30,"20-29 литров",IF(O74<50,"30-49 литров",IF(O74<60,"50-59 литров",IF(O74<70,"60-69 литров",IF(O74<80,"70-79 литров",IF(O74<90,"80-89 литров",IF(O74<100,"90-99 литров",IF(O74<200,"100-200 литров","200+ литров")))))))))))))))))) -> 6-7,9 литра | Q74: =IF(O74="","",IF(O74<1,"<1 л",IF(O74<2,"1-2 л",IF(O74<3,"2-3 л",IF(O74<5,"3-5 л",IF(O74<10,"5-10 л",IF(O74<20,"10-20 л",IF(O74<50,"20-50 л",IF(O74<100,"50-100 л","100+ л"))))))))) -> 5-10 л | R74: =IF(E74="","",--LEFT(E74,FIND("х",E74)-1)) -> 460 | S74: =IF(E74="","",--MID(E74,FIND("х",E74)+1,FIND("х",E74,FIND("х",E74)+1)-FIND("х",E74)-1)) -> 280 | T74: =IF(E74="","",--RIGHT(E74,LEN(E74)-FIND("х",E74,FIND("х",E74)+1))) -> 60 | U74: =(2*(R74+S74)+60)*(S74+T74+8)/1000000 -> 0.53592 | V74: =IF(OR(AND(R74>=2*S74,R74>=2*T74),AND(S74>=2*R74,S74>=2*T74),AND(T74>=2*R74,T74>=2*S74)),"Длинные","") | W74: =IF(OR(AND(R74<=S74/2,R74<=T74/2),AND(S74<=R74/2,S74<=T74/2),AND(T74<=R74/2,T74<=S74/2)),"Плоские","") -> Плоские | X74: =IF(LARGE($R74:$T74,1)="","",IF(LARGE($R74:$T74,1)<=99,"10-99 мм",IF(LARGE($R74:$T74,1)<=199,"100-199 мм",IF(LARGE($R74:$T74,1)<=299,"200-299 мм",IF(LARGE($R74:$T74,1)<=399,"300-399 мм",IF(LARGE($R74:$T74,1)<=499,"400-499 мм",IF(LARGE($R74:$T74,1)<=599,"500-599 мм",IF(LARGE($R74:$T74,1)<=699,"600-699 мм",IF(LARGE($R74:$T74,1)<=999,"700-999 мм","1000+ мм"))))))))) -> 400-499 мм | Y74: =IF(LARGE($R74:$T74,2)="","",IF(LARGE($R74:$T74,2)<=99,"10-99 мм",IF(LARGE($R74:$T74,2)<=199,"100-199 мм",IF(LARGE($R74:$T74,2)<=299,"200-299 мм",IF(LARGE($R74:$T74,2)<=399,"300-399 мм",IF(LARGE($R74:$T74,2)<=499,"400-499 мм",IF(LARGE($R74:$T74,2)<=599,"500-599 мм",IF(LARGE($R74:$T74,2)<=699,"600-699 мм",IF(LARGE($R74:$T74,2)<=999,"700-999 мм","1000+ мм"))))))))) -> 200-299 мм | Z74: =IF(SMALL($R74:$T74,1)="","",IF(SMALL($R74:$T74,1)<=99,"10-99 мм",IF(SMALL($R74:$T74,1)<=199,"100-199 мм",IF(SMALL($R74:$T74,1)<=299,"200-299 мм",IF(SMALL($R74:$T74,1)<=399,"300-399 мм",IF(SMALL($R74:$T74,1)<=499,"400-499 мм",IF(SMALL($R74:$T74,1)<=599,"500-599 мм",IF(SMALL($R74:$T74,1)<=699,"600-699 мм",IF(SMALL($R74:$T74,1)<=999,"700-999 мм","1000+ мм"))))))))) -> 10-99 мм | AA74: =IF(G74="","",IF(G74="Л","Лист гофрокартона",IF(G74="КД","Крышка-дно",IF(G74="С","Самосборные",IF(G74="Ч","Четырехклапанные",IF(G74="А","Архивные","Неизвестно")))))) -> Самосборные | AB74: 1.73 | AC74: =IF(O74="","",IF(O74<=1,"0-1 литров",IF(O74<=3,"2-3 литра",IF(O74<=5,"4-5 литра",IF(O74<=7,"6-7 литра",IF(O74<=9,"8-9 литров",IF(O74<=14,"10-14 литров",IF(O74<=19,"15-19 литров",IF(O74<=29,"20-29 литров",IF(O74<=49,"30-49 литров",IF(O74<=59,"50-59 литров",IF(O74<=70,"60-69 литров",IF(O74<=79,"70-79 литров",IF(O74<=89,"80-89 литров",IF(O74<=99,"90-99 литров",IF(O74<=200,"100-200 литров","200+ литров")))))))))))))))) -> 8-9 литров
A75: 1 | B75: =A75*1.2 -> 1.2 | C75: 75 | D75: У | E75: 600х115х105 | G75: С | H75: 0427 | I75: В | J75: х | K75: K75 | N75: =IF(D75="","",IF(LEFT(D75,1)="0",0,1)) -> 1 | O75: =ROUND(R75*S75*T75/1000000,2) -> 7.25 | P75: =IF(O75="","", IF(O75<1,"0,1-0,9 литров", IF(O75<2,"1-1,9 литра", IF(O75<3,"2-2,9 литра", IF(O75<4,"3-3,9 литра", IF(O75<6,"4-5,9 литра",IF(O75<8,"6-7,9 литра",IF(O75<10,"8-9,9 литров",IF(O75<15,"10-14,9 литров",IF(O75<20,"15-19,9 литров",IF(O75<30,"20-29 литров",IF(O75<50,"30-49 литров",IF(O75<60,"50-59 литров",IF(O75<70,"60-69 литров",IF(O75<80,"70-79 литров",IF(O75<90,"80-89 литров",IF(O75<100,"90-99 литров",IF(O75<200,"100-200 литров","200+ литров")))))))))))))))))) -> 6-7,9 литра | Q75: =IF(O75="","",IF(O75<1,"<1 л",IF(O75<2,"1-2 л",IF(O75<3,"2-3 л",IF(O75<5,"3-5 л",IF(O75<10,"5-10 л",IF(O75<20,"10-20 л",IF(O75<50,"20-50 л",IF(O75<100,"50-100 л","100+ л"))))))))) -> 5-10 л | R75: =IF(E75="","",--LEFT(E75,FIND("х",E75)-1)) -> 600 | S75: =IF(E75="","",--MID(E75,FIND("х",E75)+1,FIND("х",E75,FIND("х",E75)+1)-FIND("х",E75)-1)) -> 115 | T75: =IF(E75="","",--RIGHT(E75,LEN(E75)-FIND("х",E75,FIND("х",E75)+1))) -> 105 | U75: =(2*(R75+S75)+60)*(S75+T75+8)/1000000 -> 0.33972 | V75: =IF(OR(AND(R75>=2*S75,R75>=2*T75),AND(S75>=2*R75,S75>=2*T75),AND(T75>=2*R75,T75>=2*S75)),"Длинные","") -> Длинные | W75: =IF(OR(AND(R75<=S75/2,R75<=T75/2),AND(S75<=R75/2,S75<=T75/2),AND(T75<=R75/2,T75<=S75/2)),"Плоские","") | X75: =IF(LARGE($R75:$T75,1)="","",IF(LARGE($R75:$T75,1)<=99,"10-99 мм",IF(LARGE($R75:$T75,1)<=199,"100-199 мм",IF(LARGE($R75:$T75,1)<=299,"200-299 мм",IF(LARGE($R75:$T75,1)<=399,"300-399 мм",IF(LARGE($R75:$T75,1)<=499,"400-499 мм",IF(LARGE($R75:$T75,1)<=599,"500-599 мм",IF(LARGE($R75:$T75,1)<=699,"600-699 мм",IF(LARGE($R75:$T75,1)<=999,"700-999 мм","1000+ мм"))))))))) -> 600-699 мм | Y75: =IF(LARGE($R75:$T75,2)="","",IF(LARGE($R75:$T75,2)<=99,"10-99 мм",IF(LARGE($R75:$T75,2)<=199,"100-199 мм",IF(LARGE($R75:$T75,2)<=299,"200-299 мм",IF(LARGE($R75:$T75,2)<=399,"300-399 мм",IF(LARGE($R75:$T75,2)<=499,"400-499 мм",IF(LARGE($R75:$T75,2)<=599,"500-599 мм",IF(LARGE($R75:$T75,2)<=699,"600-699 мм",IF(LARGE($R75:$T75,2)<=999,"700-999 мм","1000+ мм"))))))))) -> 100-199 мм | Z75: =IF(SMALL($R75:$T75,1)="","",IF(SMALL($R75:$T75,1)<=99,"10-99 мм",IF(SMALL($R75:$T75,1)<=199,"100-199 мм",IF(SMALL($R75:$T75,1)<=299,"200-299 мм",IF(SMALL($R75:$T75,1)<=399,"300-399 мм",IF(SMALL($R75:$T75,1)<=499,"400-499 мм",IF(SMALL($R75:$T75,1)<=599,"500-599 мм",IF(SMALL($R75:$T75,1)<=699,"600-699 мм",IF(SMALL($R75:$T75,1)<=999,"700-999 мм","1000+ мм"))))))))) -> 100-199 мм | AA75: =IF(G75="","",IF(G75="Л","Лист гофрокартона",IF(G75="КД","Крышка-дно",IF(G75="С","Самосборные",IF(G75="Ч","Четырехклапанные",IF(G75="А","Архивные","Неизвестно")))))) -> Самосборные | AB75: 1.73 | AC75: =IF(O75="","",IF(O75<=1,"0-1 литров",IF(O75<=3,"2-3 литра",IF(O75<=5,"4-5 литра",IF(O75<=7,"6-7 литра",IF(O75<=9,"8-9 литров",IF(O75<=14,"10-14 литров",IF(O75<=19,"15-19 литров",IF(O75<=29,"20-29 литров",IF(O75<=49,"30-49 литров",IF(O75<=59,"50-59 литров",IF(O75<=70,"60-69 литров",IF(O75<=79,"70-79 литров",IF(O75<=89,"80-89 литров",IF(O75<=99,"90-99 литров",IF(O75<=200,"100-200 литров","200+ литров")))))))))))))))) -> 8-9 литров
A76: 0.68 | B76: =A76*1.2 -> 0.816 | C76: 76 | D76: У | E76: 170х170х90 | G76: С | H76: 0427 | I76: В | J76: х | K76: K76 | N76: =IF(D76="","",IF(LEFT(D76,1)="0",0,1)) -> 1 | O76: =ROUND(R76*S76*T76/1000000,2) -> 2.6 | P76: =IF(O76="","", IF(O76<1,"0,1-0,9 литров", IF(O76<2,"1-1,9 литра", IF(O76<3,"2-2,9 литра", IF(O76<4,"3-3,9 литра", IF(O76<6,"4-5,9 литра",IF(O76<8,"6-7,9 литра",IF(O76<10,"8-9,9 литров",IF(O76<15,"10-14,9 литров",IF(O76<20,"15-19,9 литров",IF(O76<30,"20-29 литров",IF(O76<50,"30-49 литров",IF(O76<60,"50-59 литров",IF(O76<70,"60-69 литров",IF(O76<80,"70-79 литров",IF(O76<90,"80-89 литров",IF(O76<100,"90-99 литров",IF(O76<200,"100-200 литров","200+ литров")))))))))))))))))) -> 2-2,9 литра | Q76: =IF(O76="","",IF(O76<1,"<1 л",IF(O76<2,"1-2 л",IF(O76<3,"2-3 л",IF(O76<5,"3-5 л",IF(O76<10,"5-10 л",IF(O76<20,"10-20 л",IF(O76<50,"20-50 л",IF(O76<100,"50-100 л","100+ л"))))))))) -> 2-3 л | R76: =IF(E76="","",--LEFT(E76,FIND("х",E76)-1)) -> 170 | S76: =IF(E76="","",--MID(E76,FIND("х",E76)+1,FIND("х",E76,FIND("х",E76)+1)-FIND("х",E76)-1)) -> 170 | T76: =IF(E76="","",--RIGHT(E76,LEN(E76)-FIND("х",E76,FIND("х",E76)+1))) -> 90 | U76: =(2*(R76+S76)+60)*(S76+T76+8)/1000000 -> 0.19832 | V76: =IF(OR(AND(R76>=2*S76,R76>=2*T76),AND(S76>=2*R76,S76>=2*T76),AND(T76>=2*R76,T76>=2*S76)),"Длинные","") | W76: =IF(OR(AND(R76<=S76/2,R76<=T76/2),AND(S76<=R76/2,S76<=T76/2),AND(T76<=R76/2,T76<=S76/2)),"Плоские","") | X76: =IF(LARGE($R76:$T76,1)="","",IF(LARGE($R76:$T76,1)<=99,"10-99 мм",IF(LARGE($R76:$T76,1)<=199,"100-199 мм",IF(LARGE($R76:$T76,1)<=299,"200-299 мм",IF(LARGE($R76:$T76,1)<=399,"300-399 мм",IF(LARGE($R76:$T76,1)<=499,"400-499 мм",IF(LARGE($R76:$T76,1)<=599,"500-599 мм",IF(LARGE($R76:$T76,1)<=699,"600-699 мм",IF(LARGE($R76:$T76,1)<=999,"700-999 мм","1000+ мм"))))))))) -> 100-199 мм | Y76: =IF(LARGE($R76:$T76,2)="","",IF(LARGE($R76:$T76,2)<=99,"10-99 мм",IF(LARGE($R76:$T76,2)<=199,"100-199 мм",IF(LARGE($R76:$T76,2)<=299,"200-299 мм",IF(LARGE($R76:$T76,2)<=399,"300-399 мм",IF(LARGE($R76:$T76,2)<=499,"400-499 мм",IF(LARGE($R76:$T76,2)<=599,"500-599 мм",IF(LARGE($R76:$T76,2)<=699,"600-699 мм",IF(LARGE($R76:$T76,2)<=999,"700-999 мм","1000+ мм"))))))))) -> 100-199 мм | Z76: =IF(SMALL($R76:$T76,1)="","",IF(SMALL($R76:$T76,1)<=99,"10-99 мм",IF(SMALL($R76:$T76,1)<=199,"100-199 мм",IF(SMALL($R76:$T76,1)<=299,"200-299 мм",IF(SMALL($R76:$T76,1)<=399,"300-399 мм",IF(SMALL($R76:$T76,1)<=499,"400-499 мм",IF(SMALL($R76:$T76,1)<=599,"500-599 мм",IF(SMALL($R76:$T76,1)<=699,"600-699 мм",IF(SMALL($R76:$T76,1)<=999,"700-999 мм","1000+ мм"))))))))) -> 10-99 мм | AA76: =IF(G76="","",IF(G76="Л","Лист гофрокартона",IF(G76="КД","Крышка-дно",IF(G76="С","Самосборные",IF(G76="Ч","Четырехклапанные",IF(G76="А","Архивные","Неизвестно")))))) -> Самосборные | AB76: 1.73 | AC76: =IF(O76="","",IF(O76<=1,"0-1 литров",IF(O76<=3,"2-3 литра",IF(O76<=5,"4-5 литра",IF(O76<=7,"6-7 литра",IF(O76<=9,"8-9 литров",IF(O76<=14,"10-14 литров",IF(O76<=19,"15-19 литров",IF(O76<=29,"20-29 литров",IF(O76<=49,"30-49 литров",IF(O76<=59,"50-59 литров",IF(O76<=70,"60-69 литров",IF(O76<=79,"70-79 литров",IF(O76<=89,"80-89 литров",IF(O76<=99,"90-99 литров",IF(O76<=200,"100-200 литров","200+ литров")))))))))))))))) -> 2-3 литра
A77: 1.01 | B77: =A77*1.2 -> 1.212 | C77: 77 | D77: У | E77: 780х130х84 | G77: С | H77: 0421 | I77: Е | J77: х | K77: K77 | N77: =IF(D77="","",IF(LEFT(D77,1)="0",0,1)) -> 1 | O77: =ROUND(R77*S77*T77/1000000,2) -> 8.52 | P77: =IF(O77="","", IF(O77<1,"0,1-0,9 литров", IF(O77<2,"1-1,9 литра", IF(O77<3,"2-2,9 литра", IF(O77<4,"3-3,9 литра", IF(O77<6,"4-5,9 литра",IF(O77<8,"6-7,9 литра",IF(O77<10,"8-9,9 литров",IF(O77<15,"10-14,9 литров",IF(O77<20,"15-19,9 литров",IF(O77<30,"20-29 литров",IF(O77<50,"30-49 литров",IF(O77<60,"50-59 литров",IF(O77<70,"60-69 литров",IF(O77<80,"70-79 литров",IF(O77<90,"80-89 литров",IF(O77<100,"90-99 литров",IF(O77<200,"100-200 литров","200+ литров")))))))))))))))))) -> 8-9,9 литров | Q77: =IF(O77="","",IF(O77<1,"<1 л",IF(O77<2,"1-2 л",IF(O77<3,"2-3 л",IF(O77<5,"3-5 л",IF(O77<10,"5-10 л",IF(O77<20,"10-20 л",IF(O77<50,"20-50 л",IF(O77<100,"50-100 л","100+ л"))))))))) -> 5-10 л | R77: =IF(E77="","",--LEFT(E77,FIND("х",E77)-1)) -> 780 | S77: =IF(E77="","",--MID(E77,FIND("х",E77)+1,FIND("х",E77,FIND("х",E77)+1)-FIND("х",E77)-1)) -> 130 | T77: =IF(E77="","",--RIGHT(E77,LEN(E77)-FIND("х",E77,FIND("х",E77)+1))) -> 84 | U77: =(2*(R77+S77)+60)*(S77+T77+8)/1000000 -> 0.41736 | V77: =IF(OR(AND(R77>=2*S77,R77>=2*T77),AND(S77>=2*R77,S77>=2*T77),AND(T77>=2*R77,T77>=2*S77)),"Длинные","") -> Длинные | W77: =IF(OR(AND(R77<=S77/2,R77<=T77/2),AND(S77<=R77/2,S77<=T77/2),AND(T77<=R77/2,T77<=S77/2)),"Плоские","") | X77: =IF(LARGE($R77:$T77,1)="","",IF(LARGE($R77:$T77,1)<=99,"10-99 мм",IF(LARGE($R77:$T77,1)<=199,"100-199 мм",IF(LARGE($R77:$T77,1)<=299,"200-299 мм",IF(LARGE($R77:$T77,1)<=399,"300-399 мм",IF(LARGE($R77:$T77,1)<=499,"400-499 мм",IF(LARGE($R77:$T77,1)<=599,"500-599 мм",IF(LARGE($R77:$T77,1)<=699,"600-699 мм",IF(LARGE($R77:$T77,1)<=999,"700-999 мм","1000+ мм"))))))))) -> 700-999 мм | Y77: =IF(LARGE($R77:$T77,2)="","",IF(LARGE($R77:$T77,2)<=99,"10-99 мм",IF(LARGE($R77:$T77,2)<=199,"100-199 мм",IF(LARGE($R77:$T77,2)<=299,"200-299 мм",IF(LARGE($R77:$T77,2)<=399,"300-399 мм",IF(LARGE($R77:$T77,2)<=499,"400-499 мм",IF(LARGE($R77:$T77,2)<=599,"500-599 мм",IF(LARGE($R77:$T77,2)<=699,"600-699 мм",IF(LARGE($R77:$T77,2)<=999,"700-999 мм","1000+ мм"))))))))) -> 100-199 мм | Z77: =IF(SMALL($R77:$T77,1)="","",IF(SMALL($R77:$T77,1)<=99,"10-99 мм",IF(SMALL($R77:$T77,1)<=199,"100-199 мм",IF(SMALL($R77:$T77,1)<=299,"200-299 мм",IF(SMALL($R77:$T77,1)<=399,"300-399 мм",IF(SMALL($R77:$T77,1)<=499,"400-499 мм",IF(SMALL($R77:$T77,1)<=599,"500-599 мм",IF(SMALL($R77:$T77,1)<=699,"600-699 мм",IF(SMALL($R77:$T77,1)<=999,"700-999 мм","1000+ мм"))))))))) -> 10-99 мм | AA77: =IF(G77="","",IF(G77="Л","Лист гофрокартона",IF(G77="КД","Крышка-дно",IF(G77="С","Самосборные",IF(G77="Ч","Четырехклапанные",IF(G77="А","Архивные","Неизвестно")))))) -> Самосборные | AB77: 1.73 | AC77: =IF(O77="","",IF(O77<=1,"0-1 литров",IF(O77<=3,"2-3 литра",IF(O77<=5,"4-5 литра",IF(O77<=7,"6-7 литра",IF(O77<=9,"8-9 литров",IF(O77<=14,"10-14 литров",IF(O77<=19,"15-19 литров",IF(O77<=29,"20-29 литров",IF(O77<=49,"30-49 литров",IF(O77<=59,"50-59 литров",IF(O77<=70,"60-69 литров",IF(O77<=79,"70-79 литров",IF(O77<=89,"80-89 литров",IF(O77<=99,"90-99 литров",IF(O77<=200,"100-200 литров","200+ литров")))))))))))))))) -> 8-9 литров
... A148: 1.02 | B148: =A148*1.2 -> 1.224 | C148: 148 | D148: У | E148: 535х215х165 | G148: Ч | H148: х | I148: В | J148: х | K148: K149 | N148: =IF(D148="","",IF(LEFT(D148,1)="0",0,1)) -> 1 | O148: =ROUND(R148*S148*T148/1000000,2) -> 18.98 | P148: =IF(O148="","", IF(O148<1,"0,1-0,9 литров", IF(O148<2,"1-1,9 литра", IF(O148<3,"2-2,9 литра", IF(O148<4,"3-3,9 литра", IF(O148<6,"4-5,9 литра",IF(O148<8,"6-7,9 литра",IF(O148<10,"8-9,9 литров",IF(O148<15,"10-14,9 литров",IF(O148<20,"15-19,9 литров",IF(O148<30,"20-29 литров",IF(O148<50,"30-49 литров",IF(O148<60,"50-59 литров",IF(O148<70,"60-69 литров",IF(O148<80,"70-79 литров",IF(O148<90,"80-89 литров",IF(O148<100,"90-99 литров",IF(O148<200,"100-200 литров","200+ литров")))))))))))))))))) -> 15-19,9 литров | Q148: =IF(O148="","",IF(O148<1,"<1 л",IF(O148<2,"1-2 л",IF(O148<3,"2-3 л",IF(O148<5,"3-5 л",IF(O148<10,"5-10 л",IF(O148<20,"10-20 л",IF(O148<50,"20-50 л",IF(O148<100,"50-100 л","100+ л"))))))))) -> 10-20 л | R148: =IF(E148="","",--LEFT(E148,FIND("х",E148)-1)) -> 535 | S148: =IF(E148="","",--MID(E148,FIND("х",E148)+1,FIND("х",E148,FIND("х",E148)+1)-FIND("х",E148)-1)) -> 215 | T148: =IF(E148="","",--RIGHT(E148,LEN(E148)-FIND("х",E148,FIND("х",E148)+1))) -> 165 | U148: =(2*(R148+S148)+60)*(S148+T148+8)/1000000 -> 0.60528 | V148: =IF(OR(AND(R148>=2*S148,R148>=2*T148),AND(S148>=2*R148,S148>=2*T148),AND(T148>=2*R148,T148>=2*S148)),"Длинные","") -> Длинные | W148: =IF(OR(AND(R148<=S148/2,R148<=T148/2),AND(S148<=R148/2,S148<=T148/2),AND(T148<=R148/2,T148<=S148/2)),"Плоские","") | X148: =IF(LARGE($R148:$T148,1)="","",IF(LARGE($R148:$T148,1)<=99,"10-99 мм",IF(LARGE($R148:$T148,1)<=199,"100-199 мм",IF(LARGE($R148:$T148,1)<=299,"200-299 мм",IF(LARGE($R148:$T148,1)<=399,"300-399 мм",IF(LARGE($R148:$T148,1)<=499,"400-499 мм",IF(LARGE($R148:$T148,1)<=599,"500-599 мм",IF(LARGE($R148:$T148,1)<=699,"600-699 мм",IF(LARGE($R148:$T148,1)<=999,"700-999 мм","1000+ мм"))))))))) -> 500-599 мм | Y148: =IF(LARGE($R148:$T148,2)="","",IF(LARGE($R148:$T148,2)<=99,"10-99 мм",IF(LARGE($R148:$T148,2)<=199,"100-199 мм",IF(LARGE($R148:$T148,2)<=299,"200-299 мм",IF(LARGE($R148:$T148,2)<=399,"300-399 мм",IF(LARGE($R148:$T148,2)<=499,"400-499 мм",IF(LARGE($R148:$T148,2)<=599,"500-599 мм",IF(LARGE($R148:$T148,2)<=699,"600-699 мм",IF(LARGE($R148:$T148,2)<=999,"700-999 мм","1000+ мм"))))))))) -> 200-299 мм | Z148: =IF(SMALL($R148:$T148,1)="","",IF(SMALL($R148:$T148,1)<=99,"10-99 мм",IF(SMALL($R148:$T148,1)<=199,"100-199 мм",IF(SMALL($R148:$T148,1)<=299,"200-299 мм",IF(SMALL($R148:$T148,1)<=399,"300-399 мм",IF(SMALL($R148:$T148,1)<=499,"400-499 мм",IF(SMALL($R148:$T148,1)<=599,"500-599 мм",IF(SMALL($R148:$T148,1)<=699,"600-699 мм",IF(SMALL($R148:$T148,1)<=999,"700-999 мм","1000+ мм"))))))))) -> 100-199 мм | AA148: =IF(G148="","",IF(G148="Л","Лист гофрокартона",IF(G148="КД","Крышка-дно",IF(G148="С","Самосборные",IF(G148="Ч","Четырехклапанные",IF(G148="А","Архивные","Неизвестно")))))) -> Четырехклапанные | AB148: 1.73 | AC148: =IF(O148="","",IF(O148<=1,"0-1 литров",IF(O148<=3,"2-3 литра",IF(O148<=5,"4-5 литра",IF(O148<=7,"6-7 литра",IF(O148<=9,"8-9 литров",IF(O148<=14,"10-14 литров",IF(O148<=19,"15-19 литров",IF(O148<=29,"20-29 литров",IF(O148<=49,"30-49 литров",IF(O148<=59,"50-59 литров",IF(O148<=70,"60-69 литров",IF(O148<=79,"70-79 литров",IF(O148<=89,"80-89 литров",IF(O148<=99,"90-99 литров",IF(O148<=200,"100-200 литров","200+ литров")))))))))))))))) -> 15-19 литров
A149: 2.45 | B149: =A149*1.2 -> 2.94 | C149: 149 | D149: 0-У | E149: 560х360х390 | F149: После расспр БМ опять вернуть У | G149: Ч | H149: х | I149: В | J149: х | K149: K150 | N149: =IF(D149="","",IF(LEFT(D149,1)="0",0,1)) -> 0 | O149: =ROUND(R149*S149*T149/1000000,2) -> 78.62 | P149: =IF(O149="","", IF(O149<1,"0,1-0,9 литров", IF(O149<2,"1-1,9 литра", IF(O149<3,"2-2,9 литра", IF(O149<4,"3-3,9 литра", IF(O149<6,"4-5,9 литра",IF(O149<8,"6-7,9 литра",IF(O149<10,"8-9,9 литров",IF(O149<15,"10-14,9 литров",IF(O149<20,"15-19,9 литров",IF(O149<30,"20-29 литров",IF(O149<50,"30-49 литров",IF(O149<60,"50-59 литров",IF(O149<70,"60-69 литров",IF(O149<80,"70-79 литров",IF(O149<90,"80-89 литров",IF(O149<100,"90-99 литров",IF(O149<200,"100-200 литров","200+ литров")))))))))))))))))) -> 70-79 литров | Q149: =IF(O149="","",IF(O149<1,"<1 л",IF(O149<2,"1-2 л",IF(O149<3,"2-3 л",IF(O149<5,"3-5 л",IF(O149<10,"5-10 л",IF(O149<20,"10-20 л",IF(O149<50,"20-50 л",IF(O149<100,"50-100 л","100+ л"))))))))) -> 50-100 л | R149: =IF(E149="","",--LEFT(E149,FIND("х",E149)-1)) -> 560 | S149: =IF(E149="","",--MID(E149,FIND("х",E149)+1,FIND("х",E149,FIND("х",E149)+1)-FIND("х",E149)-1)) -> 360 | T149: =IF(E149="","",--RIGHT(E149,LEN(E149)-FIND("х",E149,FIND("х",E149)+1))) -> 390 | U149: =(2*(R149+S149)+60)*(S149+T149+8)/1000000 -> 1.4402 | V149: =IF(OR(AND(R149>=2*S149,R149>=2*T149),AND(S149>=2*R149,S149>=2*T149),AND(T149>=2*R149,T149>=2*S149)),"Длинные","") | W149: =IF(OR(AND(R149<=S149/2,R149<=T149/2),AND(S149<=R149/2,S149<=T149/2),AND(T149<=R149/2,T149<=S149/2)),"Плоские","") | X149: =IF(LARGE($R149:$T149,1)="","",IF(LARGE($R149:$T149,1)<=99,"10-99 мм",IF(LARGE($R149:$T149,1)<=199,"100-199 мм",IF(LARGE($R149:$T149,1)<=299,"200-299 мм",IF(LARGE($R149:$T149,1)<=399,"300-399 мм",IF(LARGE($R149:$T149,1)<=499,"400-499 мм",IF(LARGE($R149:$T149,1)<=599,"500-599 мм",IF(LARGE($R149:$T149,1)<=699,"600-699 мм",IF(LARGE($R149:$T149,1)<=999,"700-999 мм","1000+ мм"))))))))) -> 500-599 мм | Y149: =IF(LARGE($R149:$T149,2)="","",IF(LARGE($R149:$T149,2)<=99,"10-99 мм",IF(LARGE($R149:$T149,2)<=199,"100-199 мм",IF(LARGE($R149:$T149,2)<=299,"200-299 мм",IF(LARGE($R149:$T149,2)<=399,"300-399 мм",IF(LARGE($R149:$T149,2)<=499,"400-499 мм",IF(LARGE($R149:$T149,2)<=599,"500-599 мм",IF(LARGE($R149:$T149,2)<=699,"600-699 мм",IF(LARGE($R149:$T149,2)<=999,"700-999 мм","1000+ мм"))))))))) -> 300-399 мм | Z149: =IF(SMALL($R149:$T149,1)="","",IF(SMALL($R149:$T149,1)<=99,"10-99 мм",IF(SMALL($R149:$T149,1)<=199,"100-199 мм",IF(SMALL($R149:$T149,1)<=299,"200-299 мм",IF(SMALL($R149:$T149,1)<=399,"300-399 мм",IF(SMALL($R149:$T149,1)<=499,"400-499 мм",IF(SMALL($R149:$T149,1)<=599,"500-599 мм",IF(SMALL($R149:$T149,1)<=699,"600-699 мм",IF(SMALL($R149:$T149,1)<=999,"700-999 мм","1000+ мм"))))))))) -> 300-399 мм | AA149: =IF(G149="","",IF(G149="Л","Лист гофрокартона",IF(G149="КД","Крышка-дно",IF(G149="С","Самосборные",IF(G149="Ч","Четырехклапанные",IF(G149="А","Архивные","Неизвестно")))))) -> Четырехклапанные | AB149: 1.73 | AC149: =IF(O149="","",IF(O149<=1,"0-1 литров",IF(O149<=3,"2-3 литра",IF(O149<=5,"4-5 литра",IF(O149<=7,"6-7 литра",IF(O149<=9,"8-9 литров",IF(O149<=14,"10-14 литров",IF(O149<=19,"15-19 литров",IF(O149<=29,"20-29 литров",IF(O149<=49,"30-49 литров",IF(O149<=59,"50-59 литров",IF(O149<=70,"60-69 литров",IF(O149<=79,"70-79 литров",IF(O149<=89,"80-89 литров",IF(O149<=99,"90-99 литров",IF(O149<=200,"100-200 литров","200+ литров")))))))))))))))) -> 70-79 литров
A150: 0.82 | B150: =A150*1.2 -> 0.984 | C150: 150 | D150: У | E150: 340х265х110 | G150: Ч | H150: х | I150: В | J150: х | K150: K151 | N150: =IF(D150="","",IF(LEFT(D150,1)="0",0,1)) -> 1 | O150: =ROUND(R150*S150*T150/1000000,2) -> 9.91 | P150: =IF(O150="","", IF(O150<1,"0,1-0,9 литров", IF(O150<2,"1-1,9 литра", IF(O150<3,"2-2,9 литра", IF(O150<4,"3-3,9 литра", IF(O150<6,"4-5,9 литра",IF(O150<8,"6-7,9 литра",IF(O150<10,"8-9,9 литров",IF(O150<15,"10-14,9 литров",IF(O150<20,"15-19,9 литров",IF(O150<30,"20-29 литров",IF(O150<50,"30-49 литров",IF(O150<60,"50-59 литров",IF(O150<70,"60-69 литров",IF(O150<80,"70-79 литров",IF(O150<90,"80-89 литров",IF(O150<100,"90-99 литров",IF(O150<200,"100-200 литров","200+ литров")))))))))))))))))) -> 8-9,9 литров | Q150: =IF(O150="","",IF(O150<1,"<1 л",IF(O150<2,"1-2 л",IF(O150<3,"2-3 л",IF(O150<5,"3-5 л",IF(O150<10,"5-10 л",IF(O150<20,"10-20 л",IF(O150<50,"20-50 л",IF(O150<100,"50-100 л","100+ л"))))))))) -> 5-10 л | R150: =IF(E150="","",--LEFT(E150,FIND("х",E150)-1)) -> 340 | S150: =IF(E150="","",--MID(E150,FIND("х",E150)+1,FIND("х",E150,FIND("х",E150)+1)-FIND("х",E150)-1)) -> 265 | T150: =IF(E150="","",--RIGHT(E150,LEN(E150)-FIND("х",E150,FIND("х",E150)+1))) -> 110 | U150: =(2*(R150+S150)+60)*(S150+T150+8)/1000000 -> 0.48641 | V150: =IF(OR(AND(R150>=2*S150,R150>=2*T150),AND(S150>=2*R150,S150>=2*T150),AND(T150>=2*R150,T150>=2*S150)),"Длинные","") | W150: =IF(OR(AND(R150<=S150/2,R150<=T150/2),AND(S150<=R150/2,S150<=T150/2),AND(T150<=R150/2,T150<=S150/2)),"Плоские","") -> Плоские | X150: =IF(LARGE($R150:$T150,1)="","",IF(LARGE($R150:$T150,1)<=99,"10-99 мм",IF(LARGE($R150:$T150,1)<=199,"100-199 мм",IF(LARGE($R150:$T150,1)<=299,"200-299 мм",IF(LARGE($R150:$T150,1)<=399,"300-399 мм",IF(LARGE($R150:$T150,1)<=499,"400-499 мм",IF(LARGE($R150:$T150,1)<=599,"500-599 мм",IF(LARGE($R150:$T150,1)<=699,"600-699 мм",IF(LARGE($R150:$T150,1)<=999,"700-999 мм","1000+ мм"))))))))) -> 300-399 мм | Y150: =IF(LARGE($R150:$T150,2)="","",IF(LARGE($R150:$T150,2)<=99,"10-99 мм",IF(LARGE($R150:$T150,2)<=199,"100-199 мм",IF(LARGE($R150:$T150,2)<=299,"200-299 мм",IF(LARGE($R150:$T150,2)<=399,"300-399 мм",IF(LARGE($R150:$T150,2)<=499,"400-499 мм",IF(LARGE($R150:$T150,2)<=599,"500-599 мм",IF(LARGE($R150:$T150,2)<=699,"600-699 мм",IF(LARGE($R150:$T150,2)<=999,"700-999 мм","1000+ мм"))))))))) -> 200-299 мм | Z150: =IF(SMALL($R150:$T150,1)="","",IF(SMALL($R150:$T150,1)<=99,"10-99 мм",IF(SMALL($R150:$T150,1)<=199,"100-199 мм",IF(SMALL($R150:$T150,1)<=299,"200-299 мм",IF(SMALL($R150:$T150,1)<=399,"300-399 мм",IF(SMALL($R150:$T150,1)<=499,"400-499 мм",IF(SMALL($R150:$T150,1)<=599,"500-599 мм",IF(SMALL($R150:$T150,1)<=699,"600-699 мм",IF(SMALL($R150:$T150,1)<=999,"700-999 мм","1000+ мм"))))))))) -> 100-199 мм | AA150: =IF(G150="","",IF(G150="Л","Лист гофрокартона",IF(G150="КД","Крышка-дно",IF(G150="С","Самосборные",IF(G150="Ч","Четырехклапанные",IF(G150="А","Архивные","Неизвестно")))))) -> Четырехклапанные | AB150: 1.73 | AC150: =IF(O150="","",IF(O150<=1,"0-1 литров",IF(O150<=3,"2-3 литра",IF(O150<=5,"4-5 литра",IF(O150<=7,"6-7 литра",IF(O150<=9,"8-9 литров",IF(O150<=14,"10-14 литров",IF(O150<=19,"15-19 литров",IF(O150<=29,"20-29 литров",IF(O150<=49,"30-49 литров",IF(O150<=59,"50-59 литров",IF(O150<=70,"60-69 литров",IF(O150<=79,"70-79 литров",IF(O150<=89,"80-89 литров",IF(O150<=99,"90-99 литров",IF(O150<=200,"100-200 литров","200+ литров")))))))))))))))) -> 10-14 литров
A151: 0.16 | B151: =A151*1.2 -> 0.192 | C151: 151 | D151: У | E151: 160х80х80 | G151: Ч | H151: х | I151: В | J151: х | K151: K152 | N151: =IF(D151="","",IF(LEFT(D151,1)="0",0,1)) -> 1 | O151: =ROUND(R151*S151*T151/1000000,2) -> 1.02 | P151: =IF(O151="","", IF(O151<1,"0,1-0,9 литров", IF(O151<2,"1-1,9 литра", IF(O151<3,"2-2,9 литра", IF(O151<4,"3-3,9 литра", IF(O151<6,"4-5,9 литра",IF(O151<8,"6-7,9 литра",IF(O151<10,"8-9,9 литров",IF(O151<15,"10-14,9 литров",IF(O151<20,"15-19,9 литров",IF(O151<30,"20-29 литров",IF(O151<50,"30-49 литров",IF(O151<60,"50-59 литров",IF(O151<70,"60-69 литров",IF(O151<80,"70-79 литров",IF(O151<90,"80-89 литров",IF(O151<100,"90-99 литров",IF(O151<200,"100-200 литров","200+ литров")))))))))))))))))) -> 1-1,9 литра | Q151: =IF(O151="","",IF(O151<1,"<1 л",IF(O151<2,"1-2 л",IF(O151<3,"2-3 л",IF(O151<5,"3-5 л",IF(O151<10,"5-10 л",IF(O151<20,"10-20 л",IF(O151<50,"20-50 л",IF(O151<100,"50-100 л","100+ л"))))))))) -> 1-2 л | R151: =IF(E151="","",--LEFT(E151,FIND("х",E151)-1)) -> 160 | S151: =IF(E151="","",--MID(E151,FIND("х",E151)+1,FIND("х",E151,FIND("х",E151)+1)-FIND("х",E151)-1)) -> 80 | T151: =IF(E151="","",--RIGHT(E151,LEN(E151)-FIND("х",E151,FIND("х",E151)+1))) -> 80 | U151: =(2*(R151+S151)+60)*(S151+T151+8)/1000000 -> 0.09072 | V151: =IF(OR(AND(R151>=2*S151,R151>=2*T151),AND(S151>=2*R151,S151>=2*T151),AND(T151>=2*R151,T151>=2*S151)),"Длинные","") -> Длинные | W151: =IF(OR(AND(R151<=S151/2,R151<=T151/2),AND(S151<=R151/2,S151<=T151/2),AND(T151<=R151/2,T151<=S151/2)),"Плоские","") | X151: =IF(LARGE($R151:$T151,1)="","",IF(LARGE($R151:$T151,1)<=99,"10-99 мм",IF(LARGE($R151:$T151,1)<=199,"100-199 мм",IF(LARGE($R151:$T151,1)<=299,"200-299 мм",IF(LARGE($R151:$T151,1)<=399,"300-399 мм",IF(LARGE($R151:$T151,1)<=499,"400-499 мм",IF(LARGE($R151:$T151,1)<=599,"500-599 мм",IF(LARGE($R151:$T151,1)<=699,"600-699 мм",IF(LARGE($R151:$T151,1)<=999,"700-999 мм","1000+ мм"))))))))) -> 100-199 мм | Y151: =IF(LARGE($R151:$T151,2)="","",IF(LARGE($R151:$T151,2)<=99,"10-99 мм",IF(LARGE($R151:$T151,2)<=199,"100-199 мм",IF(LARGE($R151:$T151,2)<=299,"200-299 мм",IF(LARGE($R151:$T151,2)<=399,"300-399 мм",IF(LARGE($R151:$T151,2)<=499,"400-499 мм",IF(LARGE($R151:$T151,2)<=599,"500-599 мм",IF(LARGE($R151:$T151,2)<=699,"600-699 мм",IF(LARGE($R151:$T151,2)<=999,"700-999 мм","1000+ мм"))))))))) -> 10-99 мм | Z151: =IF(SMALL($R151:$T151,1)="","",IF(SMALL($R151:$T151,1)<=99,"10-99 мм",IF(SMALL($R151:$T151,1)<=199,"100-199 мм",IF(SMALL($R151:$T151,1)<=299,"200-299 мм",IF(SMALL($R151:$T151,1)<=399,"300-399 мм",IF(SMALL($R151:$T151,1)<=499,"400-499 мм",IF(SMALL($R151:$T151,1)<=599,"500-599 мм",IF(SMALL($R151:$T151,1)<=699,"600-699 мм",IF(SMALL($R151:$T151,1)<=999,"700-999 мм","1000+ мм"))))))))) -> 10-99 мм | AA151: =IF(G151="","",IF(G151="Л","Лист гофрокартона",IF(G151="КД","Крышка-дно",IF(G151="С","Самосборные",IF(G151="Ч","Четырехклапанные",IF(G151="А","Архивные","Неизвестно")))))) -> Четырехклапанные | AB151: 1.73 | AC151: =IF(O151="","",IF(O151<=1,"0-1 литров",IF(O151<=3,"2-3 литра",IF(O151<=5,"4-5 литра",IF(O151<=7,"6-7 литра",IF(O151<=9,"8-9 литров",IF(O151<=14,"10-14 литров",IF(O151<=19,"15-19 литров",IF(O151<=29,"20-29 литров",IF(O151<=49,"30-49 литров",IF(O151<=59,"50-59 литров",IF(O151<=70,"60-69 литров",IF(O151<=79,"70-79 литров",IF(O151<=89,"80-89 литров",IF(O151<=99,"90-99 литров",IF(O151<=200,"100-200 литров","200+ литров")))))))))))))))) -> 2-3 литра
A152: 1.75 | B152: =A152*1.2 -> 2.1 | C152: 152 | D152: У | E152: 370х370х290 | G152: Ч | H152: х | I152: В | J152: х | K152: K153 | N152: =IF(D152="","",IF(LEFT(D152,1)="0",0,1)) -> 1 | O152: =ROUND(R152*S152*T152/1000000,2) -> 39.7 | P152: =IF(O152="","", IF(O152<1,"0,1-0,9 литров", IF(O152<2,"1-1,9 литра", IF(O152<3,"2-2,9 литра", IF(O152<4,"3-3,9 литра", IF(O152<6,"4-5,9 литра",IF(O152<8,"6-7,9 литра",IF(O152<10,"8-9,9 литров",IF(O152<15,"10-14,9 литров",IF(O152<20,"15-19,9 литров",IF(O152<30,"20-29 литров",IF(O152<50,"30-49 литров",IF(O152<60,"50-59 литров",IF(O152<70,"60-69 литров",IF(O152<80,"70-79 литров",IF(O152<90,"80-89 литров",IF(O152<100,"90-99 литров",IF(O152<200,"100-200 литров","200+ литров")))))))))))))))))) -> 30-49 литров | Q152: =IF(O152="","",IF(O152<1,"<1 л",IF(O152<2,"1-2 л",IF(O152<3,"2-3 л",IF(O152<5,"3-5 л",IF(O152<10,"5-10 л",IF(O152<20,"10-20 л",IF(O152<50,"20-50 л",IF(O152<100,"50-100 л","100+ л"))))))))) -> 20-50 л | R152: =IF(E152="","",--LEFT(E152,FIND("х",E152)-1)) -> 370 | S152: =IF(E152="","",--MID(E152,FIND("х",E152)+1,FIND("х",E152,FIND("х",E152)+1)-FIND("х",E152)-1)) -> 370 | T152: =IF(E152="","",--RIGHT(E152,LEN(E152)-FIND("х",E152,FIND("х",E152)+1))) -> 290 | U152: =(2*(R152+S152)+60)*(S152+T152+8)/1000000 -> 1.02872 | V152: =IF(OR(AND(R152>=2*S152,R152>=2*T152),AND(S152>=2*R152,S152>=2*T152),AND(T152>=2*R152,T152>=2*S152)),"Длинные","") | W152: =IF(OR(AND(R152<=S152/2,R152<=T152/2),AND(S152<=R152/2,S152<=T152/2),AND(T152<=R152/2,T152<=S152/2)),"Плоские","") | X152: =IF(LARGE($R152:$T152,1)="","",IF(LARGE($R152:$T152,1)<=99,"10-99 мм",IF(LARGE($R152:$T152,1)<=199,"100-199 мм",IF(LARGE($R152:$T152,1)<=299,"200-299 мм",IF(LARGE($R152:$T152,1)<=399,"300-399 мм",IF(LARGE($R152:$T152,1)<=499,"400-499 мм",IF(LARGE($R152:$T152,1)<=599,"500-599 мм",IF(LARGE($R152:$T152,1)<=699,"600-699 мм",IF(LARGE($R152:$T152,1)<=999,"700-999 мм","1000+ мм"))))))))) -> 300-399 мм | Y152: =IF(LARGE($R152:$T152,2)="","",IF(LARGE($R152:$T152,2)<=99,"10-99 мм",IF(LARGE($R152:$T152,2)<=199,"100-199 мм",IF(LARGE($R152:$T152,2)<=299,"200-299 мм",IF(LARGE($R152:$T152,2)<=399,"300-399 мм",IF(LARGE($R152:$T152,2)<=499,"400-499 мм",IF(LARGE($R152:$T152,2)<=599,"500-599 мм",IF(LARGE($R152:$T152,2)<=699,"600-699 мм",IF(LARGE($R152:$T152,2)<=999,"700-999 мм","1000+ мм"))))))))) -> 300-399 мм | Z152: =IF(SMALL($R152:$T152,1)="","",IF(SMALL($R152:$T152,1)<=99,"10-99 мм",IF(SMALL($R152:$T152,1)<=199,"100-199 мм",IF(SMALL($R152:$T152,1)<=299,"200-299 мм",IF(SMALL($R152:$T152,1)<=399,"300-399 мм",IF(SMALL($R152:$T152,1)<=499,"400-499 мм",IF(SMALL($R152:$T152,1)<=599,"500-599 мм",IF(SMALL($R152:$T152,1)<=699,"600-699 мм",IF(SMALL($R152:$T152,1)<=999,"700-999 мм","1000+ мм"))))))))) -> 200-299 мм | AA152: =IF(G152="","",IF(G152="Л","Лист гофрокартона",IF(G152="КД","Крышка-дно",IF(G152="С","Самосборные",IF(G152="Ч","Четырехклапанные",IF(G152="А","Архивные","Неизвестно")))))) -> Четырехклапанные | AB152: 1.73 | AC152: =IF(O152="","",IF(O152<=1,"0-1 литров",IF(O152<=3,"2-3 литра",IF(O152<=5,"4-5 литра",IF(O152<=7,"6-7 литра",IF(O152<=9,"8-9 литров",IF(O152<=14,"10-14 литров",IF(O152<=19,"15-19 литров",IF(O152<=29,"20-29 литров",IF(O152<=49,"30-49 литров",IF(O152<=59,"50-59 литров",IF(O152<=70,"60-69 литров",IF(O152<=79,"70-79 литров",IF(O152<=89,"80-89 литров",IF(O152<=99,"90-99 литров",IF(O152<=200,"100-200 литров","200+ литров")))))))))))))))) -> 30-49 литров
A153: 0.68 | B153: =A153*1.2 -> 0.816 | C153: 153 | D153: У | E153: 240х240х150 | G153: Ч | H153: х | I153: В | J153: х | K153: K154 | N153: =IF(D153="","",IF(LEFT(D153,1)="0",0,1)) -> 1 | O153: =ROUND(R153*S153*T153/1000000,2) -> 8.64 | P153: =IF(O153="","", IF(O153<1,"0,1-0,9 литров", IF(O153<2,"1-1,9 литра", IF(O153<3,"2-2,9 литра", IF(O153<4,"3-3,9 литра", IF(O153<6,"4-5,9 литра",IF(O153<8,"6-7,9 литра",IF(O153<10,"8-9,9 литров",IF(O153<15,"10-14,9 литров",IF(O153<20,"15-19,9 литров",IF(O153<30,"20-29 литров",IF(O153<50,"30-49 литров",IF(O153<60,"50-59 литров",IF(O153<70,"60-69 литров",IF(O153<80,"70-79 литров",IF(O153<90,"80-89 литров",IF(O153<100,"90-99 литров",IF(O153<200,"100-200 литров","200+ литров")))))))))))))))))) -> 8-9,9 литров | Q153: =IF(O153="","",IF(O153<1,"<1 л",IF(O153<2,"1-2 л",IF(O153<3,"2-3 л",IF(O153<5,"3-5 л",IF(O153<10,"5-10 л",IF(O153<20,"10-20 л",IF(O153<50,"20-50 л",IF(O153<100,"50-100 л","100+ л"))))))))) -> 5-10 л | R153: =IF(E153="","",--LEFT(E153,FIND("х",E153)-1)) -> 240 | S153: =IF(E153="","",--MID(E153,FIND("х",E153)+1,FIND("х",E153,FIND("х",E153)+1)-FIND("х",E153)-1)) -> 240 | T153: =IF(E153="","",--RIGHT(E153,LEN(E153)-FIND("х",E153,FIND("х",E153)+1))) -> 150 | U153: =(2*(R153+S153)+60)*(S153+T153+8)/1000000 -> 0.40596 | V153: =IF(OR(AND(R153>=2*S153,R153>=2*T153),AND(S153>=2*R153,S153>=2*T153),AND(T153>=2*R153,T153>=2*S153)),"Длинные","") | W153: =IF(OR(AND(R153<=S153/2,R153<=T153/2),AND(S153<=R153/2,S153<=T153/2),AND(T153<=R153/2,T153<=S153/2)),"Плоские","") | X153: =IF(LARGE($R153:$T153,1)="","",IF(LARGE($R153:$T153,1)<=99,"10-99 мм",IF(LARGE($R153:$T153,1)<=199,"100-199 мм",IF(LARGE($R153:$T153,1)<=299,"200-299 мм",IF(LARGE($R153:$T153,1)<=399,"300-399 мм",IF(LARGE($R153:$T153,1)<=499,"400-499 мм",IF(LARGE($R153:$T153,1)<=599,"500-599 мм",IF(LARGE($R153:$T153,1)<=699,"600-699 мм",IF(LARGE($R153:$T153,1)<=999,"700-999 мм","1000+ мм"))))))))) -> 200-299 мм | Y153: =IF(LARGE($R153:$T153,2)="","",IF(LARGE($R153:$T153,2)<=99,"10-99 мм",IF(LARGE($R153:$T153,2)<=199,"100-199 мм",IF(LARGE($R153:$T153,2)<=299,"200-299 мм",IF(LARGE($R153:$T153,2)<=399,"300-399 мм",IF(LARGE($R153:$T153,2)<=499,"400-499 мм",IF(LARGE($R153:$T153,2)<=599,"500-599 мм",IF(LARGE($R153:$T153,2)<=699,"600-699 мм",IF(LARGE($R153:$T153,2)<=999,"700-999 мм","1000+ мм"))))))))) -> 200-299 мм | Z153: =IF(SMALL($R153:$T153,1)="","",IF(SMALL($R153:$T153,1)<=99,"10-99 мм",IF(SMALL($R153:$T153,1)<=199,"100-199 мм",IF(SMALL($R153:$T153,1)<=299,"200-299 мм",IF(SMALL($R153:$T153,1)<=399,"300-399 мм",IF(SMALL($R153:$T153,1)<=499,"400-499 мм",IF(SMALL($R153:$T153,1)<=599,"500-599 мм",IF(SMALL($R153:$T153,1)<=699,"600-699 мм",IF(SMALL($R153:$T153,1)<=999,"700-999 мм","1000+ мм"))))))))) -> 100-199 мм | AA153: =IF(G153="","",IF(G153="Л","Лист гофрокартона",IF(G153="КД","Крышка-дно",IF(G153="С","Самосборные",IF(G153="Ч","Четырехклапанные",IF(G153="А","Архивные","Неизвестно")))))) -> Четырехклапанные | AB153: 1.73 | AC153: =IF(O153="","",IF(O153<=1,"0-1 литров",IF(O153<=3,"2-3 литра",IF(O153<=5,"4-5 литра",IF(O153<=7,"6-7 литра",IF(O153<=9,"8-9 литров",IF(O153<=14,"10-14 литров",IF(O153<=19,"15-19 литров",IF(O153<=29,"20-29 литров",IF(O153<=49,"30-49 литров",IF(O153<=59,"50-59 литров",IF(O153<=70,"60-69 литров",IF(O153<=79,"70-79 литров",IF(O153<=89,"80-89 литров",IF(O153<=99,"90-99 литров",IF(O153<=200,"100-200 литров","200+ литров")))))))))))))))) -> 8-9 литров
